Workbook
Name N1360BZ1: NEW!$N$1361
Name U156B22: 'Export Lines'!$U$1562
Name C1348C2: NEW!$C$1349

Sheet NEW
A1: Order Number | B1: Column 2 | C1: Customer Info | D1: Type | E1: PU / DROP | F1: Production Deadline | G1: Delivery Date | H1: Delivery Conf. | I1: PU / DROP Confirmed | J1: METAL | K1: POWDER COAT | L1: DEKTON | M1: CUSHIONS | N1: CORTE | O1: SEW | P1: FILLING | Q1: FABRIC | R1: FOAM | S1: QTY CUSH | T1: QTY METAL | U1: QTY DEKT | V1: Proj. Hrs Cushion | W1: Proj. Hrs Metal | X1: Proj. Hrs Dekton | Y1: Covers | Z1: Umbrella | AA1: Tenjam/Others | AB1: Firepit System | AC1: Delivery Address | AD1: Column 30
A2: 1572 | B2: ORDER COMPLETED | C2: BETH COHEN | D2: RESIDENTIAL | F2: 46203 | G2: 46204 | H2: YES | J2: COMPLETED | K2: COMPLETED | L2: COMPLETED | M2: COMPLETED | N2: COMPLETED | O2: COMPLETED | P2: COMPLETED | Q2: RECEIVED | R2: RECEIVED | S2: 4 | U2: 1 | Y2: NOT REQUIRED | Z2: NOT REQUIRED | AA2: NOT REQUIRED | AB2: NOT REQUIRED | AC2: 10604 Arista Ln, Fountain Hills, AZ 85268, USA
A3: 1591 | B3: ORDER COMPLETED | C3: BRIAN BEVERLY BUFFINI | D3: RESIDENTIAL | F3: 46203 | G3: 46204 | H3: YES | J3: COMPLETED | K3: COMPLETED | L3: COMPLETED | M3: COMPLETED | N3: COMPLETED | O3: COMPLETED | P3: COMPLETED | Q3: RECEIVED | R3: RECEIVED | S3: 13 | U3: 6 | Y3: NOT REQUIRED | Z3: RECEIVED | AA3: NOT REQUIRED | AB3: NOT REQUIRED | AC3: CALIFORNIA
A4: 1593 | B4: ORDER COMPLETED | C4: JENNIFER LAABS | D4: RESIDENTIAL | F4: 46203 | G4: 46205 | H4: YES | J4: COMPLETED | K4: COMPLETED | L4: COMPLETED | M4: COMPLETED | N4: COMPLETED | O4: COMPLETED | P4: COMPLETED | Q4: RECEIVED | R4: RECEIVED | S4: 16 | U4: 6 | Y4: NOT REQUIRED | Z4: RECEIVED | AA4: NOT REQUIRED | AB4: RECEIVED | AC4: 484 Halcyon Pl, Bethel Island, CA 94511
A5: 1598 | B5: ORDER COMPLETED | C5: WARR-DAN MAYNARD | D5: WARRANTY | E5: 46203 | F5: 46203 | G5: 46203 | J5: NOT REQUIRED | K5: NOT REQUIRED | L5: NOT REQUIRED | M5: COMPLETED | N5: COMPLETED | O5: COMPLETED | P5: COMPLETED | Q5: RECEIVED | R5: SAME-NEED | S5: 25 | T5: 0 | U5: 0 | Y5: NOT REQUIRED | Z5: NOT REQUIRED | AA5: NOT REQUIRED | AB5: NOT REQUIRED | AC5: 20408 E Cloud Rd, Queen Creek, AZ 85142, USA
A6: 1622 | B6: ORDER COMPLETED | C6: MADONA KAKISH | D6: SERVICE | F6: 46203 | G6: 46205 | H6: YES | J6: NOT REQUIRED | K6: NOT REQUIRED | L6: NOT REQUIRED | M6: COMPLETED | N6: COMPLETED | O6: COMPLETED | P6: COMPLETED | Q6: RECEIVED | R6: NOT REQUIRED | S6: 1 | U6: 0 | Y6: NOT REQUIRED | Z6: NOT REQUIRED | AA6: NOT REQUIRED | AB6: NOT REQUIRED | AC6: CALIFORNIA
A7: 1639 | B7: READY FOR DELIVERY | C7: ROBYN LAUKIE-CHRIS PARK | D7: SERVICE-WARRANT | F7: 46204 | G7: 46204 | H7: NO | I7: NA | J7: COMPLETED | K7: COMPLETED | L7: COMPLETED | M7: COMPLETED | N7: COMPLETED | O7: COMPLETED | P7: COMPLETED | Q7: RECEIVED | R7: RECEIVED | S7: 1 | T7: 1 | U7: 1 | X7: 0 | Y7: NOT REQUIRED | Z7: NOT REQUIRED | AA7: NOT REQUIRED | AB7: NOT REQUIRED | AC7: 6352 Arroyo Rd, Cave Creek, AZ 85331, USA
A8: 1677 | B8: READY FOR DELIVERY | C8: TONY KURTH | D8: PICKUP | F8: 46204 | G8: 46204 | H8: NO | I8: NA | J8: NOT REQUIRED | K8: NOT REQUIRED | L8: NOT REQUIRED | M8: NOT REQUIRED | N8: NOT REQUIRED | O8: NOT REQUIRED | P8: NOT REQUIRED | Q8: NOT REQUIRED | R8: NOT REQUIRED | S8: 0 | T8: 0 | U8: 0 | V8: 0 | W8: 0 | X8: 0 | Y8: NOT REQUIRED | Z8: NOT REQUIRED | AA8: NOT REQUIRED | AB8: NOT REQUIRED | AC8: PICKUP
A9: 1688 | B9: NEW | C9: ERIC WHITTAKER | D9: COVERS | F9: 46204 | G9: 46204 | H9: NO | I9: NA | J9: NOT REQUIRED | K9: NOT REQUIRED | L9: NOT REQUIRED | M9: NOT REQUIRED | N9: NOT REQUIRED | O9: NOT REQUIRED | P9: NOT REQUIRED | Q9: NOT REQUIRED | R9: NOT REQUIRED | S9: 0 | T9: 0 | U9: 0 | V9: 0 | W9: 0 | X9: 0 | Y9: ORDERED | Z9: NOT REQUIRED | AA9: NOT REQUIRED | AB9: NOT REQUIRED | AC9: 5400 E Valle Vista Rd #6, Phoenix, AZ 85018
A10: 1715 | B10: ORDER COMPLETED | C10: JAIME KIM LIMBER | D10: SERVICE-WARRANT | E10: 46246 | F10: 46204 | G10: 46246 | H10: YES | I10: YES | J10: COMPLETED | K10: NOT REQUIRED | L10: NOT REQUIRED | M10: NOT REQUIRED | N10: NOT REQUIRED | O10: NOT REQUIRED | P10: NOT REQUIRED | Q10: NOT REQUIRED | R10: NOT REQUIRED | S10: 0 | T10: 2 | U10: 0 | V10: 0 | Y10: NOT REQUIRED | Z10: NOT REQUIRED | AA10: NOT REQUIRED | AB10: NOT REQUIRED | AC10: 4202 N 58th St PHOENIX AZ 85018
A11: 1627 | B11: ORDER COMPLETED | C11: BRITTANY MCDOWELL | D11: RESIDENTIAL | E11: 46233 | F11: 46204 | G11: 46204 | H11: YES | I11: YES | J11: NOT REQUIRED | K11: NOT REQUIRED | L11: NOT REQUIRED | M11: NOT REQUIRED | N11: NOT REQUIRED | O11: NOT REQUIRED | P11: NOT REQUIRED | Q11: NOT REQUIRED | R11: NOT REQUIRED | S11: 0 | U11: 0 | Y11: RECEIVED | Z11: NOT REQUIRED | AA11: NOT REQUIRED | AB11: NOT REQUIRED | AC11: 8404 N 75th St, Scottsdale, AZ 85258, USA
A12: 1708 | B12: ORDER COMPLETED | C12: ECHMEYER, KRISTINA & EVAN | D12: SERVICE-WARRANT | F12: 46204 | G12: 46204 | H12: NO | I12: NA | J12: NOT REQUIRED | K12: NOT REQUIRED | L12: NOT REQUIRED | M12: NOT REQUIRED | N12: NOT REQUIRED | O12: NOT REQUIRED | P12: NOT REQUIRED | Q12: NOT REQUIRED | R12: RECEIVED | S12: 0 | T12: 0 | U12: 0 | V12: 0 | W12: 0 | X12: 0 | Y12: NOT REQUIRED | Z12: NOT REQUIRED | AA12: NOT REQUIRED | AB12: NOT REQUIRED | AC12: 8321 Baseline Rd, Boulder, CO 80303, USA
A13: 1491 | B13: NEW | C13: KONA RE-DOING-GENCUSH | D13: COMMERCIAL | F13: 46204 | G13: 46204 | H13: NO | I13: NA | J13: NOT REQUIRED | K13: NOT REQUIRED | L13: NOT REQUIRED | M13: NOT STARTED | N13: NOT STARTED | O13: NOT STARTED | P13: NOT STARTED | Q13: NEED | R13: SAME NEED | S13: 20 | T13: 0 | U13: 0 | V13: 0 | W13: 0 | X13: 0 | Y13: NOT REQUIRED | Z13: NOT REQUIRED | AA13: NOT REQUIRED | AB13: NOT REQUIRED | AC13: 72-300 Maheawalu Drive, Kailua-Kona HI 96740
A14: 1662 | B14: ORDER COMPLETED | C14: KERYN GERBER | D14: SERVICE-WARRANT | E14: 46233 | F14: 46253 | G14: 46253 | H14: YES | I14: YES | J14: NOT REQUIRED | K14: COMPLETED | L14: NOT REQUIRED | M14: NOT REQUIRED | N14: NOT REQUIRED | O14: NOT REQUIRED | P14: NOT REQUIRED | Q14: NOT REQUIRED | R14: NOT REQUIRED | S14: 0 | T14: 1 | U14: 0 | V14: 0 | W14: 0.041666667 | X14: 0 | Y14: NOT REQUIRED | Z14: NOT REQUIRED | AA14: NOT REQUIRED | AB14: NOT REQUIRED | AC14: 4103 n 64th pl, Scottsdale, Arizona 85251
A15: 1663 | B15: ORDER COMPLETED | C15: DAVE MONTZ | D15: PICKUP | E15: 46212 | F15: 46204 | G15: 46204 | H15: NO | I15: YES | J15: NOT REQUIRED | K15: NOT REQUIRED | L15: NOT REQUIRED | M15: COMPLETED | N15: COMPLETED | O15: COMPLETED | P15: COMPLETED | Q15: RECEIVED | R15: SAME RECEIVED | S15: 1 | T15: 0 | U15: 0 | Y15: NOT REQUIRED | Z15: NOT REQUIRED | AA15: NOT REQUIRED | AB15: NOT REQUIRED | AC15: DROP & PICK AT FACTORY
A16: 1687 | B16: ORDER COMPLETED | C16: JEN BERGMAN | D16: SERVICE-WARRANT | F16: 46204 | G16: 46204 | H16: NO | I16: NA | J16: NOT REQUIRED | K16: NOT REQUIRED | L16: NOT REQUIRED | M16: COMPLETED | N16: COMPLETED | O16: COMPLETED | P16: COMPLETED | Q16: ON STOCK | R16: SAME RECEIVED | S16: 1 | T16: 0 | U16: 0 | Y16: NOT REQUIRED | Z16: NOT REQUIRED | AA16: NOT REQUIRED | AB16: NOT REQUIRED | AC16: 3386 S Stuart Ave, Gilbert, AZ 85297, USA
A17: 1702 | B17: ORDER COMPLETED | C17: JILL CUTRONE | D17: SERVICE-WARRANT | F17: 46204 | G17: 46204 | H17: NO | I17: NA | J17: NOT REQUIRED | K17: NOT REQUIRED | L17: COMPLETED | M17: NOT REQUIRED | N17: NOT REQUIRED | O17: NOT REQUIRED | P17: NOT REQUIRED | Q17: NOT REQUIRED | R17: NOT REQUIRED | Y17: NOT REQUIRED | Z17: NOT REQUIRED | AA17: NOT REQUIRED | AB17: NOT REQUIRED | AC17: 14762 N Strong Stone Dr, Oro Valley, AZ 85755, USA
A18: 1703 | B18: ORDER COMPLETED | C18: MIKE CHAFFEUR | D18: SERVICE-WARRANT | F18: 46204 | G18: 46204 | H18: NO | I18: NA | J18: NOT REQUIRED | K18: NOT REQUIRED | L18: NOT REQUIRED | M18: COMPLETED | N18: COMPLETED | O18: COMPLETED | P18: COMPLETED | Q18: NOT REQUIRED | R18: SAME RECEIVED | S18: 2 | Y18: NOT REQUIRED | Z18: NOT REQUIRED | AA18: NOT REQUIRED | AB18: NOT REQUIRED | AC18: 9431 N Solitude Canyon Fountain Hills AZ 85268
A19: 1696 | B19: ORDER COMPLETED | C19: LISA FORD | D19: SERVICE-WARRANT | F19: 46205 | G19: 46205 | H19: YES | I19: NA | J19: NOT REQUIRED | K19: NOT REQUIRED | L19: NOT REQUIRED | M19: COMPLETED | N19: COMPLETED | O19: COMPLETED | P19: COMPLETED | Q19: ON STOCK | R19: RECEIVED | S19: 1 | T19: 0 | U19: 0 | W19: 0 | X19: 0 | Y19: NOT REQUIRED | Z19: NOT REQUIRED | AA19: NOT REQUIRED | AB19: NOT REQUIRED | AC19: COLORADO
A20: 1704 | B20: ORDER COMPLETED | C20: LINDSAY MADERIA WALSH | D20: RESIDENTIAL | F20: 46205 | G20: 46205 | H20: YES | I20: NA | J20: NOT REQUIRED | K20: NOT REQUIRED | L20: NOT REQUIRED | M20: COMPLETED | N20: COMPLETED | O20: COMPLETED | P20: NOT REQUIRED | Q20: RECEIVED | R20: NOT REQUIRED | S20: 9 | T20: 0 | U20: 0 | W20: 0 | X20: 0 | Y20: NOT REQUIRED | Z20: NOT REQUIRED | AA20: NOT REQUIRED | AB20: NOT REQUIRED | AC20: 2055 Bear Hollow Dr, Park City, UT 84098, USA
A21: 1638 | B21: ORDER COMPLETED | C21: DIANE GALATI | D21: SERVICE | F21: 46209 | G21: 46210 | H21: YES | J21: NOT REQUIRED | K21: NOT REQUIRED | L21: IN PROGRESS | M21: NOT REQUIRED | N21: NOT REQUIRED | O21: NOT REQUIRED | P21: NOT REQUIRED | Q21: NOT REQUIRED | R21: NOT REQUIRED | S21: 0 | U21: 1 | Y21: NOT REQUIRED | Z21: NOT REQUIRED | AA21: NOT REQUIRED | AB21: NOT REQUIRED | AC21: 4939 E Horseshoe Rd, Paradise Valley, AZ 85253, USA
A22: 1605 | B22: ORDER COMPLETED | C22: DEANNE SPRENGER | D22: RESIDENTIAL | E22: 46212 | F22: 46210 | G22: 46210 | H22: YES | I22: YES | J22: NOT REQUIRED | K22: NOT REQUIRED | L22: NOT REQUIRED | M22: COMPLETED | N22: COMPLETED | O22: COMPLETED | P22: COMPLETED | Q22: NOT REQUIRED | R22: RECEIVED | S22: 1 | U22: 0 | Y22: NOT REQUIRED | Z22: NOT REQUIRED | AA22: NOT REQUIRED | AB22: NOT REQUIRED | AC22: 13452 E Desert Trail Scottsdale, AZ 85259
A23: 1643 | B23: ORDER COMPLETED | C23: MEGAN KELLY ADD-ON | D23: RESIDENTIAL | F23: 46210 | G23: 46211 | H23: YES | I23: NA | J23: COMPLETED | K23: COMPLETED | L23: COMPLETED | M23: COMPLETED | N23: COMPLETED | O23: COMPLETED | P23: COMPLETED | Q23: IN STOCK | R23: RECEIVED | S23: 5 | T23: 5 | U23: 0 | Y23: NOT REQUIRED | Z23: NOT REQUIRED | AA23: NOT REQUIRED | AB23: NOT REQUIRED | AC23: 10276 White Birch St, Presque Isle, MI 49777, USA
A24: 1521 | B24: ORDER COMPLETED | C24: RUSH SHOWROOM SWING CUSHION | D24: SHOWROOM SCOTTSDALE | F24: 46212 | G24: 46212 | H24: YES | I24: NA | J24: NOT REQUIRED | K24: NOT REQUIRED | L24: NOT REQUIRED | M24: COMPLETED | N24: COMPLETED | O24: COMPLETED | P24: COMPLETED | Q24: IN STOCK | R24: RECEIVED | S24: 1 | U24: 0 | Y24: NOT REQUIRED | Z24: NOT REQUIRED | AA24: NOT REQUIRED | AB24: NOT REQUIRED | AC24: 15037 N Scottsdale Rd Ste 120, Scottsdale, AZ 85254
A25: 1502 | B25: ORDER COMPLETED | C25: ROB ROY | D25: RESIDENTIAL | F25: 46217 | G25: 46218 | H25: YES | I25: NA | J25: COMPLETED | K25: COMPLETED | L25: COMPLETED | M25: COMPLETED | N25: COMPLETED | O25: COMPLETED | P25: COMPLETED | Q25: RECEIVED | R25: RECEIVED | S25: 18 | U25: 7 | Y25: NOT REQUIRED | Z25: NOT REQUIRED | AA25: NOT REQUIRED | AB25: NOT REQUIRED | AC25: CALIFORNIA
A26: 1573 | B26: ORDER COMPLETED | C26: SOLANA BEACH SHOWROOM 4-29 | D26: SHOWROOM | F26: 46217 | G26: 46218 | H26: YES | I26: NA | J26: COMPLETED | K26: COMPLETED | L26: NOT REQUIRED | M26: COMPLETED | N26: COMPLETED | O26: COMPLETED | P26: COMPLETED | Q26: RECEIVED | R26: RECEIVED | S26: 4 | U26: 0 | Y26: NOT REQUIRED | Z26: NOT REQUIRED | AA26: NOT REQUIRED | AB26: NOT REQUIRED | AC26: CALIFORNIA
A27: 1576 | B27: ORDER COMPLETED | C27: RICHARD AGUILAR | D27: RESIDENTIAL | F27: 46217 | G27: 46218 | H27: YES | I27: NA | J27: COMPLETED | K27: COMPLETED | L27: COMPLETED | M27: COMPLETED | N27: COMPLETED | O27: COMPLETED | P27: COMPLETED | Q27: RECEIVED | R27: RECEIVED | S27: 7 | U27: 3 | Y27: NOT REQUIRED | Z27: NOT REQUIRED | AA27: NOT REQUIRED | AB27: NOT REQUIRED | AC27: 5435 Calumet Ave, LA JOLLA, CA
A28: 1604 | B28: ORDER COMPLETED | C28: MELANIE SPAHN | D28: SERVICE | E28: 46218 | F28: 46217 | G28: 46218 | H28: YES | I28: YES | J28: NOT REQUIRED | K28: COMPLETED | L28: NOT REQUIRED | M28: NOT REQUIRED | N28: NOT REQUIRED | O28: NOT REQUIRED | P28: NOT REQUIRED | Q28: NOT REQUIRED | R28: NOT REQUIRED | S28: 0 | U28: 0 | Y28: NOT REQUIRED | Z28: NOT REQUIRED | AA28: NOT REQUIRED | AB28: NOT REQUIRED | AC28: 8621 E Clarendon Ave, Scottsdale, AZ 85251, USA
A29: 1610 | B29: ORDER COMPLETED | C29: PAUL DICOSMO-REDO | D29: REDOING | E29: 46211 | F29: 46217 | G29: 46217 | H29: YES | I29: YES | J29: NOT REQUIRED | K29: NOT REQUIRED | L29: COMPLETED | M29: COMPLETED | N29: COMPLETED | O29: COMPLETED | P29: COMPLETED | Q29: RECEIVED | R29: RECEIVED | S29: 2 | U29: 1 | Y29: RECEIVED | Z29: NOT REQUIRED | AA29: NOT REQUIRED | AB29: NOT REQUIRED | AC29: 18724 E Chandler Heights Rd, Queen Creek, AZ 85142, USA
A30: 1613 | B30: ORDER COMPLETED | C30: RAQUEL-JASON NORTON | D30: RESIDENTIAL | F30: 46217 | G30: 46218 | H30: YES | I30: NA | J30: COMPLETED | K30: COMPLETED | L30: NOT REQUIRED | M30: COMPLETED | N30: COMPLETED | O30: COMPLETED | P30: COMPLETED | Q30: RECEIVED | R30: RECEIVED | S30: 3 | T30: 3 | U30: 0 | Y30: NOT REQUIRED | Z30: NOT REQUIRED | AA30: NOT REQUIRED | AB30: NOT REQUIRED | AC30: CALIFORNIA
A31: 1614 | B31: ORDER COMPLETED | C31: BETH HOFFMAN | D31: RESIDENTIAL | F31: 46217 | G31: 46218 | H31: YES | I31: NA | J31: COMPLETED | K31: COMPLETED | L31: COMPLETED | M31: COMPLETED | N31: COMPLETED | O31: COMPLETED | P31: COMPLETED | Q31: RECEIVED | R31: RECEIVED | S31: 5 | U31: 4 | Y31: NOT REQUIRED | Z31: NOT REQUIRED | AA31: NOT REQUIRED | AB31: NOT REQUIRED | AC31: CALIFORNIA
A32: 1624 | B32: ORDER COMPLETED | C32: RAQUEL-JASON NORTON | D32: RESIDENTIAL | F32: 46217 | G32: 46218 | H32: YES | I32: NA | J32: COMPLETED | K32: COMPLETED | L32: COMPLETED | M32: NOT REQUIRED | N32: NOT REQUIRED | O32: NOT REQUIRED | P32: NOT REQUIRED | Q32: NOT REQUIRED | R32: NOT REQUIRED | S32: 0 | T32: 1 | U32: 0 | Y32: NOT REQUIRED | Z32: NOT REQUIRED | AA32: NOT REQUIRED | AB32: NOT REQUIRED | AC32: 1468 Rimcrest Ct, BONITA CA 91902
A33: 1651 | B33: ORDER COMPLETED | C33: CHAD | D33: SERVICE | E33: 46212 | F33: 46217 | G33: 46218 | H33: YES | I33: YES | J33: NOT REQUIRED | K33: COMPLETED | L33: COMPLETED | M33: NOT REQUIRED | N33: NOT REQUIRED | O33: NOT REQUIRED | P33: NOT REQUIRED | Q33: NOT REQUIRED | R33: NOT REQUIRED | Y33: NOT REQUIRED | Z33: NOT REQUIRED | AA33: NOT REQUIRED | AB33: NOT REQUIRED | AC33: 13260 N 83rd Pl SCOTTSDALE AZ 85260
A34: 1653 | B34: ORDER COMPLETED | C34: CA AMAR TAKHUR | D34: RESIDENTIAL | F34: 46217 | G34: 46219 | H34: YES | I34: NA | J34: NOT REQUIRED | K34: NOT REQUIRED | L34: COMPLETED | M34: NOT REQUIRED | N34: NOT REQUIRED | O34: NOT REQUIRED | P34: NOT REQUIRED | Q34: NOT REQUIRED | R34: NOT REQUIRED | S34: 0 | T34: 0 | U34: 1 | Y34: NOT REQUIRED | Z34: NOT REQUIRED | AA34: NOT REQUIRED | AB34: NOT REQUIRED | AC34: 304 N Sierra Ave, Solana Beach, CA 92075
A35: 1608 | B35: ORDER COMPLETED | C35: ANDREA SYDENHAM-SERVICE | D35: SERVICE | E35: 46202 | F35: 46218 | G35: 46219 | H35: YES | I35: YES | J35: NOT REQUIRED | K35: COMPLETED | L35: NOT REQUIRED | M35: NOT REQUIRED | N35: NOT REQUIRED | O35: NOT REQUIRED | P35: NOT REQUIRED | Q35: NOT REQUIRED | R35: NOT REQUIRED | S35: 0 | U35: 0 | Y35: NOT REQUIRED | Z35: NOT REQUIRED | AA35: NOT REQUIRED | AB35: NOT REQUIRED | AC35: 26814 Boulder Ln, Scottsdale, AZ 85255, USA
A36: 1617 | B36: ORDER COMPLETED | C36: REDO SHELLY GROTHAUS | D36: WARRANTY | E36: 46202 | F36: 46218 | G36: 46219 | H36: YES | I36: YES | J36: NOT REQUIRED | K36: NOT REQUIRED | L36: NOT REQUIRED | M36: COMPLETED | N36: COMPLETED | O36: COMPLETED | P36: COMPLETED | Q36: IN STOCK | R36: SAME-READY | S36: 2 | U36: 0 | Y36: NOT REQUIRED | Z36: NOT REQUIRED | AA36: NOT REQUIRED | AB36: NOT REQUIRED | AC36: 10801 E Happy Valley Rd, Scottsdale, AZ 85255, USA
A37: 1654 | B37: ORDER COMPLETED | C37: CA Edisoon Reynoso | D37: SERVICE | F37: 46218 | G37: 46219 | H37: YES | I37: NA | J37: NOT REQUIRED | K37: NOT REQUIRED | L37: NOT REQUIRED | M37: NOT REQUIRED | N37: NOT REQUIRED | O37: NOT REQUIRED | P37: NOT REQUIRED | Q37: NOT REQUIRED | R37: NOT REQUIRED | S37: 0 | T37: 0 | U37: 0 | Y37: NOT REQUIRED | Z37: NOT REQUIRED | AA37: NOT REQUIRED | AB37: NOT REQUIRED | AC37: 5986 Greensview Ct, RANCHO SANTA FE, CA 92067
A38: 1607 | B38: ORDER COMPLETED | C38: STEPHANIE EVERS-SERVICE | D38: SERVICE | E38: 46204 | F38: 46219 | G38: 46219 | H38: YES | I38: YES | J38: NOT REQUIRED | K38: COMPLETED | L38: NOT REQUIRED | M38: NOT REQUIRED | N38: NOT REQUIRED | O38: NOT REQUIRED | P38: NOT REQUIRED | Q38: NOT REQUIRED | R38: NOT REQUIRED | S38: 0 | U38: 0 | Y38: NOT REQUIRED | Z38: NOT REQUIRED | AA38: NOT REQUIRED | AB38: NOT REQUIRED | AC38: 5736 E Lowden Rd, Cave Creek, AZ 85331, USA
A39: 1669 | B39: ORDER COMPLETED | C39: HAMID SHOWROOM 7-17-26 | D39: COMMERCIAL | F39: 46219 | G39: 46219 | H39: YES | I39: NA | J39: COMPLETED | K39: COMPLETED | L39: COMPLETED | M39: COMPLETED | N39: COMPLETED | O39: COMPLETED | P39: COMPLETED | Q39: IN STOCK | R39: RECEIVED | S39: 8 | Y39: NOT REQUIRED | Z39: NOT REQUIRED | AA39: NOT REQUIRED | AB39: NOT REQUIRED | AC39: SCOTTSDALE SHOWROOM
A40: 1546 | B40: ORDER COMPLETED | C40: JIM-CAROL LAUB | D40: RESIDENTIAL | F40: 46223 | G40: 46225 | H40: YES | I40: NA | J40: COMPLETED | K40: COMPLETED | L40: COMPLETED | M40: COMPLETED | N40: COMPLETED | O40: COMPLETED | P40: COMPLETED | Q40: RECEIVED | R40: RECEIVED | S40: 19 | U40: 10 | Y40: NOT REQUIRED | Z40: RECEIVED | AA40: NOT REQUIRED | AB40: RECEIVED | AC40: 8745 North Lookout Lane, Park City, UT
A41: 1646 | B41: ORDER COMPLETED | C41: JOE REDMOND III | D41: RESIDENTIAL | F41: 46225 | G41: 46226 | H41: YES | I41: NA | J41: COMPLETED | K41: COMPLETED | L41: NOT REQUIRED | M41: COMPLETED | N41: COMPLETED | O41: COMPLETED | P41: COMPLETED | Q41: RECEIVED | R41: RECEIVED | S41: 6 | Y41: NOT REQUIRED | Z41: NOT REQUIRED | AA41: NOT REQUIRED | AB41: NOT REQUIRED | AC41: 5824 E SABDFORD ST MESA 85215
A42: 1626 | B42: ORDER COMPLETED | C42: ERIC WHITTAKER | D42: RESIDENTIAL | F42: 46226 | G42: 46227 | H42: YES | I42: NA | J42: COMPLETED | K42: COMPLETED | L42: COMPLETED | M42: COMPLETED | N42: COMPLETED | O42: COMPLETED | P42: COMPLETED | Q42: RECEIVED | R42: RECEIVED | S42: 62 | U42: 8 | Y42: NOT REQUIRED | Z42: NOT REQUIRED | AA42: NOT REQUIRED | AB42: NOT REQUIRED | AC42: 5400 E Valle Vista rd 85018
A43: 1623 | B43: ORDER COMPLETED | C43: DEBBIE KILIAN | D43: RESIDENTIAL | F43: 46227 | G43: 46230 | H43: YES | I43: NA | J43: COMPLETED | K43: COMPLETED | L43: COMPLETED | M43: COMPLETED | N43: COMPLETED | O43: COMPLETED | P43: COMPLETED | Q43: RECEIVED | R43: RECEIVED | S43: 28 | U43: 8 | Y43: RECEIVED | Z43: NOT REQUIRED | AA43: NOT REQUIRED | AB43: RECEIVED | AC43: 4208 Kettle Ridge Trail, SLINGER, WISCONSIN
A44: 1655 | B44: ORDER COMPLETED | C44: OPTIMA CHICAGO FINAL | D44: COMMERCIAL | F44: 46227 | G44: 46227 | H44: YES | I44: NA | J44: COMPLETED | K44: COMPLETED | L44: COMPLETED | M44: NOT REQUIRED | N44: NOT REQUIRED | O44: NOT REQUIRED | P44: NOT REQUIRED | Q44: NOT REQUIRED | R44: NOT REQUIRED | S44: 0 | Y44: NOT REQUIRED | Z44: RECEIVED | AA44: NOT REQUIRED | AB44: NOT REQUIRED | AC44: CHICAGO
A45: 1670 | B45: ORDER COMPLETED | C45: STEPHANIE LALLEY | D45: RESIDENTIAL | F45: 46227 | G45: 46226 | H45: YES | I45: NA | J45: COMPLETED | K45: COMPLETED | L45: COMPLETED | M45: NOT REQUIRED | N45: NOT REQUIRED | O45: NOT REQUIRED | P45: NOT REQUIRED | Q45: NOT REQUIRED | R45: NOT REQUIRED | S45: 0 | T45: 1 | Y45: NOT REQUIRED | Z45: NOT REQUIRED | AA45: NOT REQUIRED | AB45: NOT REQUIRED | AC45: 1000 Berkshire Ln N #11 Plymouth, MN 55441
A46: 1616 | B46: ORDER COMPLETED | C46: JILL CUTRONE | D46: RESIDENTIAL | F46: 46230 | G46: 46231 | H46: YES | I46: NA | J46: COMPLETED | K46: COMPLETED | L46: COMPLETED | M46: COMPLETED | N46: COMPLETED | O46: COMPLETED | P46: COMPLETED | Q46: RECEIVED | R46: RECEIVED | S46: 80 | T46: 30 | U46: 10 | V46: 3.6076389 | Y46: NOT REQUIRED | Z46: RECEIVED | AA46: RECEIVED | AB46: RECEIVED | AC46: 14762 N Strong Stone Dr Oro Valley, AZ 85755
A47: 1628 | B47: ORDER COMPLETED | C47: JOHN MARTELL | D47: RESIDENTIAL | F47: 46230 | G47: 46230 | H47: YES | I47: NA | J47: COMPLETED | K47: COMPLETED | L47: COMPLETED | M47: COMPLETED | N47: COMPLETED | O47: COMPLETED | P47: COMPLETED | Q47: RECEIVED | R47: RECEIVED | S47: 2 | U47: 2 | Y47: NOT REQUIRED | Z47: NOT REQUIRED | AA47: NOT REQUIRED | AB47: NOT REQUIRED | AC47: 7120 E kierland, Scottsdale AZ 85254 APT #705
A48: 1615 | B48: ORDER COMPLETED | C48: KORRENA GLEN | D48: RESIDENTIAL | F48: 46231 | G48: 46232 | H48: YES | I48: YES | J48: COMPLETED | K48: COMPLETED | L48: COMPLETED | M48: COMPLETED | N48: COMPLETED | O48: COMPLETED | P48: COMPLETED | Q48: RECEIVED | R48: RECEIVED | S48: 11 | U48: 4 | V48: 0.625 | Y48: RECEIVED | Z48: RECEIVED | AA48: NOT REQUIRED | AB48: RECEIVED | AC48: 8230 N. Mockinbird Ln Paradise valley AZ 85253
A49: 1634 | B49: ORDER COMPLETED | C49: NIKKI PERES | D49: SERVICE-WARRANT | E49: 46212 | F49: 46231 | G49: 46232 | H49: YES | I49: YES | J49: NOT REQUIRED | K49: NOT REQUIRED | L49: NOT REQUIRED | M49: COMPLETED | N49: COMPLETED | O49: COMPLETED | P49: COMPLETED | Q49: RECEIVED | R49: RECEIVED | S49: 4 | U49: 0 | V49: 0.20833333 | Y49: NOT REQUIRED | Z49: NOT REQUIRED | AA49: NOT REQUIRED | AB49: NOT REQUIRED | AC49: DROP & PICK FROM FACTORY
A50: 1656 | B50: ORDER COMPLETED | C50: LINDA SALKOW | D50: RESIDENTIAL | F50: 46231 | G50: 46232 | H50: YES | I50: YES | J50: COMPLETED | K50: COMPLETED | L50: COMPLETED | M50: COMPLETED | N50: COMPLETED | O50: COMPLETED | P50: COMPLETED | Q50: RECEIVED | R50: RECEIVED | S50: 4 | T50: 5 | U50: 1 | V50: 0.041666667 | Y50: NOT REQUIRED | Z50: NOT REQUIRED | AA50: NOT REQUIRED | AB50: NOT REQUIRED | AC50: 10330 E Nolina Trail, Scottsdale, AZ
A51: 1660 | B51: ORDER COMPLETED | C51: NIKKI PERES - HUNTER T TABLES | D51: RESIDENTIAL | F51: 46231 | G51: 46232 | H51: YES | I51: YES | J51: COMPLETED | K51: COMPLETED | L51: COMPLETED | M51: NOT REQUIRED | N51: NOT REQUIRED | O51: NOT REQUIRED | P51: NOT REQUIRED | Q51: NOT REQUIRED | R51: NOT REQUIRED | S51: 0 | Y51: NOT REQUIRED | Z51: NOT REQUIRED | AA51: NOT REQUIRED | AB51: NOT REQUIRED | AC51: 8980 East Raintree Drive, Suite 100 Scottsdale, Az 85260
A52: 1620 | B52: ORDER COMPLETED | C52: JENNIFER JOHNSON | D52: SERVICE-WARRANT | E52: 46233 | F52: 46232 | G52: 46233 | H52: YES | I52: YES | J52: NOT REQUIRED | K52: NOT REQUIRED | L52: NOT REQUIRED | M52: COMPLETED | N52: COMPLETED | O52: COMPLETED | P52: COMPLETED | Q52: RECEIVED | R52: SAME RECEIVED | S52: 2 | U52: 0 | Y52: RECEIVED | Z52: NOT REQUIRED | AA52: NOT REQUIRED | AB52: NOT REQUIRED | AC52: 2666 E Raven Way, Gilbert, AZ 85297, USA
A53: 1631 | B53: ORDER COMPLETED | C53: JEN BERGMAN | D53: SERVICE-WARRANT | E53: 46217 | F53: 46232 | G53: 46233 | H53: YES | I53: YES | J53: NOT REQUIRED | K53: NOT REQUIRED | L53: NOT REQUIRED | M53: COMPLETED | N53: COMPLETED | O53: COMPLETED | P53: COMPLETED | Q53: RECEIVED | R53: SAME RECEIVED | S53: 39 | U53: 0 | V53: 1.3958333 | Y53: NOT REQUIRED | Z53: NOT REQUIRED | AA53: NOT REQUIRED | AB53: NOT REQUIRED | AC53: 3386 S Stuart Ave, Gilbert, AZ 85297, USA
A54: 1618 | B54: ORDER COMPLETED | C54: MIKE CHAFFEUR | D54: RESIDENTIAL | F54: 46233 | G54: 46237 | H54: YES | I54: NA | J54: COMPLETED | K54: COMPLETED | L54: COMPLETED | M54: COMPLETED | N54: COMPLETED | O54: COMPLETED | P54: COMPLETED | Q54: RECEIVED | R54: RECEIVED | S54: 37 | T54: 22 | U54: 7 | V54: 1.21875 | Y54: NOT REQUIRED | Z54: NOT REQUIRED | AA54: NOT REQUIRED | AB54: NOT REQUIRED | AC54: 9431 N Solitude Canyon, Fountain Hills AZ 85268
A55: 1606 | B55: ORDER COMPLETED | C55: CORINA COVACIU-SERVICE | D55: SERVICE | E55: 46209 | F55: 46234 | G55: 46224 | H55: NO | I55: YES | J55: NOT REQUIRED | K55: COMPLETED | L55: NOT REQUIRED | M55: NOT REQUIRED | N55: NOT REQUIRED | O55: NOT REQUIRED | P55: NOT REQUIRED | Q55: NOT REQUIRED | R55: NOT REQUIRED | S55: 0 | U55: 0 | Y55: NOT REQUIRED | Z55: NOT REQUIRED | AA55: NOT REQUIRED | AB55: NOT REQUIRED | AC55: 7936 W Villa Chula, Peoria, AZ 85383, USA
A56: 1619 | B56: ORDER COMPLETED | C56: LISA FORD | D56: RESIDENTIAL | F56: 46234 | G56: 46235 | H56: YES | I56: NA | J56: COMPLETED | K56: COMPLETED | L56: NOT REQUIRED | M56: COMPLETED | N56: COMPLETED | O56: COMPLETED | P56: COMPLETED | Q56: RECEIVED | R56: RECEIVED | S56: 13 | T56: 3 | U56: 0 | Y56: NOT REQUIRED | Z56: NOT REQUIRED | AA56: NOT REQUIRED | AB56: NOT REQUIRED | AC56: 2260 Bear Hollow Dr. PARK CITY, UTAH
A57: 1633 | B57: ORDER COMPLETED | C57: KIRK JOHNS | D57: CUSTOM | F57: 46234 | G57: 46235 | H57: YES | I57: NA | J57: COMPLETED | K57: COMPLETED | L57: NOT REQUIRED | M57: COMPLETED | N57: COMPLETED | O57: COMPLETED | P57: COMPLETED | Q57: RECEIVED | R57: RECEIVED | S57: 2 | T57: 1 | U57: 0 | V57: 0.60416667 | Y57: NOT REQUIRED | Z57: RECEIVED | AA57: NOT REQUIRED | AB57: NOT REQUIRED | AC57: 3418 Seneca Dr. Las Vegas, NV 89169
A58: 1647 | B58: ORDER COMPLETED | C58: LINDSAY MADERIA WALSH | D58: RESIDENTIAL | F58: 46234 | G58: 46235 | H58: YES | I58: NA | J58: COMPLETED | K58: COMPLETED | L58: NOT REQUIRED | M58: COMPLETED | N58: COMPLETED | O58: COMPLETED | P58: COMPLETED | Q58: RECEIVED | R58: RECEIVED | S58: 9 | T58: 2 | Y58: NOT REQUIRED | Z58: NOT REQUIRED | AA58: NOT REQUIRED | AB58: NOT REQUIRED | AC58: 2055 Bear Hollow Drive, PC 84098 PARK CITY UTAH
A59: 1648 | B59: ORDER COMPLETED | C59: MELISSA FISCHER | D59: RESIDENTIAL | F59: 46234 | G59: 46235 | H59: YES | I59: NA | J59: COMPLETED | K59: COMPLETED | L59: NOT REQUIRED | M59: COMPLETED | N59: COMPLETED | O59: COMPLETED | P59: COMPLETED | Q59: RECEIVED | R59: RECEIVED | S59: 5 | T59: 1 | Y59: NOT REQUIRED | Z59: NOT REQUIRED | AA59: NOT REQUIRED | AB59: NOT REQUIRED | AC59: 201 White Pine Canyon Road, Park City UT 84060
A60: 1671 | B60: ORDER COMPLETED | C60: CAROL LAUB RUSH | D60: RESIDENTIAL | F60: 46234 | G60: 46235 | H60: YES | I60: NA | J60: COMPLETED | K60: COMPLETED | L60: COMPLETED | M60: COMPLETED | N60: COMPLETED | O60: COMPLETED | P60: COMPLETED | Q60: RECEIVED | R60: RECEIVED | S60: 12 | T60: 5 | V60: 0.27777778 | Y60: NOT REQUIRED | Z60: NOT REQUIRED | AA60: NOT REQUIRED | AB60: NOT REQUIRED | AC60: 8745 North Lookout Lane, Park City, UT
A61: 1683 | B61: ORDER COMPLETED | C61: CAROL LAUB RUSH | D61: SERVICE-WARRANT | F61: 46234 | G61: 46234 | H61: YES | I61: NA | J61: COMPLETED | K61: COMPLETED | L61: COMPLETED | M61: NOT REQUIRED | N61: NOT REQUIRED | O61: NOT REQUIRED | P61: NOT REQUIRED | Q61: NOT REQUIRED | R61: NOT REQUIRED | S61: 0 | T61: 1 | Y61: NOT REQUIRED | Z61: NOT REQUIRED | AA61: NOT REQUIRED | AB61: RECEIVED | AC61: 8745 North Lookout Lane, Park City, UT
A62: 1637 | B62: ORDER COMPLETED | C62: DENISE STEINKIRCHNER | D62: CUSTOM | F62: 46237 | G62: 46237 | H62: YES | I62: NA | J62: COMPLETED | K62: COMPLETED | L62: COMPLETED | M62: COMPLETED | N62: COMPLETED | O62: COMPLETED | P62: COMPLETED | Q62: RECEIVED | R62: RECEIVED | S62: 1 | T62: 1 | U62: 1 | V62: 0.375 | Y62: SHIPPED | Z62: RECEIVED | AA62: NOT REQUIRED | AB62: NOT REQUIRED | AC62: 293 Canterwood Lane Wexford, PA 15090
A63: 1664 | B63: ORDER COMPLETED | C63: TONY SCHINDLER | D63: RESIDENTIAL | F63: 46237 | G63: 46238 | H63: YES | I63: NA | J63: COMPLETED | K63: COMPLETED | L63: NOT REQUIRED | M63: NOT REQUIRED | N63: NOT REQUIRED | O63: NOT REQUIRED | P63: NOT REQUIRED | Q63: NOT REQUIRED | R63: NOT REQUIRED | S63: 0 | T63: 1 | Y63: NOT REQUIRED | Z63: NOT REQUIRED | AA63: NOT REQUIRED | AB63: NOT REQUIRED | AC63: 37702 N. Schoolhouse Rd CAVE CREEK AZ
A64: 1689 | B64: ORDER COMPLETED | C64: KIRK JOHNS | D64: COVERS | F64: 46237 | G64: 46237 | H64: YES | I64: NA | J64: NOT REQUIRED | K64: NOT REQUIRED | L64: NOT REQUIRED | M64: NOT REQUIRED | N64: NOT REQUIRED | O64: NOT REQUIRED | P64: NOT REQUIRED | Q64: NOT REQUIRED | R64: NOT REQUIRED | S64: 0 | T64: 0 | U64: 0 | Y64: NEED | Z64: NOT REQUIRED | AA64: NOT REQUIRED | AB64: NOT REQUIRED | AC64: 3418 Seneca Dr. Las Vegas, NV 89169 | AD64: NOT REQUIRED
A65: 1583 | B65: ORDER COMPLETED | C65: MELANIE DEPATIE WARRANTY | D65: SERVICE-WARRANT | E65: 46195 | F65: 46238 | G65: 46239 | H65: YES | I65: YES | J65: COMPLETED | K65: COMPLETED | L65: NOT REQUIRED | M65: COMPLETED | N65: COMPLETED | O65: COMPLETED | P65: COMPLETED | Q65: RECEIVED | R65: SAME RECEIVED | S65: 13 | T65: 0 | U65: 0 | Y65: NOT REQUIRED | Z65: NOT REQUIRED | AA65: NOT REQUIRED | AB65: NOT REQUIRED | AC65: 5879 E Onyx Ave, SCOTTSDALE, AZ
A66: 1583 | B66: ORDER COMPLETED | C66: MELANIE DEPATIE NEW SECTION | D66: RESIDENTIAL | F66: 46238 | G66: 46239 | H66: YES | I66: NA | J66: COMPLETED | K66: COMPLETED | L66: COMPLETED | M66: COMPLETED | N66: COMPLETED | O66: COMPLETED | P66: COMPLETED | Q66: RECEIVED | R66: RECEIVED | S66: 14 | T66: 4 | U66: 3 | V66: 0.49652778 | Y66: NOT REQUIRED | Z66: NOT REQUIRED | AA66: NOT REQUIRED | AB66: NOT REQUIRED | AC66: 5879 E Onyx Ave, SCOTTSDALE, AZ
A67: 1642 | B67: ORDER COMPLETED | C67: CATHY-JIM SURRAT | D67: CUSTOM | F67: 46239 | G67: 46240 | H67: YES | I67: NA | J67: COMPLETED | K67: COMPLETED | L67: NOT REQUIRED | M67: COMPLETED | N67: COMPLETED | O67: COMPLETED | P67: COMPLETED | Q67: RECEIVED | R67: RECEIVED | S67: 5 | Y67: NOT REQUIRED | Z67: NOT REQUIRED | AA67: NOT REQUIRED | AB67: NOT REQUIRED | AC67: 14347 E THOROUGHBRED TRAIL, SCOTTSDALE AZ 85259
A68: 1661 | B68: ORDER COMPLETED | C68: PERKINS COIE LLP-WARRANTY | D68: SERVICE-WARRANT | E68: 46231 | F68: 46239 | G68: 46240 | H68: YES | I68: YES | J68: NOT REQUIRED | K68: NOT REQUIRED | L68: NOT REQUIRED | M68: COMPLETED | N68: COMPLETED | O68: COMPLETED | P68: COMPLETED | Q68: ON STOCK | R68: SAME RECEIVED | S68: 4 | Y68: NOT REQUIRED | Z68: NOT REQUIRED | AA68: NOT REQUIRED | AB68: NOT REQUIRED | AC68: 2525 E Camelback Rd suite 500, Phoenix, AZ 85016, USA
A69: 1705 | B69: ORDER COMPLETED | C69: JOHN MARTELL REDO | D69: RESIDENTIAL | F69: 46239 | G69: 46239 | H69: YES | I69: NA | J69: NOT REQUIRED | K69: NOT REQUIRED | L69: COMPLETED | M69: NOT REQUIRED | N69: NOT REQUIRED | O69: NOT REQUIRED | P69: NOT REQUIRED | Q69: NOT REQUIRED | R69: NOT REQUIRED | Y69: NOT REQUIRED | Z69: NOT REQUIRED | AA69: NOT REQUIRED | AB69: NOT REQUIRED | AC69: DROP OFF AT SCOTTSDALE SHOWROOM
A70: 1698 | B70: ORDER COMPLETED | C70: OPTIMA 7220 BARSTOOL REUPHOLSTERY | D70: COMMERCIAL | E70: 46244 | F70: 46244 | G70: 46244 | H70: YES | I70: YES | J70: NOT REQUIRED | K70: NOT REQUIRED | L70: NOT REQUIRED | M70: COMPLETED | N70: COMPLETED | O70: COMPLETED | P70: COMPLETED | Q70: RECEIVED | R70: SAME RECEIVED | S70: 12 | Y70: NOT REQUIRED | Z70: NOT REQUIRED | AA70: NOT REQUIRED | AB70: NOT REQUIRED | AC70: OPTIMA 7220
A71: 1713 | B71: ORDER COMPLETED | C71: OPTIMA 7220 RUSH DOWNSTAIRS | D71: COMMERCIAL | E71: 46244 | F71: 46244 | G71: 46244 | H71: YES | I71: YES | J71: NOT REQUIRED | K71: NOT REQUIRED | L71: NOT REQUIRED | M71: COMPLETED | N71: COMPLETED | O71: COMPLETED | P71: IN PROGRESS | Q71: ON STOCK | R71: SAME RECEIVED | S71: 49 | T71: 0 | U71: 0 | V71: 2.2958333 | Y71: NOT REQUIRED | Z71: NOT REQUIRED | AA71: NOT REQUIRED | AB71: NOT REQUIRED
A72: 1657 | B72: ORDER COMPLETED | C72: TIFFANY HERTER | D72: RESIDENTIAL | E72: 46246 | F72: 46245 | G72: 46246 | H72: YES | I72: YES | J72: COMPLETED | K72: COMPLETED | L72: COMPLETED | M72: COMPLETED | N72: COMPLETED | O72: COMPLETED | P72: COMPLETED | Q72: RECEIVED | R72: RECEIVED | S72: 34 | T72: 13 | U72: 7 | Y72: NOT REQUIRED | Z72: NOT REQUIRED | AA72: NOT REQUIRED | AB72: NOT REQUIRED | AC72: 28119 N. 109th Way
A73: 1684 | B73: ORDER COMPLETED | C73: OPTIMA 7140 FRAMES PHASE I | D73: SERVICE-WARRANT | E73: 46240 | F73: 46245 | G73: 46245 | H73: YES | I73: YES | J73: NOT REQUIRED | K73: COMPLETED | L73: NOT REQUIRED | M73: NOT REQUIRED | N73: NOT REQUIRED | O73: NOT REQUIRED | P73: NOT REQUIRED | Q73: NOT REQUIRED | R73: NOT REQUIRED | S73: 0 | U73: 0 | Y73: NOT REQUIRED | Z73: NOT REQUIRED | AA73: NOT REQUIRED | AB73: NOT REQUIRED | AC73: OPTIMA 7140
A74: 1641 | B74: ORDER COMPLETED | C74: DEBBIE BATTISTA | D74: RESIDENTIAL | F74: 46246 | G74: 46247 | H74: YES | I74: NA | J74: COMPLETED | K74: COMPLETED | L74: COMPLETED | M74: COMPLETED | N74: COMPLETED | O74: COMPLETED | P74: COMPLETED | Q74: RECEIVED | R74: RECEIVED | S74: 1 | T74: 3 | U74: 2 | X74: 0 | Y74: RECEIVED | Z74: NOT REQUIRED | AA74: NOT REQUIRED | AB74: NOT REQUIRED | AC74: 1175 E. Copper Hollow Way, Queen Creek, AZ 85740
A75: 1650 | B75: ORDER COMPLETED | C75: CAROL COLOMBO | D75: RESIDENTIAL | F75: 46246 | G75: 46247 | H75: YES | I75: NA | J75: COMPLETED | K75: COMPLETED | L75: COMPLETED | M75: COMPLETED | N75: COMPLETED | O75: COMPLETED | P75: COMPLETED | Q75: RECEIVED | R75: RECEIVED | S75: 12 | T75: 6 | U75: 3 | X75: 0 | Y75: NOT REQUIRED | Z75: NOT REQUIRED | AA75: NOT REQUIRED | AB75: NOT REQUIRED | AC75: 5633 N. Royal Circle, Paradise Valley, AZ
A76: 1684 | B76: ORDER COMPLETED | C76: OPTIMA 7140 FRAMES PHASE II | D76: SERVICE-WARRANT | E76: 46245 | F76: 46248 | G76: 46248 | H76: YES | I76: YES | J76: NOT REQUIRED | K76: COMPLETED | L76: NOT REQUIRED | M76: NOT REQUIRED | N76: NOT REQUIRED | O76: NOT REQUIRED | P76: NOT REQUIRED | Q76: NOT REQUIRED | R76: NOT REQUIRED | S76: 0 | T76: 47 | U76: 0 | V76: 0 | W76: 0.65277778 | X76: 0 | Y76: NOT REQUIRED | Z76: NOT REQUIRED | AA76: NOT REQUIRED | AB76: NOT REQUIRED | AC76: OPTIMA 7140
A77: 1714 | B77: ORDER COMPLETED | C77: CHERYL BURK | D77: RESIDENTIAL | F77: 46253 | G77: 46253 | H77: YES | I77: NA | J77: NOT REQUIRED | K77: NOT REQUIRED | L77: COMPLETED | M77: NOT REQUIRED | N77: NOT REQUIRED | O77: NOT REQUIRED | P77: NOT REQUIRED | Q77: NOT REQUIRED | R77: NOT REQUIRED | S77: 0 | T77: 0 | U77: 1 | V77: 0 | W77: 0 | X77: 0.041666667 | Y77: NOT REQUIRED | Z77: NOT REQUIRED | AA77: NOT REQUIRED | AB77: NOT REQUIRED | AC77: SCOTTSDALE SHOWROOM
A78: 1684 | B78: NEW | C78: OPTIMA 7140 PHASE III | D78: SERVICE-WARRANT | E78: 46254 | F78: 46254 | G78: 46253 | H78: YES | I78: YES | J78: NOT REQUIRED | K78: IN PROGRESS | L78: NOT REQUIRED | M78: IN PROGRESS | N78: IN PROGRESS | O78: IN PROGRESS | P78: IN PROGRESS | Q78: RECEIVED | R78: RECEIVED | S78: 0 | T78: 47 | U78: 0 | V78: 0.70833333 | W78: 0.65277778 | X78: 0 | Y78: NOT REQUIRED | Z78: NOT REQUIRED | AA78: NOT REQUIRED | AB78: NOT REQUIRED | AC78: OPTIMA 7140
A79: 1635 | B79: ORDER COMPLETED | C79: KATHLEEN WIT | D79: RESIDENTIAL | F79: 46254 | G79: 46254 | H79: YES | I79: NA | J79: COMPLETED | K79: COMPLETED | L79: NOT REQUIRED | M79: COMPLETED | N79: COMPLETED | O79: COMPLETED | P79: COMPLETED | Q79: RECEIVED | R79: RECEIVED | T79: 3 | U79: 0 | V79: 0.125 | W79: 0.083333333 | X79: 0 | Y79: NOT REQUIRED | Z79: NEED | AA79: NOT REQUIRED | AB79: NOT REQUIRED | AC79: 157 Mozart Ave , CA 92007
A80: 1668 | B80: ORDER COMPLETED | C80: SHARIF & MALIHE | D80: RESIDENTIAL | F80: 46254 | G80: 46254 | H80: YES | I80: NA | J80: COMPLETED | K80: COMPLETED | L80: COMPLETED | M80: COMPLETED | N80: COMPLETED | O80: COMPLETED | P80: COMPLETED | Q80: ON STOCK | R80: RECEIVED | T80: 5 | U80: 1 | V80: 0.083333333 | W80: 0.083333333 | X80: 0.041666667 | Y80: NOT REQUIRED | Z80: NOT REQUIRED | AA80: NOT REQUIRED | AB80: NOT REQUIRED | AC80: 4832 Fairport Way, San Diego, CA 92130, USA
A81: 1679 | B81: READY FOR DELIVERY | C81: BETH HOFFMAN | D81: SERVICE-WARRANT | F81: 46254 | G81: 46255 | H81: YES | I81: NA | J81: NOT REQUIRED | K81: NOT REQUIRED | L81: COMPLETED | M81: NOT REQUIRED | N81: NOT REQUIRED | O81: NOT REQUIRED | P81: NOT REQUIRED | Q81: NOT REQUIRED | R81: NOT REQUIRED | S81: 0 | T81: 0 | U81: 1 | V81: 0 | W81: 0 | X81: 1 | Y81: NOT REQUIRED | Z81: NOT REQUIRED | AA81: NOT REQUIRED | AB81: NOT REQUIRED | AC81: 5895 Blazing Star Ln, San Diego, CA 92130, USA
A82: 1690 | B82: ORDER COMPLETED | C82: SOLONA BEACH SHOWROOM | D82: COMMERCIAL | F82: 46254 | G82: 46254 | H82: YES | I82: NA | J82: COMPLETED | K82: COMPLETED | L82: COMPLETED | M82: COMPLETED | N82: COMPLETED | O82: COMPLETED | P82: COMPLETED | Q82: RECEIVED | R82: RECEIVED | T82: 10 | U82: 4 | V82: 0.25 | W82: 0.20833333 | X82: 0.125 | Y82: NOT REQUIRED | Z82: NOT REQUIRED | AA82: NOT REQUIRED | AB82: NOT REQUIRED | AC82: SOLONA BEACH SHOWROOM
A83: 1693 | B83: READY FOR DELIVERY | C83: DAN AMBROSE | D83: RESIDENTIAL | F83: 46254 | G83: 46255 | H83: YES | I83: NA | J83: COMPLETED | K83: COMPLETED | L83: NOT REQUIRED | M83: COMPLETED | N83: COMPLETED | O83: COMPLETED | P83: COMPLETED | Q83: RECEIVED | R83: RECEIVED | S83: 2 | T83: 2 | U83: 0 | V83: 1 | W83: 1 | X83: 0 | Y83: NOT REQUIRED | Z83: NOT REQUIRED | AA83: NOT REQUIRED | AB83: NOT REQUIRED | AC83: 26 9th St HER,OSA BEACH CA
A84: 1578-S | B84: READY FOR DELIVERY | C84: DAN AMBROSE | D84: SERVICE-WARRANT | F84: 46254 | G84: 46255 | H84: YES | I84: NA | J84: NOT REQUIRED | K84: NOT REQUIRED | L84: COMPLETED | M84: NOT REQUIRED | N84: NOT REQUIRED | O84: NOT REQUIRED | P84: NOT REQUIRED | Q84: NOT REQUIRED | R84: NOT REQUIRED | S84: 0 | T84: 0 | U84: 1 | V84: 0 | W84: 0 | X84: 3 | Y84: NOT REQUIRED | Z84: NOT REQUIRED | AA84: NOT REQUIRED | AB84: NOT REQUIRED | AC84: 26 9th St HER,OSA BEACH CA
A85: 1726 | B85: ORDER COMPLETED | C85: CAROL COLOMBO | D85: SERVICE-WARRANT | F85: 46254 | G85: 46254 | H85: YES | I85: NA | J85: COMPLETED | K85: COMPLETED | L85: NOT REQUIRED | M85: NOT REQUIRED | N85: NOT REQUIRED | O85: NOT REQUIRED | P85: NOT REQUIRED | Q85: NOT REQUIRED | R85: NOT REQUIRED | Y85: NOT REQUIRED | Z85: NOT REQUIRED | AA85: NOT REQUIRED | AB85: NOT REQUIRED
A86: 1707 | B86: NEW | C86: SCOTTSDALE SHOWROOM | D86: COMMERCIAL | F86: 46258 | G86: 46258 | H86: YES | I86: NA | J86: COMPLETED | K86: COMPLETED | L86: COMPLETED | M86: IN PROGRESS | N86: IN PROGRESS | O86: IN PROGRESS | P86: IN PROGRESS | Q86: RECEIVED | R86: RECEIVED | S86: 30 | T86: 5 | U86: 3 | V86: 0.375 | W86: 0.125 | X86: 0.125 | Y86: NOT REQUIRED | Z86: NOT REQUIRED | AA86: NOT REQUIRED | AB86: NOT REQUIRED | AC86: SCOTTSDALE SHOWROOM
A87: 1673 | B87: NEW | C87: CYNTHIA MANN | D87: RESIDENTIAL | E87: NEED TEMPLATE | F87: 46258 | G87: 46259 | H87: YES | I87: YES | J87: NOT REQUIRED | K87: NOT REQUIRED | L87: NOT REQUIRED | M87: IN PROGRESS | N87: COMPLETED | O87: COMPLETED | P87: IN PROGRESS | Q87: RECEIVED | R87: RECEIVED | S87: 8 | T87: 0 | U87: 0 | V87: 0.25 | W87: 0 | X87: 0 | Y87: NOT REQUIRED | Z87: NOT REQUIRED | AA87: NOT REQUIRED | AB87: NOT REQUIRED | AC87: 556 W. Moon Valley Drive, Phoenix, AZ
A88: 1682 | B88: READY FOR DELIVERY | C88: JOHN BUTZ | D88: RESIDENTIAL | F88: 46259 | G88: 46260 | H88: YES | I88: NA | J88: COMPLETED | K88: COMPLETED | L88: COMPLETED | M88: NOT REQUIRED | N88: NOT REQUIRED | O88: NOT REQUIRED | P88: NOT REQUIRED | Q88: NOT REQUIRED | R88: NOT REQUIRED | S88: 0 | T88: 1 | U88: 1 | V88: 0 | W88: 0.041666667 | X88: 0.041666667 | Y88: NOT REQUIRED | Z88: NOT REQUIRED | AA88: NOT REQUIRED | AB88: NOT REQUIRED | AC88: 2926 North Valencia Lane
A89: 1685 | B89: NEW | C89: OPTIMA 7190 FRAMES PHASE I | D89: SERVICE-WARRANT | E89: 46252 | F89: 46259 | G89: 46259 | H89: YES | I89: YES | J89: NOT REQUIRED | K89: IN PROGRESS | L89: NOT REQUIRED | M89: NOT REQUIRED | N89: NOT REQUIRED | O89: NOT REQUIRED | P89: NOT REQUIRED | Q89: NOT REQUIRED | R89: NOT REQUIRED | T89: 41 | U89: 0 | V89: 0 | W89: 0.56944444 | X89: 0 | Y89: NOT REQUIRED | Z89: NOT REQUIRED | AA89: NOT REQUIRED | AB89: NOT REQUIRED | AC89: OPTIMA 7190
A90: 1680 | B90: READY FOR DELIVERY | C90: SHERI RODGERS | D90: RESIDENTIAL | E90: 46261 | F90: 46261 | G90: 46261 | H90: YES | I90: YES | J90: NOT REQUIRED | K90: NOT REQUIRED | L90: NOT REQUIRED | M90: NOT REQUIRED | N90: NOT REQUIRED | O90: NOT REQUIRED | P90: NOT REQUIRED | Q90: NOT REQUIRED | R90: NOT REQUIRED | S90: 0 | T90: 0 | U90: 0 | V90: 0 | W90: 0 | X90: 0 | Y90: NOT REQUIRED | Z90: NOT REQUIRED | AA90: NOT REQUIRED | AB90: NOT REQUIRED | AC90: 1802 E Phoenix St Payson AZ 85541 / PICK UP FROM SCOTTSDALE SHOWROOM
A91: 1694 | B91: NEW | C91: MIKE GANTZEL | D91: REDO-JOB | E91: 46238 | F91: 46261 | G91: 46261 | H91: YES | I91: YES | J91: NOT REQUIRED | K91: NOT STARTED | L91: NOT REQUIRED | M91: COMPLETED | N91: COMPLETED | O91: COMPLETED | P91: COMPLETED | Q91: RECEIVED | R91: RECEIVED | S91: 10 | T91: 0 | U91: 4 | V91: 0.375 | W91: 0 | X91: 0.20833333 | Y91: NOT REQUIRED | Z91: NOT REQUIRED | AA91: NOT REQUIRED | AB91: NOT REQUIRED | AC91: 4099 East Meadowview Dr Gilbert Az 85298
A92: 1644 | B92: READY FOR DELIVERY | C92: CHRISTINE WILSON | D92: RESIDENTIAL | F92: 46265 | G92: 46265 | H92: YES | I92: NA | J92: COMPLETED | K92: COMPLETED | L92: NOT REQUIRED | M92: COMPLETED | N92: COMPLETED | O92: COMPLETED | P92: COMPLETED | Q92: RECEIVED | R92: RECEIVED | T92: 5 | U92: 0 | V92: 0.25 | W92: 0.16666667 | X92: 0 | Y92: NOT REQUIRED | Z92: NOT REQUIRED | AA92: NOT REQUIRED | AB92: NOT REQUIRED | AC92: 1854 DOWNS ST OCEAN SIDE CA 92054
A93: 1681 | B93: NEW | C93: DAVE KRISTEN ANDERSON | D93: RESIDENTIAL | E93: KIAN DROP | F93: 46265 | G93: 46265 | H93: YES | I93: YES | J93: COMPLETED | K93: COMPLETED | L93: COMPLETED | M93: IN PROGRESS | N93: IN PROGRESS | O93: IN PROGRESS | P93: NOT STARTED | Q93: RECEIVED | R93: PARTIAL ORDERED | S93: 86 | T93: 39 | U93: 13 | V93: 0.83333333 | W93: 0.75 | X93: 1.4583333 | Y93: NOT REQUIRED | Z93: NEED | AA93: NOT REQUIRED | AB93: NOT REQUIRED | AC93: 6343 Clubhouse Dr, Rancho Santa Fe, CA 92091, USA
A94: 1701 | B94: READY FOR DELIVERY | C94: MADONNA KAKISH | D94: RESIDENTIAL | F94: 46265 | G94: 46265 | H94: YES | I94: NA | J94: COMPLETED | K94: COMPLETED | L94: COMPLETED | M94: NOT REQUIRED | N94: NOT REQUIRED | O94: NOT REQUIRED | P94: NOT REQUIRED | Q94: NOT REQUIRED | R94: NOT REQUIRED | S94: 0 | T94: 1 | U94: 1 | V94: 0 | W94: 1 | X94: 1 | Y94: NOT REQUIRED | Z94: NOT REQUIRED | AA94: NOT REQUIRED | AB94: NOT REQUIRED | AC94: 32090 Via Bella Vita TEMECULA CA
A95: 1548 | B95: READY FOR DELIVERY | C95: STEVE-MARGUERITE MORRELL | D95: RESIDENTIAL | F95: 46266 | G95: 46266 | H95: YES | I95: NA | J95: COMPLETED | K95: COMPLETED | L95: COMPLETED | M95: COMPLETED | N95: COMPLETED | O95: COMPLETED | P95: COMPLETED | Q95: RECEIVED | R95: RECEIVED | S95: 8 | U95: 4 | Y95: NOT REQUIRED | Z95: NOT REQUIRED | AA95: NOT REQUIRED | AB95: NOT REQUIRED | AC95: 16734 N Mountain Parkway, FOUNTAIN HILLS
A96: 1685 | B96: NEW | C96: OPTIMA 7190 FRAMES PHASE II | D96: SERVICE-WARRANT | E96: 46259 | F96: 46266 | G96: 46266 | H96: YES | I96: YES | J96: NOT REQUIRED | K96: NOT STARTED | L96: NOT REQUIRED | M96: NOT REQUIRED | N96: NOT REQUIRED | O96: NOT REQUIRED | P96: NOT REQUIRED | Q96: NOT REQUIRED | R96: NOT REQUIRED | T96: 41 | U96: 0 | V96: 0 | W96: 0.56944444 | X96: 0 | Y96: NOT REQUIRED | Z96: NOT REQUIRED | AA96: NOT REQUIRED | AB96: NOT REQUIRED | AC96: OPTIMA 7190
A97: 1667 | B97: READY FOR DELIVERY | C97: STEPHEN HAKAMI | D97: RESIDENTIAL | F97: 46267 | G97: 46267 | H97: YES | I97: NA | J97: COMPLETED | K97: COMPLETED | L97: COMPLETED | M97: COMPLETED | N97: COMPLETED | O97: COMPLETED | P97: COMPLETED | Q97: ON STOCK | R97: RECEIVED | S97: 6 | T97: 8 | V97: 0.59027778 | X97: 0 | Y97: NOT REQUIRED | Z97: NOT REQUIRED | AA97: NOT REQUIRED | AB97: NOT REQUIRED | AC97: 6026 North 77th Place SCOTTSDALE AZ 85250
A98: 1723 | B98: NEW | C98: GIL KONFINO | D98: RESIDENTIAL | F98: 46268 | G98: 46268 | H98: YES | I98: NA | J98: COMPLETED | K98: NOT STARTED | L98: IN PROGRESS | M98: NOT STARTED | N98: NOT STARTED | O98: NOT STARTED | P98: NOT STARTED | Q98: ORDERED | R98: NEED | S98: 6 | T98: 6 | U98: 4 | V98: 0.41666667 | W98: 3 | X98: 1 | Y98: NOT REQUIRED | Z98: RECEIVED | AA98: RECEIVED | AB98: NOT REQUIRED | AC98: 33962 N Cole Ranch Rd QUEEN CREEK AZ
A99: 1716 | B99: NEW | C99: JENNIFER JOHNSON | D99: SERVICE-WARRANT | F99: 46269 | G99: 46269 | H99: NO | I99: NO | J99: NOT REQUIRED | K99: NOT REQUIRED | L99: NOT REQUIRED | M99: NOT STARTED | N99: NOT STARTED | O99: NOT STARTED | P99: NOT STARTED | Q99: RECEIVED | R99: SAME NEED | T99: 0 | U99: 0 | V99: 0.041666667 | W99: 0 | X99: 0 | Y99: NOT REQUIRED | Z99: NOT REQUIRED | AA99: NOT REQUIRED | AB99: NOT REQUIRED | AC99: 2666 E Raven Way GILBERT AZ 85297
A100: 1645 | B100: NEW | C100: ERIN CRAVENS | D100: RESIDENTIAL | F100: 46269 | G100: 46269 | H100: NO | I100: NA | J100: NOT STARTED | K100: NOT STARTED | L100: NOT REQUIRED | M100: NOT STARTED | N100: NOT STARTED | O100: NOT STARTED | P100: NOT STARTED | Q100: RECEIVED | R100: NEED | Y100: NOT REQUIRED | Z100: NOT REQUIRED | AA100: NOT REQUIRED | AB100: NOT REQUIRED | AC100: 8650 E SAN LORENZO DR SCOTTSDALE AZ 85258
...

Sheet Export Lines
B1: Order # | C1: Customer info | D1: Order Type | E1: PRODUCT. DEAD LINE | F1: PU/ DROP | G1: Delivery Date | H1: Cushions | I1: 3RD PARTY | J1: Covers | K1: Umbre- | L1: Tenjam | M1: Firepit System | N1: Metal | O1: Powder Coat | P1: Dekton | Q1: Delivery Address | R1: Order Status | S1: Start Date | T1: End Date | U1: Order payment status
B2: 184 | C2: LAMB, CINDY & JOHN | H2: Not started | N2: Not Started | O2: Not Started | P2: Not started | Q2: complete | S2: 44595 | T2: 44926 | U2: Not collected
B3: 186 | C3: CAROLL, DAVID | H3: Sew Start | N3: Not Started | O3: Not Started | P3: Not started | Q3: complete | S3: 44600 | T3: 44788 | U3: Not collected
B4: 199 | C4: PALMER, TERESA | G4: 44785 | H4: Completed | N4: Completed | O4: Completed | P4: Completed | Q4: complete | S4: 44621 | T4: 44666 | U4: Collected
B5: 248 | C5: TRADER, PAULA & BOB | H5: Sew End | N5: Not Started | O5: Not Started | P5: Not started | Q5: complete | S5: 44686 | T5: 44805 | U5: Not collected
B6: 259 | C6: BLOEBAUM, AMY | G6: 44798 | H6: Sew End | N6: Completed | O6: Not Started | P6: Completed | Q6: complete | S6: 44697 | T6: 44795 | U6: Collected
B7: 262 | C7: SALZMAN, JENNIFER | H7: Not required | N7: Not Started | O7: Not Started | P7: Not started | Q7: complete | S7: 44704 | T7: 44775 | U7: Ready to collect
B8: 263 | C8: BARAVADA, ATLAS | H8: Completed | N8: Completed | O8: Completed | P8: Not Required | Q8: complete | S8: 44705 | T8: 44926 | U8: Not collected
B9: 267 | C9: JONES, MARY LU | G9: 44788 | H9: Sew End | N9: Grind Start | O9: Not Started | P9: Not started | Q9: complete | S9: 44712 | T9: 44757 | U9: Collected
B10: 269 | C10: BICKELHAUPT, REESE | G10: 44784 | H10: Sew End | N10: Completed | O10: Powder Coat Start | P10: Cut Start | Q10: complete | S10: 44712 | T10: 44770 | U10: Collected
B11: 274 | C11: GUELI, SUSAN | G11: 44792 | H11: Sew Start | N11: Cut Start | O11: Not Started | P11: Not started | Q11: complete | S11: 44720 | T11: 44776 | U11: Collected
B12: 276 | C12: BELL, SUSAN | G12: 44783 | H12: Completed | N12: Completed | O12: Completed | P12: Polish Start | Q12: complete | S12: 44720 | T12: 44754 | U12: Collected
B13: 279 | C13: MAPSTEAD, JILL & JIM | G13: 44784 | H13: Completed | N13: Not Started | O13: Not Started | P13: Cut End | Q13: complete | S13: 44722 | T13: 44775 | U13: Collected
B14: 280 | C14: forsberg, clay | H14: Sew End | N14: Cut End | O14: Not Started | P14: Not Required | Q14: complete | S14: 44730 | T14: 44837 | U14: Collected
B15: 282 | C15: Sullivan, Mike | H15: Sew End | N15: Not Started | O15: Not Started | P15: Not started | Q15: complete | S15: 44734 | T15: 44785 | U15: Not collected
B16: 284 | C16: Peggy, Garret | G16: 44782 | H16: Sew End | N16: Completed | O16: Completed | P16: Completed | Q16: complete | S16: 44734 | T16: 44764 | U16: Collected
B17: 285 | C17: Tesar, Jim | H17: Not started | N17: Not Started | O17: Not Started | P17: Not started | Q17: complete | S17: 44734 | T17: 44816 | U17: Not collected
B18: 287 | C18: GARCIA, JON | H18: Sew End | N18: Not Started | O18: Not Started | P18: Not started | Q18: complete | S18: 44737 | T18: 44844 | U18: Not collected
B19: 288 | C19: SIVARA, LISSA | G19: 44795 | H19: Completed | N19: Weld Start | O19: Not Started | P19: Not started | Q19: complete | S19: 44737 | T19: 44764 | U19: Collected
B20: 289 | C20: WELLS, AMANDA & MATT | H20: Issue | N20: Not Started | O20: Not Started | P20: Not started | Q20: complete | S20: 44737 | T20: 44790 | U20: Not collected
B21: 290 | C21: KROLL, BRIAN | H21: Cut End | N21: Not Started | O21: Not Started | P21: Not started | Q21: complete | S21: 44740 | T21: 44803 | U21: Not collected
B22: 291 | C22: JOFFE, BETH & AARON | G22: 44791 | H22: Completed | N22: Not Started | O22: Not Started | P22: Cut End | Q22: complete | S22: 44740 | T22: 44771 | U22: Collected
B23: 292 | C23: KILIAN, STEVE & DEBBIE | H23: Completed | N23: Completed | O23: Not Started | P23: Completed | Q23: complete | S23: 44740 | T23: 44848 | U23: Ready to collect
B24: 293 | C24: PATEL, RANJAN | H24: Sew Start | N24: Not Started | O24: Not Started | P24: Not started | Q24: complete | S24: 44740 | T24: 44790 | U24: Not collected
B25: 294 | C25: VOTTIERO, PHIL & SHERRIE | H25: Cut End | N25: Not Started | O25: Not Started | P25: Not started | Q25: complete | S25: 44740 | T25: 44793 | U25: Not collected
B26: 296 | C26: FRIESEN, DON | H26: Not started | N26: Not Started | O26: Not Started | P26: Not started | Q26: complete | S26: 44748 | T26: 44817 | U26: Not collected
B27: 297 | C27: Bochner, Cheryl | H27: Sew Start | N27: Not Started | O27: Not Started | P27: Not started | Q27: complete | S27: 44749 | T27: 44792 | U27: Not collected
B28: 298 | C28: ECHMEYER, KRISTINA & EVAN | H28: Not started | N28: Not Started | O28: Not Started | P28: Not started | Q28: complete | S28: 44749 | T28: 44793 | U28: Not collected
B29: 299 | C29: Lester, Kay | H29: Cut Start | N29: Not Started | O29: Not Started | P29: Not started | Q29: complete | S29: 44750 | T29: 44785 | U29: Not collected
B30: 300 | C30: COOPER, GREG | H30: Issue | N30: Not Started | O30: Not Started | P30: Not started | Q30: complete | S30: 44755 | T30: 44824 | U30: Not collected
B31: 301 | C31: EICHLER, WENDI & JOHN | H31: Issue | N31: Not Started | O31: Not Started | P31: Not started | Q31: complete | S31: 44755 | T31: 44825 | U31: Not collected
B32: 302 | C32: MCGELLA, SUSAN | H32: Issue | N32: Not Started | O32: Not Started | P32: Not started | Q32: complete | S32: 44756 | T32: 44848 | U32: Not collected
B33: 303 | C33: WALLACH, MICHELLE | H33: Not started | N33: Not Started | O33: Not Started | P33: Not started | Q33: complete | S33: 44760 | T33: 44790 | U33: Not collected
B34: 304 | C34: ROBERTS, CINDY | H34: Not started | N34: Not Started | O34: Not Started | P34: Not started | Q34: complete | S34: 44762 | T34: 44804 | U34: Not collected
... B36: 306 | C36: CLARK, ELIZABETH | H36: Not started | N36: Not Started | O36: Not Started | P36: Not started | Q36: complete | S36: 44764 | T36: 44816 | U36: Not collected
B37: 307 | C37: SUSAN & RICHARD, GROSSMAN | G37: 44791 | H37: Not required | N37: Completed | O37: Sandblast End | P37: Not started | Q37: complete | S37: 44765 | T37: 44772 | U37: Collected
B38: 308 | C38: ONE CAMELBACK, ONE CAMELBACK | H38: Not started | N38: Not Started | O38: Not Started | P38: Not started | Q38: complete | S38: 44767 | T38: 44826 | U38: Not collected
B39: 309 | C39: WILVER, PETE & MICHELLE | H39: Not started | N39: Not Started | O39: Not Started | P39: Not started | Q39: complete | S39: 44768 | T39: 44830 | U39: Not collected
B40: 310 | C40: SIMPSON, AMBER | H40: Not started | N40: Not Started | O40: Not Started | P40: Not started | Q40: complete | S40: 44768 | T40: 44831 | U40: Not collected
B41: 311 | C41: Uzcategui, Nicolas | H41: Issue | N41: Not Started | O41: Not Started | P41: Not Required | Q41: complete | S41: 44770 | T41: 44791 | U41: Not collected
B42: 312 | C42: WILLIAMS, BRENT & JENNIFER | H42: Issue | N42: Not Started | O42: Not Started | P42: Not started | Q42: complete | S42: 44770 | T42: 44796 | U42: Not collected
B43: 313 | C43: IORILLO, HEATHER | H43: Issue | N43: Not Started | O43: Not Started | P43: Not started | Q43: complete | S43: 44770 | T43: 44855 | U43: Not collected
B44: 314 | C44: COUCH, SUSAN & RICHARD | H44: Issue | N44: Not Started | O44: Not Started | P44: Not started | Q44: complete | S44: 44774 | T44: 44837 | U44: Not collected
B45: 315 | C45: BLOMQUIST, MICHELLE | H45: Not started | N45: Not Started | O45: Not Started | P45: Not started | Q45: complete | S45: 44774 | T45: 44846 | U45: Not collected
B46: 316 | C46: POTHIER, SHAWNI | H46: Sew End | N46: Not Required | O46: Not Required | P46: Not Required | Q46: complete | S46: 44775 | T46: 44785
B47: 317 | C47: FISCHIETTO, DANA | H47: Not started | N47: Not Started | O47: Not Started | P47: Not started | Q47: complete | S47: 44776 | T47: 44834 | U47: Not collected
B48: 318 | C48: KEETON, ALISSA | H48: Issue | N48: Not Started | O48: Not Started | P48: Not started | Q48: complete | S48: 44776 | T48: 44855 | U48: Not collected
B49: 319 | C49: FORD, PAMELA | H49: Issue | N49: Not Started | O49: Not Started | P49: Not started | Q49: complete | S49: 44776 | T49: 44817 | U49: Not collected
B50: 320 | C50: MT Builders LLC, . | H50: Not started | N50: Not Started | O50: Not Started | P50: Not Required | Q50: complete | S50: 44777 | T50: 44897 | U50: Not collected
B51: LJ_29 | C51: DOLENTE, JENNIFER | H51: Cut End | N51: Not Started | O51: Not Started | P51: Not started | Q51: complete | S51: 44695 | T51: 44757 | U51: Not collected
B52: LJ_30 | C52: BOSCH, SHARON | H52: Sew End | N52: Not Started | O52: Not Started | P52: Not started | Q52: complete | S52: 44728 | T52: 44784 | U52: Not collected
B53: 321 | C53: 21 INTERIORS, HEATH | H53: Not started | N53: Not Started | O53: Not Started | P53: Not Required | Q53: complete | S53: 44781 | T53: 44831 | U53: Collected
B54: 322 | C54: MARGES, MARGES | H54: Not started | N54: Not Started | O54: Not Started | P54: Not started | Q54: complete | S54: 44782 | T54: 44839 | U54: Not collected
B55: 323 | C55: 21 INTERIORS, KAUL | H55: Not started | N55: Not Started | O55: Not Started | P55: Not started | Q55: complete | S55: 44782 | T55: 44823 | U55: Not collected
B56: 324 | C56: SWEDLANA, HOMA | H56: Not started | N56: Not Started | O56: Not Started | P56: Not started | Q56: complete | S56: 44782 | T56: 44869 | U56: Collected
B57: 325 | C57: STANEK, LIZ | H57: Not required | N57: Not Required | O57: Not Required | P57: Not Required | Q57: complete | S57: 44784 | T57: 44798 | U57: Collected
B58: 326 | C58: GANGADHAR, NSLINI | H58: Not started | N58: Not Started | O58: Not Started | P58: Not started | Q58: complete | S58: 44784 | T58: 44834 | U58: Not collected
B59: 327 | C59: AFRICA, COURTNEY | H59: Not started | N59: Not Started | O59: Not Started | P59: Not started | Q59: complete | S59: 44784 | T59: 44856 | U59: Not collected
B60: 328 | C60: 21 INTERIORS, PETERSON | H60: Not started | N60: Not Started | O60: Not Started | P60: Not Required | Q60: complete | S60: 44785 | T60: 44831 | U60: Not collected
B61: 329 | C61: STRAUS, REBORTA & STUART | H61: Not started | N61: Not Started | O61: Not Started | P61: Not started | Q61: complete | S61: 44785 | T61: 44816 | U61: Not collected
B62: 330 | C62: VANDER STOEP, PETER | H62: Not started | N62: Not Started | O62: Not Started | P62: Not started | Q62: complete | S62: 44785 | T62: 44848 | U62: Collected
B63: 331 | C63: KEITH, GINA | H63: Not started | N63: Not Required | O63: Not Required | P63: Not Required | Q63: complete | S63: 44785 | T63: 44813 | U63: Collected
B64: LJ_34 | C64: RETTING, MICHAEL | H64: Not started | N64: Not Started | O64: Not Started | P64: Not started | Q64: complete | S64: 44761 | T64: 44824
B65: LJ_32 | C65: Stuart, Candace | H65: Not started | N65: Not Started | O65: Not Started | P65: Not started | Q65: complete | S65: 44734 | T65: 44788
B66: LJ_35 | C66: ANDREW, ANDREW | H66: Cut Start | N66: Not Started | O66: Not Started | P66: Not started | Q66: complete | S66: 44761 | T66: 44831 | U66: Not collected
B67: LJ_36 | C67: Xiao, Susan | H67: Not started | N67: Not Started | O67: Not Started | P67: Not started | Q67: complete | S67: 44769 | T67: 44846
B68: LJ_3 | C68: Abdi, Sharon | H68: Completed | N68: Completed | O68: Completed | P68: Completed | Q68: complete | S68: 44322 | T68: 44378
B69: 332 | C69: PALMER, CHERYL | H69: Issue | N69: Not Started | O69: Not Started | P69: Not started | Q69: complete | S69: 44797 | T69: 44860 | U69: Not collected
B70: 333 | C70: WELTON, DAN | H70: Not started | N70: Not Started | O70: Not Started | P70: Not started | Q70: complete | S70: 44799 | T70: 44855 | U70: Not collected
B71: 334 | C71: WEINSTEIN, GREG | H71: Not started | N71: Not Started | O71: Not Started | P71: Not started | Q71: complete | S71: 44800 | T71: 44865 | U71: Not collected
B72: 335 | C72: Harris, Jan | H72: Not started | N72: Not Required | O72: Not Required | P72: Not Required | Q72: complete | S72: 44805 | T72: 44814 | U72: Collected
B73: 336 | C73: Peggy, Garret | H73: Not required | N73: Not Required | O73: Not Required | P73: Not started | Q73: complete | S73: 44805 | T73: 44814 | U73: Collected
B74: 337 | C74: MILLER, JARED | H74: Not started | N74: Not Required | O74: Not Required | P74: Not Required | Q74: complete | S74: 44805 | T74: 44828
B75: 338 | C75: Optima 7180, optima | H75: Not started | N75: Not Required | O75: Not Required | P75: Not Required | Q75: complete | S75: 44805 | T75: 44926 | U75: Not collected
B76: 339 | C76: & Chantel, Grady | H76: Not started | N76: Not Required | O76: Not Required | P76: Not Required | Q76: complete | S76: 44805 | T76: 44862
B77: 340 | C77: ROSENBERG, CHARLES & RENIE | H77: Not started | N77: Not Started | O77: Not Started | P77: Not started | Q77: complete | S77: 44807 | T77: 44841 | U77: Not collected
B78: 341 | C78: LOCHHEAD, SCOTT | H78: Not started | N78: Not Started | O78: Not Started | P78: Not started | Q78: complete | S78: 44809 | T78: 44846 | U78: Not collected
B79: 342 | C79: LARSEN, VICKIE | H79: Not started | N79: Not Started | O79: Not Started | P79: Not started | Q79: complete | S79: 44809 | T79: 44875 | U79: Not collected
B80: 343 | C80: MAZE, JACKIE | H80: Not started | N80: Not Started | O80: Not Started | P80: Not started | Q80: complete | S80: 44809 | T80: 44870 | U80: Collected
B81: 344 | C81: KC, AOUFE | H81: Not started | N81: Not Started | O81: Not Started | P81: Not started | Q81: complete | S81: 44792 | T81: 44863 | U81: Not collected
B82: 346 | C82: LYNN, CC PATIO | H82: Not started | N82: Not Started | O82: Not Started | P82: Not started | Q82: complete | S82: 44812 | T82: 44883 | U82: Not collected
B83: 347 | C83: HEMSTREET, GREG | H83: Not required | N83: Not Started | O83: Not Started | P83: Not started | Q83: complete | S83: 44817 | T83: 44866 | U83: Not collected
B84: LJ_37 | C84: YAKORNI, CHARLOTTE | H84: Not started | N84: Not Started | O84: Not Started | P84: Not started | Q84: complete | S84: 44810 | T84: 44880 | U84: Collected
B85: LJ_38 | C85: BROWDER, WENDY | H85: Not started | N85: Not Started | O85: Not Started | P85: Not started | Q85: complete | S85: 44813 | T85: 44888 | U85: Collected
B86: 348 | C86: AZIZ, BILL | H86: Not started | N86: Not Started | O86: Not Started | P86: Not started | Q86: complete | S86: 44820 | T86: 44884 | U86: Not collected
B87: 349 | C87: BASCHE, ADAM | H87: Not started | N87: Not Started | O87: Not Started | P87: Not started | Q87: complete | S87: 44820 | T87: 44876 | U87: Not collected
B88: 350 | C88: REITER, COLLEEN & STEVE | H88: Not started | N88: Not Started | O88: Not Started | P88: Not started | Q88: complete | S88: 44820 | T88: 44882 | U88: Not collected
B89: 351 | C89: MARINO, JOEY & BECKY | H89: Not started | N89: Not Started | O89: Not Started | P89: Not started | Q89: complete | S89: 44820 | T89: 44888 | U89: Not collected
B90: 352 | C90: CLAUSEN, KEITH | H90: Not started | N90: Not Started | O90: Not Started | P90: Not started | Q90: complete | S90: 44820 | T90: 44958 | U90: Not collected
B91: 353 | C91: Petznick, Olen | H91: Not started | N91: Not Required | O91: Not Required | P91: Not Required | Q91: complete | S91: 44824 | T91: 44895
B92: 354 | C92: Gerber, Kyrin | H92: Not started | N92: Not Required | O92: Not Required | P92: Not Required | Q92: complete | S92: 44826 | T92: 44863
B93: 355 | C93: UNIAT, LOIS | H93: Not started | N93: Not Required | O93: Not Required | P93: Not Required | Q93: complete | S93: 44826 | T93: 44862
B94: 356 | C94: LOVE, SUSAN & CRAWFORD | H94: Issue | N94: Not Started | O94: Not Started | P94: Not started | Q94: complete | S94: 44831 | T94: 44895 | U94: Not collected
B95: 357 | C95: BALDWIN, ANNIE | H95: Not started | N95: Not Started | O95: Not Started | P95: Not started | Q95: complete | S95: 44831 | T95: 44905 | U95: Not collected
B96: 358 | C96: SCHNEIDER, STACY | H96: Not started | N96: Not Started | O96: Not Started | P96: Not started | Q96: complete | S96: 44838 | T96: 44900 | U96: Not collected
B97: 359 | C97: DeSouza, FRANCIS | H97: Not started | N97: Not Started | O97: Not Started | P97: Not started | Q97: complete | S97: 44838 | T97: 44888 | U97: Not collected
B98: 360 | C98: Bertenshaw, Kathi | H98: Not started | N98: Not Required | O98: Not Required | P98: Not Required | Q98: complete | S98: 44838 | T98: 44866
B99: 361 | C99: CICIORA, SUSAN | H99: Issue | N99: Not Started | O99: Not Started | P99: Not started | Q99: complete | S99: 44845 | T99: 44910 | U99: Not collected
B100: 362 | C100: KITTLESON, KELSEY | H100: Issue | N100: Not Started | O100: Not Started | P100: Not started | Q100: complete | S100: 44845 | T100: 44909 | U100: Not collected
B101: 363 | C101: CHAPMAN, MATTHEW | G101: 44872 | H101: Not started | N101: Not Started | O101: Not Started | P101: Not started | Q101: complete | S101: 44845 | T101: 44865 | U101: Collected
...

Sheet Copy of CAPACITY
A1: CC PATIO — CAPACITY & LEAD-TIME PLANNER
A2: Live from the NEW tab · each department independent · schedule real weekly hours in the planner and every date re-solves
A4: SETTINGS
A5: Capacity (hrs / wk / dept, default) | B5: 49 | C5: ← default; override per week in planner
A6: Lead buffer (days before delivery) | B6: 1
A7: Today | B7: =TODAY() -> 46255
A8: Cushion drops off once CORTE + SEW are COMPLETED (filling is not a constraint). Metal drops at POWDER COAT = COMPLETED. Dekton drops at DEKTON = COMPLETED.
A10: SNAPSHOT
A11: ORDERS BEHIND | C11: CATCH-UP CUSH (h) | E11: CATCH-UP PC (h) | G11: THIS-WK LOAD (h) | I11: NEXT-WK LOAD (h) | K11: BINDING DEPT
A12: =COUNTIF(M39:M88,"BEHIND") -> 50 | C12: =B29 -> 0 | E12: =B30 -> 0 | G12: =B29+B30+B31 -> 0 | I12: =C29+C30+C31 -> 0 | K12: {=IF(MAX(J16:J18)<=0,"all OK",INDEX(G16:G18,MATCH(MAX(J16:J18),J16:J18,0)))} -> all OK
A14: DEPARTMENT LOAD | G14: REQUIRED RUN-RATE vs CAPACITY
A15: DEPARTMENT | B15: REMAIN h | C15: WEEKS @def | D15: CLEAR DATE | E15: DROPS WHEN | G15: DEPARTMENT | H15: REQ h/wk | I15: CAPACITY | J15: GAP | K15: VERDICT
A16: Cushion | B16: =(SUMIFS(NEW!$V$2:$V$1528,NEW!$B$2:$B$1528,"NEW",NEW!$M$2:$M$1528,"<>COMPLETED")-SUMIFS(NEW!$V$2:$V$1528,NEW!$B$2:$B$1528,"NEW",NEW!$M$2:$M$1528,"<>COMPLETED",NEW!$N$2:$N$1528,"COMPLETED",NEW!$O$2:$O$1528,"COMPLETED"))*24 -> 380.03333 | C16: =B16/$B$5 -> 7.7557823 | D16: =$B$7+C16*7 -> 46309.29 | E16: CORTE + SEW = COMPLETED | G16: Cushion | H16: =MAX(P39:P88) -> 0 | I16: =$B$5 -> 49 | J16: =H16-I16 -> -49 | K16: =IF(J16<=0,"OK — fits","SHORT "&TEXT(J16,"0")&" h/wk") -> OK — fits
A17: Powder Coat (Metal) | B17: =SUMIFS(NEW!$W$2:$W$1528,NEW!$B$2:$B$1528,"NEW",NEW!$K$2:$K$1528,"<>COMPLETED")*24 -> 300.33333 | C17: =B17/$B$5 -> 6.1292517 | D17: =$B$7+C17*7 -> 46297.905 | E17: POWDER COAT = COMPLETED | G17: Powder Coat (Metal) | H17: =MAX(Q39:Q88) -> 0 | I17: =$B$5 -> 49 | J17: =H17-I17 -> -49 | K17: =IF(J17<=0,"OK — fits","SHORT "&TEXT(J17,"0")&" h/wk") -> OK — fits
A18: Dekton | B18: =SUMIFS(NEW!$X$2:$X$1528,NEW!$B$2:$B$1528,"NEW",NEW!$L$2:$L$1528,"<>COMPLETED")*24 -> 181 | C18: =B18/$B$5 -> 3.6938776 | D18: =$B$7+C18*7 -> 46280.857 | E18: DEKTON = COMPLETED | G18: Dekton | H18: =MAX(R39:R88) -> 0 | I18: =$B$5 -> 49 | J18: =H18-I18 -> -49 | K18: =IF(J18<=0,"OK — fits","SHORT "&TEXT(J18,"0")&" h/wk") -> OK — fits
G19: REQ = rate to finish every dated order by (delivery − buffer), set by the tightest cumulative stretch. Orders due within the buffer are catch-up (see snapshot).
A21: WEEKLY CAPACITY PLANNER — type the hours you'll actually staff each week (yellow = edit)
A22: Department | B22: =$B$7+0 -> 46255 | C22: =$B$7+7 -> 46262 | D22: =$B$7+14 -> 46269 | E22: =$B$7+21 -> 46276 | F22: =$B$7+28 -> 46283 | G22: =$B$7+35 -> 46290 | H22: =$B$7+42 -> 46297 | I22: =$B$7+49 -> 46304
A23: Cushion | B23: 50 | C23: 50 | D23: 36 | E23: 36 | F23: 36 | G23: 36 | H23: 36 | I23: 36
A24: Powder Coat | B24: 36 | C24: 36 | D24: 36 | E24: 36 | F24: 36 | G24: 36 | H24: 36 | I24: 36
A25: Dekton | B25: 36 | C25: 0 | D25: 36 | E25: 36 | F25: 36 | G25: 36 | H25: 36 | I25: 36
A26: Example loaded: Cushion 50 h this & next week (overtime), Dekton 0 next week (people moved out). Edit any yellow cell — the timeline and clear-dates update.
A27: LOAD vs CAPACITY TIMELINE — work landing each week (by target) vs capacity scheduled above
A28: Week of → | B28: =B22 -> 46255 | C28: =C22 -> 46262 | D28: =D22 -> 46269 | E28: =E22 -> 46276 | F28: =F22 -> 46283 | G28: =G22 -> 46290 | H28: =H22 -> 46297 | I28: =I22 -> 46304
A29: Cushion demand | B29: =SUMIFS($E$39:$E$88,$D$39:$D$88,"<"&(B$28+7)) -> 0 | C29: =SUMIFS($E$39:$E$88,$D$39:$D$88,">="&C$28,$D$39:$D$88,"<"&(C$28+7)) -> 0 | D29: =SUMIFS($E$39:$E$88,$D$39:$D$88,">="&D$28,$D$39:$D$88,"<"&(D$28+7)) -> 0 | E29: =SUMIFS($E$39:$E$88,$D$39:$D$88,">="&E$28,$D$39:$D$88,"<"&(E$28+7)) -> 0 | F29: =SUMIFS($E$39:$E$88,$D$39:$D$88,">="&F$28,$D$39:$D$88,"<"&(F$28+7)) -> 0 | G29: =SUMIFS($E$39:$E$88,$D$39:$D$88,">="&G$28,$D$39:$D$88,"<"&(G$28+7)) -> 0 | H29: =SUMIFS($E$39:$E$88,$D$39:$D$88,">="&H$28,$D$39:$D$88,"<"&(H$28+7)) -> 0 | I29: =SUMIFS($E$39:$E$88,$D$39:$D$88,">="&I$28,$D$39:$D$88,"<"&(I$28+7)) -> 0
A30: Powder Coat demand | B30: =SUMIFS($F$39:$F$88,$D$39:$D$88,"<"&(B$28+7)) -> 0 | C30: =SUMIFS($F$39:$F$88,$D$39:$D$88,">="&C$28,$D$39:$D$88,"<"&(C$28+7)) -> 0 | D30: =SUMIFS($F$39:$F$88,$D$39:$D$88,">="&D$28,$D$39:$D$88,"<"&(D$28+7)) -> 0 | E30: =SUMIFS($F$39:$F$88,$D$39:$D$88,">="&E$28,$D$39:$D$88,"<"&(E$28+7)) -> 0 | F30: =SUMIFS($F$39:$F$88,$D$39:$D$88,">="&F$28,$D$39:$D$88,"<"&(F$28+7)) -> 0 | G30: =SUMIFS($F$39:$F$88,$D$39:$D$88,">="&G$28,$D$39:$D$88,"<"&(G$28+7)) -> 0 | H30: =SUMIFS($F$39:$F$88,$D$39:$D$88,">="&H$28,$D$39:$D$88,"<"&(H$28+7)) -> 0 | I30: =SUMIFS($F$39:$F$88,$D$39:$D$88,">="&I$28,$D$39:$D$88,"<"&(I$28+7)) -> 0
A31: Dekton demand | B31: =SUMIFS($G$39:$G$88,$D$39:$D$88,"<"&(B$28+7)) -> 0 | C31: =SUMIFS($G$39:$G$88,$D$39:$D$88,">="&C$28,$D$39:$D$88,"<"&(C$28+7)) -> 0 | D31: =SUMIFS($G$39:$G$88,$D$39:$D$88,">="&D$28,$D$39:$D$88,"<"&(D$28+7)) -> 0 | E31: =SUMIFS($G$39:$G$88,$D$39:$D$88,">="&E$28,$D$39:$D$88,"<"&(E$28+7)) -> 0 | F31: =SUMIFS($G$39:$G$88,$D$39:$D$88,">="&F$28,$D$39:$D$88,"<"&(F$28+7)) -> 0 | G31: =SUMIFS($G$39:$G$88,$D$39:$D$88,">="&G$28,$D$39:$D$88,"<"&(G$28+7)) -> 0 | H31: =SUMIFS($G$39:$G$88,$D$39:$D$88,">="&H$28,$D$39:$D$88,"<"&(H$28+7)) -> 0 | I31: =SUMIFS($G$39:$G$88,$D$39:$D$88,">="&I$28,$D$39:$D$88,"<"&(I$28+7)) -> 0
A32: Cushion — behind by (h) | B32: =MAX(0,SUM($B$29:B$29)-SUM($B$23:B$23)) -> 0 | C32: =MAX(0,SUM($B$29:C$29)-SUM($B$23:C$23)) -> 0 | D32: =MAX(0,SUM($B$29:D$29)-SUM($B$23:D$23)) -> 0 | E32: =MAX(0,SUM($B$29:E$29)-SUM($B$23:E$23)) -> 0 | F32: =MAX(0,SUM($B$29:F$29)-SUM($B$23:F$23)) -> 0 | G32: =MAX(0,SUM($B$29:G$29)-SUM($B$23:G$23)) -> 0 | H32: =MAX(0,SUM($B$29:H$29)-SUM($B$23:H$23)) -> 0 | I32: =MAX(0,SUM($B$29:I$29)-SUM($B$23:I$23)) -> 0
A33: Powder Coat — behind by (h) | B33: =MAX(0,SUM($B$30:B$30)-SUM($B$24:B$24)) -> 0 | C33: =MAX(0,SUM($B$30:C$30)-SUM($B$24:C$24)) -> 0 | D33: =MAX(0,SUM($B$30:D$30)-SUM($B$24:D$24)) -> 0 | E33: =MAX(0,SUM($B$30:E$30)-SUM($B$24:E$24)) -> 0 | F33: =MAX(0,SUM($B$30:F$30)-SUM($B$24:F$24)) -> 0 | G33: =MAX(0,SUM($B$30:G$30)-SUM($B$24:G$24)) -> 0 | H33: =MAX(0,SUM($B$30:H$30)-SUM($B$24:H$24)) -> 0 | I33: =MAX(0,SUM($B$30:I$30)-SUM($B$24:I$24)) -> 0
A34: Dekton — behind by (h) | B34: =MAX(0,SUM($B$31:B$31)-SUM($B$25:B$25)) -> 0 | C34: =MAX(0,SUM($B$31:C$31)-SUM($B$25:C$25)) -> 0 | D34: =MAX(0,SUM($B$31:D$31)-SUM($B$25:D$25)) -> 0 | E34: =MAX(0,SUM($B$31:E$31)-SUM($B$25:E$25)) -> 0 | F34: =MAX(0,SUM($B$31:F$31)-SUM($B$25:F$25)) -> 0 | G34: =MAX(0,SUM($B$31:G$31)-SUM($B$25:G$25)) -> 0 | H34: =MAX(0,SUM($B$31:H$31)-SUM($B$25:H$25)) -> 0 | I34: =MAX(0,SUM($B$31:I$31)-SUM($B$25:I$25)) -> 0
A35: 'Behind by' = cumulative demand minus cumulative scheduled capacity through that week. 0 (green) = keeping up; >0 (red) = that many hours late entering the next week.
A36: ORDER WORKLIST — sorted by target; work top-down (hours drop as depts are marked COMPLETED)
A38: ORDER # | B38: CUSTOMER | C38: DELIVERY | D38: TARGET | E38: CUSH h | F38: PC h | G38: DEKT h | H38: Σ CUSH | I38: Σ PC | J38: Σ DEKT | K38: PROJ DONE | L38: DAYS vs TGT | M38: STATUS | N38: HEALTH | P38: req·c | Q38: req·pc | R38: req·dk
A39: =NEW!A1235 -> 1376 | B39: =NEW!C1235 -> ROXANN FREDERICK | C39: =NEW!G1235 -> 45986 | D39: =IF(ISNUMBER(C39),C39-$B$6,"") -> 45985 | E39: =IF(OR(NEW!M1235="COMPLETED",AND(NEW!N1235="COMPLETED",NEW!O1235="COMPLETED")),0,NEW!V1235*24) -> 0 | F39: =IF(NEW!K1235="COMPLETED",0,NEW!W1235*24) -> 0 | G39: =IF(NEW!L1235="COMPLETED",0,NEW!X1235*24) -> 0 | H39: =SUM(E$39:E39) -> 0 | I39: =SUM(F$39:F39) -> 0 | J39: =SUM(G$39:G39) -> 0 | K39: =$B$7+MAX(H39,I39,J39)/$B$5*7 -> 46255 | L39: =IF(ISNUMBER(D39),D39-K39,"") -> -270 | M39: =IF(ISNUMBER(D39),IF(L39<0,"BEHIND",IF(L39<$B$6,"START NOW","ON TRACK")),"no date") -> BEHIND | N39: =IF(ISNUMBER(D39),IF(L39<0,"● LATE",IF(L39<7,"● TIGHT","● OK")),"") -> ● LATE | P39: =IF(ISNUMBER(D39),IF((D39-$B$7)>=7,H39/((D39-$B$7)/7),""),"") | Q39: =IF(ISNUMBER(D39),IF((D39-$B$7)>=7,I39/((D39-$B$7)/7),""),"") | R39: =IF(ISNUMBER(D39),IF((D39-$B$7)>=7,J39/((D39-$B$7)/7),""),"")
A40: =NEW!A1382 -> 1522 | B40: =NEW!C1382 -> JOAN RASKIN-BROKEN FIRE PIT | C40: =NEW!G1382 -> 46100 | D40: =IF(ISNUMBER(C40),C40-$B$6,"") -> 46099 | E40: =IF(OR(NEW!M1382="COMPLETED",AND(NEW!N1382="COMPLETED",NEW!O1382="COMPLETED")),0,NEW!V1382*24) -> 0 | F40: =IF(NEW!K1382="COMPLETED",0,NEW!W1382*24) -> 0 | G40: =IF(NEW!L1382="COMPLETED",0,NEW!X1382*24) -> 0 | H40: =SUM(E$39:E40) -> 0 | I40: =SUM(F$39:F40) -> 0 | J40: =SUM(G$39:G40) -> 0 | K40: =$B$7+MAX(H40,I40,J40)/$B$5*7 -> 46255 | L40: =IF(ISNUMBER(D40),D40-K40,"") -> -156 | M40: =IF(ISNUMBER(D40),IF(L40<0,"BEHIND",IF(L40<$B$6,"START NOW","ON TRACK")),"no date") -> BEHIND | N40: =IF(ISNUMBER(D40),IF(L40<0,"● LATE",IF(L40<7,"● TIGHT","● OK")),"") -> ● LATE | P40: =IF(ISNUMBER(D40),IF((D40-$B$7)>=7,H40/((D40-$B$7)/7),""),"") | Q40: =IF(ISNUMBER(D40),IF((D40-$B$7)>=7,I40/((D40-$B$7)/7),""),"") | R40: =IF(ISNUMBER(D40),IF((D40-$B$7)>=7,J40/((D40-$B$7)/7),""),"")
A41: =NEW!A1388 -> 1529 | B41: =NEW!C1388 -> GINA PIPER | C41: =NEW!G1388 -> 46143 | D41: =IF(ISNUMBER(C41),C41-$B$6,"") -> 46142 | E41: =IF(OR(NEW!M1388="COMPLETED",AND(NEW!N1388="COMPLETED",NEW!O1388="COMPLETED")),0,NEW!V1388*24) -> 0 | F41: =IF(NEW!K1388="COMPLETED",0,NEW!W1388*24) -> 0 | G41: =IF(NEW!L1388="COMPLETED",0,NEW!X1388*24) -> 0 | H41: =SUM(E$39:E41) -> 0 | I41: =SUM(F$39:F41) -> 0 | J41: =SUM(G$39:G41) -> 0 | K41: =$B$7+MAX(H41,I41,J41)/$B$5*7 -> 46255 | L41: =IF(ISNUMBER(D41),D41-K41,"") -> -113 | M41: =IF(ISNUMBER(D41),IF(L41<0,"BEHIND",IF(L41<$B$6,"START NOW","ON TRACK")),"no date") -> BEHIND | N41: =IF(ISNUMBER(D41),IF(L41<0,"● LATE",IF(L41<7,"● TIGHT","● OK")),"") -> ● LATE | P41: =IF(ISNUMBER(D41),IF((D41-$B$7)>=7,H41/((D41-$B$7)/7),""),"") | Q41: =IF(ISNUMBER(D41),IF((D41-$B$7)>=7,I41/((D41-$B$7)/7),""),"") | R41: =IF(ISNUMBER(D41),IF((D41-$B$7)>=7,J41/((D41-$B$7)/7),""),"")
A42: =NEW!A1393 -> 1534 | B42: =NEW!C1393 -> RITA-RICHARD RUSSEL | C42: =NEW!G1393 -> 46154 | D42: =IF(ISNUMBER(C42),C42-$B$6,"") -> 46153 | E42: =IF(OR(NEW!M1393="COMPLETED",AND(NEW!N1393="COMPLETED",NEW!O1393="COMPLETED")),0,NEW!V1393*24) -> 0 | F42: =IF(NEW!K1393="COMPLETED",0,NEW!W1393*24) -> 0 | G42: =IF(NEW!L1393="COMPLETED",0,NEW!X1393*24) -> 0 | H42: =SUM(E$39:E42) -> 0 | I42: =SUM(F$39:F42) -> 0 | J42: =SUM(G$39:G42) -> 0 | K42: =$B$7+MAX(H42,I42,J42)/$B$5*7 -> 46255 | L42: =IF(ISNUMBER(D42),D42-K42,"") -> -102 | M42: =IF(ISNUMBER(D42),IF(L42<0,"BEHIND",IF(L42<$B$6,"START NOW","ON TRACK")),"no date") -> BEHIND | N42: =IF(ISNUMBER(D42),IF(L42<0,"● LATE",IF(L42<7,"● TIGHT","● OK")),"") -> ● LATE | P42: =IF(ISNUMBER(D42),IF((D42-$B$7)>=7,H42/((D42-$B$7)/7),""),"") | Q42: =IF(ISNUMBER(D42),IF((D42-$B$7)>=7,I42/((D42-$B$7)/7),""),"") | R42: =IF(ISNUMBER(D42),IF((D42-$B$7)>=7,J42/((D42-$B$7)/7),""),"")
A43: =NEW!A1394 -> 1535 | B43: =NEW!C1394 -> BAHAMAS-CHRIS PRICE | C43: =NEW!G1394 -> 46181 | D43: =IF(ISNUMBER(C43),C43-$B$6,"") -> 46180 | E43: =IF(OR(NEW!M1394="COMPLETED",AND(NEW!N1394="COMPLETED",NEW!O1394="COMPLETED")),0,NEW!V1394*24) -> 0 | F43: =IF(NEW!K1394="COMPLETED",0,NEW!W1394*24) -> 0 | G43: =IF(NEW!L1394="COMPLETED",0,NEW!X1394*24) -> 0 | H43: =SUM(E$39:E43) -> 0 | I43: =SUM(F$39:F43) -> 0 | J43: =SUM(G$39:G43) -> 0 | K43: =$B$7+MAX(H43,I43,J43)/$B$5*7 -> 46255 | L43: =IF(ISNUMBER(D43),D43-K43,"") -> -75 | M43: =IF(ISNUMBER(D43),IF(L43<0,"BEHIND",IF(L43<$B$6,"START NOW","ON TRACK")),"no date") -> BEHIND | N43: =IF(ISNUMBER(D43),IF(L43<0,"● LATE",IF(L43<7,"● TIGHT","● OK")),"") -> ● LATE | P43: =IF(ISNUMBER(D43),IF((D43-$B$7)>=7,H43/((D43-$B$7)/7),""),"") | Q43: =IF(ISNUMBER(D43),IF((D43-$B$7)>=7,I43/((D43-$B$7)/7),""),"") | R43: =IF(ISNUMBER(D43),IF((D43-$B$7)>=7,J43/((D43-$B$7)/7),""),"")
A44: =NEW!A1395 -> 1536 | B44: =NEW!C1395 -> BRUCE SUSAN HALL | C44: =NEW!G1395 -> 46149 | D44: =IF(ISNUMBER(C44),C44-$B$6,"") -> 46148 | E44: =IF(OR(NEW!M1395="COMPLETED",AND(NEW!N1395="COMPLETED",NEW!O1395="COMPLETED")),0,NEW!V1395*24) -> 0 | F44: =IF(NEW!K1395="COMPLETED",0,NEW!W1395*24) -> 0 | G44: =IF(NEW!L1395="COMPLETED",0,NEW!X1395*24) -> 0 | H44: =SUM(E$39:E44) -> 0 | I44: =SUM(F$39:F44) -> 0 | J44: =SUM(G$39:G44) -> 0 | K44: =$B$7+MAX(H44,I44,J44)/$B$5*7 -> 46255 | L44: =IF(ISNUMBER(D44),D44-K44,"") -> -107 | M44: =IF(ISNUMBER(D44),IF(L44<0,"BEHIND",IF(L44<$B$6,"START NOW","ON TRACK")),"no date") -> BEHIND | N44: =IF(ISNUMBER(D44),IF(L44<0,"● LATE",IF(L44<7,"● TIGHT","● OK")),"") -> ● LATE | P44: =IF(ISNUMBER(D44),IF((D44-$B$7)>=7,H44/((D44-$B$7)/7),""),"") | Q44: =IF(ISNUMBER(D44),IF((D44-$B$7)>=7,I44/((D44-$B$7)/7),""),"") | R44: =IF(ISNUMBER(D44),IF((D44-$B$7)>=7,J44/((D44-$B$7)/7),""),"")
A45: =NEW!A1398 -> 1539 | B45: =NEW!C1398 -> PATTI MIKE KLAYKO | C45: =NEW!G1398 -> 46142 | D45: =IF(ISNUMBER(C45),C45-$B$6,"") -> 46141 | E45: =IF(OR(NEW!M1398="COMPLETED",AND(NEW!N1398="COMPLETED",NEW!O1398="COMPLETED")),0,NEW!V1398*24) -> 0 | F45: =IF(NEW!K1398="COMPLETED",0,NEW!W1398*24) -> 0 | G45: =IF(NEW!L1398="COMPLETED",0,NEW!X1398*24) -> 0 | H45: =SUM(E$39:E45) -> 0 | I45: =SUM(F$39:F45) -> 0 | J45: =SUM(G$39:G45) -> 0 | K45: =$B$7+MAX(H45,I45,J45)/$B$5*7 -> 46255 | L45: =IF(ISNUMBER(D45),D45-K45,"") -> -114 | M45: =IF(ISNUMBER(D45),IF(L45<0,"BEHIND",IF(L45<$B$6,"START NOW","ON TRACK")),"no date") -> BEHIND | N45: =IF(ISNUMBER(D45),IF(L45<0,"● LATE",IF(L45<7,"● TIGHT","● OK")),"") -> ● LATE | P45: =IF(ISNUMBER(D45),IF((D45-$B$7)>=7,H45/((D45-$B$7)/7),""),"") | Q45: =IF(ISNUMBER(D45),IF((D45-$B$7)>=7,I45/((D45-$B$7)/7),""),"") | R45: =IF(ISNUMBER(D45),IF((D45-$B$7)>=7,J45/((D45-$B$7)/7),""),"")
A46: =NEW!A1402 -> 1543 | B46: =NEW!C1402 -> MARK PATRICK ROACH | C46: =NEW!G1402 -> 46162 | D46: =IF(ISNUMBER(C46),C46-$B$6,"") -> 46161 | E46: =IF(OR(NEW!M1402="COMPLETED",AND(NEW!N1402="COMPLETED",NEW!O1402="COMPLETED")),0,NEW!V1402*24) -> 0 | F46: =IF(NEW!K1402="COMPLETED",0,NEW!W1402*24) -> 0 | G46: =IF(NEW!L1402="COMPLETED",0,NEW!X1402*24) -> 0 | H46: =SUM(E$39:E46) -> 0 | I46: =SUM(F$39:F46) -> 0 | J46: =SUM(G$39:G46) -> 0 | K46: =$B$7+MAX(H46,I46,J46)/$B$5*7 -> 46255 | L46: =IF(ISNUMBER(D46),D46-K46,"") -> -94 | M46: =IF(ISNUMBER(D46),IF(L46<0,"BEHIND",IF(L46<$B$6,"START NOW","ON TRACK")),"no date") -> BEHIND | N46: =IF(ISNUMBER(D46),IF(L46<0,"● LATE",IF(L46<7,"● TIGHT","● OK")),"") -> ● LATE | P46: =IF(ISNUMBER(D46),IF((D46-$B$7)>=7,H46/((D46-$B$7)/7),""),"") | Q46: =IF(ISNUMBER(D46),IF((D46-$B$7)>=7,I46/((D46-$B$7)/7),""),"") | R46: =IF(ISNUMBER(D46),IF((D46-$B$7)>=7,J46/((D46-$B$7)/7),""),"")
A47: =NEW!A1408 -> 1551 | B47: =NEW!C1408 -> JEN BAWNER DEKTON | C47: =NEW!G1408 -> 46139 | D47: =IF(ISNUMBER(C47),C47-$B$6,"") -> 46138 | E47: =IF(OR(NEW!M1408="COMPLETED",AND(NEW!N1408="COMPLETED",NEW!O1408="COMPLETED")),0,NEW!V1408*24) -> 0 | F47: =IF(NEW!K1408="COMPLETED",0,NEW!W1408*24) -> 0 | G47: =IF(NEW!L1408="COMPLETED",0,NEW!X1408*24) -> 0 | H47: =SUM(E$39:E47) -> 0 | I47: =SUM(F$39:F47) -> 0 | J47: =SUM(G$39:G47) -> 0 | K47: =$B$7+MAX(H47,I47,J47)/$B$5*7 -> 46255 | L47: =IF(ISNUMBER(D47),D47-K47,"") -> -117 | M47: =IF(ISNUMBER(D47),IF(L47<0,"BEHIND",IF(L47<$B$6,"START NOW","ON TRACK")),"no date") -> BEHIND | N47: =IF(ISNUMBER(D47),IF(L47<0,"● LATE",IF(L47<7,"● TIGHT","● OK")),"") -> ● LATE | P47: =IF(ISNUMBER(D47),IF((D47-$B$7)>=7,H47/((D47-$B$7)/7),""),"") | Q47: =IF(ISNUMBER(D47),IF((D47-$B$7)>=7,I47/((D47-$B$7)/7),""),"") | R47: =IF(ISNUMBER(D47),IF((D47-$B$7)>=7,J47/((D47-$B$7)/7),""),"")
A48: =NEW!A1409 -> 1552 | B48: =NEW!C1409 -> LINDA SCHOENER | C48: =NEW!G1409 -> 46168 | D48: =IF(ISNUMBER(C48),C48-$B$6,"") -> 46167 | E48: =IF(OR(NEW!M1409="COMPLETED",AND(NEW!N1409="COMPLETED",NEW!O1409="COMPLETED")),0,NEW!V1409*24) -> 0 | F48: =IF(NEW!K1409="COMPLETED",0,NEW!W1409*24) -> 0 | G48: =IF(NEW!L1409="COMPLETED",0,NEW!X1409*24) -> 0 | H48: =SUM(E$39:E48) -> 0 | I48: =SUM(F$39:F48) -> 0 | J48: =SUM(G$39:G48) -> 0 | K48: =$B$7+MAX(H48,I48,J48)/$B$5*7 -> 46255 | L48: =IF(ISNUMBER(D48),D48-K48,"") -> -88 | M48: =IF(ISNUMBER(D48),IF(L48<0,"BEHIND",IF(L48<$B$6,"START NOW","ON TRACK")),"no date") -> BEHIND | N48: =IF(ISNUMBER(D48),IF(L48<0,"● LATE",IF(L48<7,"● TIGHT","● OK")),"") -> ● LATE | P48: =IF(ISNUMBER(D48),IF((D48-$B$7)>=7,H48/((D48-$B$7)/7),""),"") | Q48: =IF(ISNUMBER(D48),IF((D48-$B$7)>=7,I48/((D48-$B$7)/7),""),"") | R48: =IF(ISNUMBER(D48),IF((D48-$B$7)>=7,J48/((D48-$B$7)/7),""),"")
A49: =NEW!A1411 -> 1553 | B49: =NEW!C1411 -> OPTIMA SIGNATURE CHICAGO | C49: =NEW!G1411 -> 46153 | D49: =IF(ISNUMBER(C49),C49-$B$6,"") -> 46152 | E49: =IF(OR(NEW!M1411="COMPLETED",AND(NEW!N1411="COMPLETED",NEW!O1411="COMPLETED")),0,NEW!V1411*24) -> 0 | F49: =IF(NEW!K1411="COMPLETED",0,NEW!W1411*24) -> 0 | G49: =IF(NEW!L1411="COMPLETED",0,NEW!X1411*24) -> 0 | H49: =SUM(E$39:E49) -> 0 | I49: =SUM(F$39:F49) -> 0 | J49: =SUM(G$39:G49) -> 0 | K49: =$B$7+MAX(H49,I49,J49)/$B$5*7 -> 46255 | L49: =IF(ISNUMBER(D49),D49-K49,"") -> -103 | M49: =IF(ISNUMBER(D49),IF(L49<0,"BEHIND",IF(L49<$B$6,"START NOW","ON TRACK")),"no date") -> BEHIND | N49: =IF(ISNUMBER(D49),IF(L49<0,"● LATE",IF(L49<7,"● TIGHT","● OK")),"") -> ● LATE | P49: =IF(ISNUMBER(D49),IF((D49-$B$7)>=7,H49/((D49-$B$7)/7),""),"") | Q49: =IF(ISNUMBER(D49),IF((D49-$B$7)>=7,I49/((D49-$B$7)/7),""),"") | R49: =IF(ISNUMBER(D49),IF((D49-$B$7)>=7,J49/((D49-$B$7)/7),""),"")
A50: =NEW!A1410 -> 1552 | B50: =NEW!C1410 -> LINDA SCHOENER | C50: =NEW!G1410 -> 46148 | D50: =IF(ISNUMBER(C50),C50-$B$6,"") -> 46147 | E50: =IF(OR(NEW!M1410="COMPLETED",AND(NEW!N1410="COMPLETED",NEW!O1410="COMPLETED")),0,NEW!V1410*24) -> 0 | F50: =IF(NEW!K1410="COMPLETED",0,NEW!W1410*24) -> 0 | G50: =IF(NEW!L1410="COMPLETED",0,NEW!X1410*24) -> 0 | H50: =SUM(E$39:E50) -> 0 | I50: =SUM(F$39:F50) -> 0 | J50: =SUM(G$39:G50) -> 0 | K50: =$B$7+MAX(H50,I50,J50)/$B$5*7 -> 46255 | L50: =IF(ISNUMBER(D50),D50-K50,"") -> -108 | M50: =IF(ISNUMBER(D50),IF(L50<0,"BEHIND",IF(L50<$B$6,"START NOW","ON TRACK")),"no date") -> BEHIND | N50: =IF(ISNUMBER(D50),IF(L50<0,"● LATE",IF(L50<7,"● TIGHT","● OK")),"") -> ● LATE | P50: =IF(ISNUMBER(D50),IF((D50-$B$7)>=7,H50/((D50-$B$7)/7),""),"") | Q50: =IF(ISNUMBER(D50),IF((D50-$B$7)>=7,I50/((D50-$B$7)/7),""),"") | R50: =IF(ISNUMBER(D50),IF((D50-$B$7)>=7,J50/((D50-$B$7)/7),""),"")
A51: =NEW!A1414 -> 1554 | B51: =NEW!C1414 -> NIVINE-DANY BAHDOUCH | C51: =NEW!G1414 -> 46155 | D51: =IF(ISNUMBER(C51),C51-$B$6,"") -> 46154 | E51: =IF(OR(NEW!M1414="COMPLETED",AND(NEW!N1414="COMPLETED",NEW!O1414="COMPLETED")),0,NEW!V1414*24) -> 0 | F51: =IF(NEW!K1414="COMPLETED",0,NEW!W1414*24) -> 0 | G51: =IF(NEW!L1414="COMPLETED",0,NEW!X1414*24) -> 0 | H51: =SUM(E$39:E51) -> 0 | I51: =SUM(F$39:F51) -> 0 | J51: =SUM(G$39:G51) -> 0 | K51: =$B$7+MAX(H51,I51,J51)/$B$5*7 -> 46255 | L51: =IF(ISNUMBER(D51),D51-K51,"") -> -101 | M51: =IF(ISNUMBER(D51),IF(L51<0,"BEHIND",IF(L51<$B$6,"START NOW","ON TRACK")),"no date") -> BEHIND | N51: =IF(ISNUMBER(D51),IF(L51<0,"● LATE",IF(L51<7,"● TIGHT","● OK")),"") -> ● LATE | P51: =IF(ISNUMBER(D51),IF((D51-$B$7)>=7,H51/((D51-$B$7)/7),""),"") | Q51: =IF(ISNUMBER(D51),IF((D51-$B$7)>=7,I51/((D51-$B$7)/7),""),"") | R51: =IF(ISNUMBER(D51),IF((D51-$B$7)>=7,J51/((D51-$B$7)/7),""),"")
A52: =NEW!A1415 -> 1555 | B52: =NEW!C1415 -> DESIGN ONE | C52: =NEW!G1415 -> 46160 | D52: =IF(ISNUMBER(C52),C52-$B$6,"") -> 46159 | E52: =IF(OR(NEW!M1415="COMPLETED",AND(NEW!N1415="COMPLETED",NEW!O1415="COMPLETED")),0,NEW!V1415*24) -> 0 | F52: =IF(NEW!K1415="COMPLETED",0,NEW!W1415*24) -> 0 | G52: =IF(NEW!L1415="COMPLETED",0,NEW!X1415*24) -> 0 | H52: =SUM(E$39:E52) -> 0 | I52: =SUM(F$39:F52) -> 0 | J52: =SUM(G$39:G52) -> 0 | K52: =$B$7+MAX(H52,I52,J52)/$B$5*7 -> 46255 | L52: =IF(ISNUMBER(D52),D52-K52,"") -> -96 | M52: =IF(ISNUMBER(D52),IF(L52<0,"BEHIND",IF(L52<$B$6,"START NOW","ON TRACK")),"no date") -> BEHIND | N52: =IF(ISNUMBER(D52),IF(L52<0,"● LATE",IF(L52<7,"● TIGHT","● OK")),"") -> ● LATE | P52: =IF(ISNUMBER(D52),IF((D52-$B$7)>=7,H52/((D52-$B$7)/7),""),"") | Q52: =IF(ISNUMBER(D52),IF((D52-$B$7)>=7,I52/((D52-$B$7)/7),""),"") | R52: =IF(ISNUMBER(D52),IF((D52-$B$7)>=7,J52/((D52-$B$7)/7),""),"")
A53: =NEW!A1416 -> 1555 | B53: =NEW!C1416 -> DESIGN ONE | C53: =NEW!G1416 -> 46160 | D53: =IF(ISNUMBER(C53),C53-$B$6,"") -> 46159 | E53: =IF(OR(NEW!M1416="COMPLETED",AND(NEW!N1416="COMPLETED",NEW!O1416="COMPLETED")),0,NEW!V1416*24) -> 0 | F53: =IF(NEW!K1416="COMPLETED",0,NEW!W1416*24) -> 0 | G53: =IF(NEW!L1416="COMPLETED",0,NEW!X1416*24) -> 0 | H53: =SUM(E$39:E53) -> 0 | I53: =SUM(F$39:F53) -> 0 | J53: =SUM(G$39:G53) -> 0 | K53: =$B$7+MAX(H53,I53,J53)/$B$5*7 -> 46255 | L53: =IF(ISNUMBER(D53),D53-K53,"") -> -96 | M53: =IF(ISNUMBER(D53),IF(L53<0,"BEHIND",IF(L53<$B$6,"START NOW","ON TRACK")),"no date") -> BEHIND | N53: =IF(ISNUMBER(D53),IF(L53<0,"● LATE",IF(L53<7,"● TIGHT","● OK")),"") -> ● LATE | P53: =IF(ISNUMBER(D53),IF((D53-$B$7)>=7,H53/((D53-$B$7)/7),""),"") | Q53: =IF(ISNUMBER(D53),IF((D53-$B$7)>=7,I53/((D53-$B$7)/7),""),"") | R53: =IF(ISNUMBER(D53),IF((D53-$B$7)>=7,J53/((D53-$B$7)/7),""),"")
A54: =NEW!A1420 -> 1557 | B54: =NEW!C1420 -> JESSA CURTIS | C54: =NEW!G1420 -> 46177 | D54: =IF(ISNUMBER(C54),C54-$B$6,"") -> 46176 | E54: =IF(OR(NEW!M1420="COMPLETED",AND(NEW!N1420="COMPLETED",NEW!O1420="COMPLETED")),0,NEW!V1420*24) -> 0 | F54: =IF(NEW!K1420="COMPLETED",0,NEW!W1420*24) -> 0 | G54: =IF(NEW!L1420="COMPLETED",0,NEW!X1420*24) -> 0 | H54: =SUM(E$39:E54) -> 0 | I54: =SUM(F$39:F54) -> 0 | J54: =SUM(G$39:G54) -> 0 | K54: =$B$7+MAX(H54,I54,J54)/$B$5*7 -> 46255 | L54: =IF(ISNUMBER(D54),D54-K54,"") -> -79 | M54: =IF(ISNUMBER(D54),IF(L54<0,"BEHIND",IF(L54<$B$6,"START NOW","ON TRACK")),"no date") -> BEHIND | N54: =IF(ISNUMBER(D54),IF(L54<0,"● LATE",IF(L54<7,"● TIGHT","● OK")),"") -> ● LATE | P54: =IF(ISNUMBER(D54),IF((D54-$B$7)>=7,H54/((D54-$B$7)/7),""),"") | Q54: =IF(ISNUMBER(D54),IF((D54-$B$7)>=7,I54/((D54-$B$7)/7),""),"") | R54: =IF(ISNUMBER(D54),IF((D54-$B$7)>=7,J54/((D54-$B$7)/7),""),"")
A55: =NEW!A1421 -> 1558 | B55: =NEW!C1421 -> HARRY HOBBS (ADD-ON) | C55: =NEW!G1421 -> 46172 | D55: =IF(ISNUMBER(C55),C55-$B$6,"") -> 46171 | E55: =IF(OR(NEW!M1421="COMPLETED",AND(NEW!N1421="COMPLETED",NEW!O1421="COMPLETED")),0,NEW!V1421*24) -> 0 | F55: =IF(NEW!K1421="COMPLETED",0,NEW!W1421*24) -> 0 | G55: =IF(NEW!L1421="COMPLETED",0,NEW!X1421*24) -> 0 | H55: =SUM(E$39:E55) -> 0 | I55: =SUM(F$39:F55) -> 0 | J55: =SUM(G$39:G55) -> 0 | K55: =$B$7+MAX(H55,I55,J55)/$B$5*7 -> 46255 | L55: =IF(ISNUMBER(D55),D55-K55,"") -> -84 | M55: =IF(ISNUMBER(D55),IF(L55<0,"BEHIND",IF(L55<$B$6,"START NOW","ON TRACK")),"no date") -> BEHIND | N55: =IF(ISNUMBER(D55),IF(L55<0,"● LATE",IF(L55<7,"● TIGHT","● OK")),"") -> ● LATE | P55: =IF(ISNUMBER(D55),IF((D55-$B$7)>=7,H55/((D55-$B$7)/7),""),"") | Q55: =IF(ISNUMBER(D55),IF((D55-$B$7)>=7,I55/((D55-$B$7)/7),""),"") | R55: =IF(ISNUMBER(D55),IF((D55-$B$7)>=7,J55/((D55-$B$7)/7),""),"")
A56: =NEW!A1422 -> 1558 | B56: =NEW!C1422 -> HARRY HOBBS (ADD-ON) | C56: =NEW!G1422 -> 46163 | D56: =IF(ISNUMBER(C56),C56-$B$6,"") -> 46162 | E56: =IF(OR(NEW!M1422="COMPLETED",AND(NEW!N1422="COMPLETED",NEW!O1422="COMPLETED")),0,NEW!V1422*24) -> 0 | F56: =IF(NEW!K1422="COMPLETED",0,NEW!W1422*24) -> 0 | G56: =IF(NEW!L1422="COMPLETED",0,NEW!X1422*24) -> 0 | H56: =SUM(E$39:E56) -> 0 | I56: =SUM(F$39:F56) -> 0 | J56: =SUM(G$39:G56) -> 0 | K56: =$B$7+MAX(H56,I56,J56)/$B$5*7 -> 46255 | L56: =IF(ISNUMBER(D56),D56-K56,"") -> -93 | M56: =IF(ISNUMBER(D56),IF(L56<0,"BEHIND",IF(L56<$B$6,"START NOW","ON TRACK")),"no date") -> BEHIND | N56: =IF(ISNUMBER(D56),IF(L56<0,"● LATE",IF(L56<7,"● TIGHT","● OK")),"") -> ● LATE | P56: =IF(ISNUMBER(D56),IF((D56-$B$7)>=7,H56/((D56-$B$7)/7),""),"") | Q56: =IF(ISNUMBER(D56),IF((D56-$B$7)>=7,I56/((D56-$B$7)/7),""),"") | R56: =IF(ISNUMBER(D56),IF((D56-$B$7)>=7,J56/((D56-$B$7)/7),""),"")
A57: =NEW!A1423 -> 1560 | B57: =NEW!C1423 -> AMANDA STEVEN HOUGHTON | C57: =NEW!G1423 -> 46133 | D57: =IF(ISNUMBER(C57),C57-$B$6,"") -> 46132 | E57: =IF(OR(NEW!M1423="COMPLETED",AND(NEW!N1423="COMPLETED",NEW!O1423="COMPLETED")),0,NEW!V1423*24) -> 0 | F57: =IF(NEW!K1423="COMPLETED",0,NEW!W1423*24) -> 0 | G57: =IF(NEW!L1423="COMPLETED",0,NEW!X1423*24) -> 0 | H57: =SUM(E$39:E57) -> 0 | I57: =SUM(F$39:F57) -> 0 | J57: =SUM(G$39:G57) -> 0 | K57: =$B$7+MAX(H57,I57,J57)/$B$5*7 -> 46255 | L57: =IF(ISNUMBER(D57),D57-K57,"") -> -123 | M57: =IF(ISNUMBER(D57),IF(L57<0,"BEHIND",IF(L57<$B$6,"START NOW","ON TRACK")),"no date") -> BEHIND | N57: =IF(ISNUMBER(D57),IF(L57<0,"● LATE",IF(L57<7,"● TIGHT","● OK")),"") -> ● LATE | P57: =IF(ISNUMBER(D57),IF((D57-$B$7)>=7,H57/((D57-$B$7)/7),""),"") | Q57: =IF(ISNUMBER(D57),IF((D57-$B$7)>=7,I57/((D57-$B$7)/7),""),"") | R57: =IF(ISNUMBER(D57),IF((D57-$B$7)>=7,J57/((D57-$B$7)/7),""),"")
A58: =NEW!A1425 -> 1562 | B58: =NEW!C1425 -> JW MARRIOT BED | C58: =NEW!G1425 -> 46141 | D58: =IF(ISNUMBER(C58),C58-$B$6,"") -> 46140 | E58: =IF(OR(NEW!M1425="COMPLETED",AND(NEW!N1425="COMPLETED",NEW!O1425="COMPLETED")),0,NEW!V1425*24) -> 0 | F58: =IF(NEW!K1425="COMPLETED",0,NEW!W1425*24) -> 0 | G58: =IF(NEW!L1425="COMPLETED",0,NEW!X1425*24) -> 0 | H58: =SUM(E$39:E58) -> 0 | I58: =SUM(F$39:F58) -> 0 | J58: =SUM(G$39:G58) -> 0 | K58: =$B$7+MAX(H58,I58,J58)/$B$5*7 -> 46255 | L58: =IF(ISNUMBER(D58),D58-K58,"") -> -115 | M58: =IF(ISNUMBER(D58),IF(L58<0,"BEHIND",IF(L58<$B$6,"START NOW","ON TRACK")),"no date") -> BEHIND | N58: =IF(ISNUMBER(D58),IF(L58<0,"● LATE",IF(L58<7,"● TIGHT","● OK")),"") -> ● LATE | P58: =IF(ISNUMBER(D58),IF((D58-$B$7)>=7,H58/((D58-$B$7)/7),""),"") | Q58: =IF(ISNUMBER(D58),IF((D58-$B$7)>=7,I58/((D58-$B$7)/7),""),"") | R58: =IF(ISNUMBER(D58),IF((D58-$B$7)>=7,J58/((D58-$B$7)/7),""),"")
A59: =NEW!A1427 -> 1564 | B59: =NEW!C1427 -> NANCY-MARK BOWMAN | C59: =NEW!G1427 -> 46163 | D59: =IF(ISNUMBER(C59),C59-$B$6,"") -> 46162 | E59: =IF(OR(NEW!M1427="COMPLETED",AND(NEW!N1427="COMPLETED",NEW!O1427="COMPLETED")),0,NEW!V1427*24) -> 0 | F59: =IF(NEW!K1427="COMPLETED",0,NEW!W1427*24) -> 0 | G59: =IF(NEW!L1427="COMPLETED",0,NEW!X1427*24) -> 0 | H59: =SUM(E$39:E59) -> 0 | I59: =SUM(F$39:F59) -> 0 | J59: =SUM(G$39:G59) -> 0 | K59: =$B$7+MAX(H59,I59,J59)/$B$5*7 -> 46255 | L59: =IF(ISNUMBER(D59),D59-K59,"") -> -93 | M59: =IF(ISNUMBER(D59),IF(L59<0,"BEHIND",IF(L59<$B$6,"START NOW","ON TRACK")),"no date") -> BEHIND | N59: =IF(ISNUMBER(D59),IF(L59<0,"● LATE",IF(L59<7,"● TIGHT","● OK")),"") -> ● LATE | P59: =IF(ISNUMBER(D59),IF((D59-$B$7)>=7,H59/((D59-$B$7)/7),""),"") | Q59: =IF(ISNUMBER(D59),IF((D59-$B$7)>=7,I59/((D59-$B$7)/7),""),"") | R59: =IF(ISNUMBER(D59),IF((D59-$B$7)>=7,J59/((D59-$B$7)/7),""),"")
A60: =NEW!A1428 -> 1565 | B60: =NEW!C1428 -> AMAR TAKHUR | C60: =NEW!G1428 -> 46192 | D60: =IF(ISNUMBER(C60),C60-$B$6,"") -> 46191 | E60: =IF(OR(NEW!M1428="COMPLETED",AND(NEW!N1428="COMPLETED",NEW!O1428="COMPLETED")),0,NEW!V1428*24) -> 0 | F60: =IF(NEW!K1428="COMPLETED",0,NEW!W1428*24) -> 0 | G60: =IF(NEW!L1428="COMPLETED",0,NEW!X1428*24) -> 0 | H60: =SUM(E$39:E60) -> 0 | I60: =SUM(F$39:F60) -> 0 | J60: =SUM(G$39:G60) -> 0 | K60: =$B$7+MAX(H60,I60,J60)/$B$5*7 -> 46255 | L60: =IF(ISNUMBER(D60),D60-K60,"") -> -64 | M60: =IF(ISNUMBER(D60),IF(L60<0,"BEHIND",IF(L60<$B$6,"START NOW","ON TRACK")),"no date") -> BEHIND | N60: =IF(ISNUMBER(D60),IF(L60<0,"● LATE",IF(L60<7,"● TIGHT","● OK")),"") -> ● LATE | P60: =IF(ISNUMBER(D60),IF((D60-$B$7)>=7,H60/((D60-$B$7)/7),""),"") | Q60: =IF(ISNUMBER(D60),IF((D60-$B$7)>=7,I60/((D60-$B$7)/7),""),"") | R60: =IF(ISNUMBER(D60),IF((D60-$B$7)>=7,J60/((D60-$B$7)/7),""),"")
A61: =NEW!A1429 -> 1566 | B61: =NEW!C1429 -> CHERYSE MILLER | C61: =NEW!G1429 -> 46174 | D61: =IF(ISNUMBER(C61),C61-$B$6,"") -> 46173 | E61: =IF(OR(NEW!M1429="COMPLETED",AND(NEW!N1429="COMPLETED",NEW!O1429="COMPLETED")),0,NEW!V1429*24) -> 0 | F61: =IF(NEW!K1429="COMPLETED",0,NEW!W1429*24) -> 0 | G61: =IF(NEW!L1429="COMPLETED",0,NEW!X1429*24) -> 0 | H61: =SUM(E$39:E61) -> 0 | I61: =SUM(F$39:F61) -> 0 | J61: =SUM(G$39:G61) -> 0 | K61: =$B$7+MAX(H61,I61,J61)/$B$5*7 -> 46255 | L61: =IF(ISNUMBER(D61),D61-K61,"") -> -82 | M61: =IF(ISNUMBER(D61),IF(L61<0,"BEHIND",IF(L61<$B$6,"START NOW","ON TRACK")),"no date") -> BEHIND | N61: =IF(ISNUMBER(D61),IF(L61<0,"● LATE",IF(L61<7,"● TIGHT","● OK")),"") -> ● LATE | P61: =IF(ISNUMBER(D61),IF((D61-$B$7)>=7,H61/((D61-$B$7)/7),""),"") | Q61: =IF(ISNUMBER(D61),IF((D61-$B$7)>=7,I61/((D61-$B$7)/7),""),"") | R61: =IF(ISNUMBER(D61),IF((D61-$B$7)>=7,J61/((D61-$B$7)/7),""),"")
A62: =NEW!A1430 -> 1567 | B62: =NEW!C1430 -> ROBYN-CHRIS PARK | C62: =NEW!G1430 -> 46184 | D62: =IF(ISNUMBER(C62),C62-$B$6,"") -> 46183 | E62: =IF(OR(NEW!M1430="COMPLETED",AND(NEW!N1430="COMPLETED",NEW!O1430="COMPLETED")),0,NEW!V1430*24) -> 0 | F62: =IF(NEW!K1430="COMPLETED",0,NEW!W1430*24) -> 0 | G62: =IF(NEW!L1430="COMPLETED",0,NEW!X1430*24) -> 0 | H62: =SUM(E$39:E62) -> 0 | I62: =SUM(F$39:F62) -> 0 | J62: =SUM(G$39:G62) -> 0 | K62: =$B$7+MAX(H62,I62,J62)/$B$5*7 -> 46255 | L62: =IF(ISNUMBER(D62),D62-K62,"") -> -72 | M62: =IF(ISNUMBER(D62),IF(L62<0,"BEHIND",IF(L62<$B$6,"START NOW","ON TRACK")),"no date") -> BEHIND | N62: =IF(ISNUMBER(D62),IF(L62<0,"● LATE",IF(L62<7,"● TIGHT","● OK")),"") -> ● LATE | P62: =IF(ISNUMBER(D62),IF((D62-$B$7)>=7,H62/((D62-$B$7)/7),""),"") | Q62: =IF(ISNUMBER(D62),IF((D62-$B$7)>=7,I62/((D62-$B$7)/7),""),"") | R62: =IF(ISNUMBER(D62),IF((D62-$B$7)>=7,J62/((D62-$B$7)/7),""),"")
A63: =NEW!A1431 -> 1568 | B63: =NEW!C1431 -> AMANDA WOOD | C63: =NEW!G1431 -> 46170 | D63: =IF(ISNUMBER(C63),C63-$B$6,"") -> 46169 | E63: =IF(OR(NEW!M1431="COMPLETED",AND(NEW!N1431="COMPLETED",NEW!O1431="COMPLETED")),0,NEW!V1431*24) -> 0 | F63: =IF(NEW!K1431="COMPLETED",0,NEW!W1431*24) -> 0 | G63: =IF(NEW!L1431="COMPLETED",0,NEW!X1431*24) -> 0 | H63: =SUM(E$39:E63) -> 0 | I63: =SUM(F$39:F63) -> 0 | J63: =SUM(G$39:G63) -> 0 | K63: =$B$7+MAX(H63,I63,J63)/$B$5*7 -> 46255 | L63: =IF(ISNUMBER(D63),D63-K63,"") -> -86 | M63: =IF(ISNUMBER(D63),IF(L63<0,"BEHIND",IF(L63<$B$6,"START NOW","ON TRACK")),"no date") -> BEHIND | N63: =IF(ISNUMBER(D63),IF(L63<0,"● LATE",IF(L63<7,"● TIGHT","● OK")),"") -> ● LATE | P63: =IF(ISNUMBER(D63),IF((D63-$B$7)>=7,H63/((D63-$B$7)/7),""),"") | Q63: =IF(ISNUMBER(D63),IF((D63-$B$7)>=7,I63/((D63-$B$7)/7),""),"") | R63: =IF(ISNUMBER(D63),IF((D63-$B$7)>=7,J63/((D63-$B$7)/7),""),"")
A64: =NEW!A1432 -> 1569 | B64: =NEW!C1432 -> JEFF BENCK | C64: =NEW!G1432 -> 46181 | D64: =IF(ISNUMBER(C64),C64-$B$6,"") -> 46180 | E64: =IF(OR(NEW!M1432="COMPLETED",AND(NEW!N1432="COMPLETED",NEW!O1432="COMPLETED")),0,NEW!V1432*24) -> 0 | F64: =IF(NEW!K1432="COMPLETED",0,NEW!W1432*24) -> 0 | G64: =IF(NEW!L1432="COMPLETED",0,NEW!X1432*24) -> 0 | H64: =SUM(E$39:E64) -> 0 | I64: =SUM(F$39:F64) -> 0 | J64: =SUM(G$39:G64) -> 0 | K64: =$B$7+MAX(H64,I64,J64)/$B$5*7 -> 46255 | L64: =IF(ISNUMBER(D64),D64-K64,"") -> -75 | M64: =IF(ISNUMBER(D64),IF(L64<0,"BEHIND",IF(L64<$B$6,"START NOW","ON TRACK")),"no date") -> BEHIND | N64: =IF(ISNUMBER(D64),IF(L64<0,"● LATE",IF(L64<7,"● TIGHT","● OK")),"") -> ● LATE | P64: =IF(ISNUMBER(D64),IF((D64-$B$7)>=7,H64/((D64-$B$7)/7),""),"") | Q64: =IF(ISNUMBER(D64),IF((D64-$B$7)>=7,I64/((D64-$B$7)/7),""),"") | R64: =IF(ISNUMBER(D64),IF((D64-$B$7)>=7,J64/((D64-$B$7)/7),""),"")
A65: =NEW!A1433 -> 1570 | B65: =NEW!C1433 -> LORI KENDRICK | C65: =NEW!G1433 -> 46183 | D65: =IF(ISNUMBER(C65),C65-$B$6,"") -> 46182 | E65: =IF(OR(NEW!M1433="COMPLETED",AND(NEW!N1433="COMPLETED",NEW!O1433="COMPLETED")),0,NEW!V1433*24) -> 0 | F65: =IF(NEW!K1433="COMPLETED",0,NEW!W1433*24) -> 0 | G65: =IF(NEW!L1433="COMPLETED",0,NEW!X1433*24) -> 0 | H65: =SUM(E$39:E65) -> 0 | I65: =SUM(F$39:F65) -> 0 | J65: =SUM(G$39:G65) -> 0 | K65: =$B$7+MAX(H65,I65,J65)/$B$5*7 -> 46255 | L65: =IF(ISNUMBER(D65),D65-K65,"") -> -73 | M65: =IF(ISNUMBER(D65),IF(L65<0,"BEHIND",IF(L65<$B$6,"START NOW","ON TRACK")),"no date") -> BEHIND | N65: =IF(ISNUMBER(D65),IF(L65<0,"● LATE",IF(L65<7,"● TIGHT","● OK")),"") -> ● LATE | P65: =IF(ISNUMBER(D65),IF((D65-$B$7)>=7,H65/((D65-$B$7)/7),""),"") | Q65: =IF(ISNUMBER(D65),IF((D65-$B$7)>=7,I65/((D65-$B$7)/7),""),"") | R65: =IF(ISNUMBER(D65),IF((D65-$B$7)>=7,J65/((D65-$B$7)/7),""),"")
A66: =NEW!A1445 -> 1586 | B66: =NEW!C1445 -> ROBIN CZAP | C66: =NEW!G1445 -> 46176 | D66: =IF(ISNUMBER(C66),C66-$B$6,"") -> 46175 | E66: =IF(OR(NEW!M1445="COMPLETED",AND(NEW!N1445="COMPLETED",NEW!O1445="COMPLETED")),0,NEW!V1445*24) -> 0 | F66: =IF(NEW!K1445="COMPLETED",0,NEW!W1445*24) -> 0 | G66: =IF(NEW!L1445="COMPLETED",0,NEW!X1445*24) -> 0 | H66: =SUM(E$39:E66) -> 0 | I66: =SUM(F$39:F66) -> 0 | J66: =SUM(G$39:G66) -> 0 | K66: =$B$7+MAX(H66,I66,J66)/$B$5*7 -> 46255 | L66: =IF(ISNUMBER(D66),D66-K66,"") -> -80 | M66: =IF(ISNUMBER(D66),IF(L66<0,"BEHIND",IF(L66<$B$6,"START NOW","ON TRACK")),"no date") -> BEHIND | N66: =IF(ISNUMBER(D66),IF(L66<0,"● LATE",IF(L66<7,"● TIGHT","● OK")),"") -> ● LATE | P66: =IF(ISNUMBER(D66),IF((D66-$B$7)>=7,H66/((D66-$B$7)/7),""),"") | Q66: =IF(ISNUMBER(D66),IF((D66-$B$7)>=7,I66/((D66-$B$7)/7),""),"") | R66: =IF(ISNUMBER(D66),IF((D66-$B$7)>=7,J66/((D66-$B$7)/7),""),"")
A67: =NEW!A1434 -> 1571 | B67: =NEW!C1434 -> VASANTHA SUMANTH | C67: =NEW!G1434 -> 46161 | D67: =IF(ISNUMBER(C67),C67-$B$6,"") -> 46160 | E67: =IF(OR(NEW!M1434="COMPLETED",AND(NEW!N1434="COMPLETED",NEW!O1434="COMPLETED")),0,NEW!V1434*24) -> 0 | F67: =IF(NEW!K1434="COMPLETED",0,NEW!W1434*24) -> 0 | G67: =IF(NEW!L1434="COMPLETED",0,NEW!X1434*24) -> 0 | H67: =SUM(E$39:E67) -> 0 | I67: =SUM(F$39:F67) -> 0 | J67: =SUM(G$39:G67) -> 0 | K67: =$B$7+MAX(H67,I67,J67)/$B$5*7 -> 46255 | L67: =IF(ISNUMBER(D67),D67-K67,"") -> -95 | M67: =IF(ISNUMBER(D67),IF(L67<0,"BEHIND",IF(L67<$B$6,"START NOW","ON TRACK")),"no date") -> BEHIND | N67: =IF(ISNUMBER(D67),IF(L67<0,"● LATE",IF(L67<7,"● TIGHT","● OK")),"") -> ● LATE | P67: =IF(ISNUMBER(D67),IF((D67-$B$7)>=7,H67/((D67-$B$7)/7),""),"") | Q67: =IF(ISNUMBER(D67),IF((D67-$B$7)>=7,I67/((D67-$B$7)/7),""),"") | R67: =IF(ISNUMBER(D67),IF((D67-$B$7)>=7,J67/((D67-$B$7)/7),""),"")
A68: =NEW!A1436 -> 1575 | B68: =NEW!C1436 -> ASHLEY CHAMPAGNE | C68: =NEW!G1436 -> 46191 | D68: =IF(ISNUMBER(C68),C68-$B$6,"") -> 46190 | E68: =IF(OR(NEW!M1436="COMPLETED",AND(NEW!N1436="COMPLETED",NEW!O1436="COMPLETED")),0,NEW!V1436*24) -> 0 | F68: =IF(NEW!K1436="COMPLETED",0,NEW!W1436*24) -> 0 | G68: =IF(NEW!L1436="COMPLETED",0,NEW!X1436*24) -> 0 | H68: =SUM(E$39:E68) -> 0 | I68: =SUM(F$39:F68) -> 0 | J68: =SUM(G$39:G68) -> 0 | K68: =$B$7+MAX(H68,I68,J68)/$B$5*7 -> 46255 | L68: =IF(ISNUMBER(D68),D68-K68,"") -> -65 | M68: =IF(ISNUMBER(D68),IF(L68<0,"BEHIND",IF(L68<$B$6,"START NOW","ON TRACK")),"no date") -> BEHIND | N68: =IF(ISNUMBER(D68),IF(L68<0,"● LATE",IF(L68<7,"● TIGHT","● OK")),"") -> ● LATE | P68: =IF(ISNUMBER(D68),IF((D68-$B$7)>=7,H68/((D68-$B$7)/7),""),"") | Q68: =IF(ISNUMBER(D68),IF((D68-$B$7)>=7,I68/((D68-$B$7)/7),""),"") | R68: =IF(ISNUMBER(D68),IF((D68-$B$7)>=7,J68/((D68-$B$7)/7),""),"")
A69: =NEW!A1437 -> 1577 | B69: =NEW!C1437 -> DR MARK SIEGEL | C69: =NEW!G1437 -> 46142 | D69: =IF(ISNUMBER(C69),C69-$B$6,"") -> 46141 | E69: =IF(OR(NEW!M1437="COMPLETED",AND(NEW!N1437="COMPLETED",NEW!O1437="COMPLETED")),0,NEW!V1437*24) -> 0 | F69: =IF(NEW!K1437="COMPLETED",0,NEW!W1437*24) -> 0 | G69: =IF(NEW!L1437="COMPLETED",0,NEW!X1437*24) -> 0 | H69: =SUM(E$39:E69) -> 0 | I69: =SUM(F$39:F69) -> 0 | J69: =SUM(G$39:G69) -> 0 | K69: =$B$7+MAX(H69,I69,J69)/$B$5*7 -> 46255 | L69: =IF(ISNUMBER(D69),D69-K69,"") -> -114 | M69: =IF(ISNUMBER(D69),IF(L69<0,"BEHIND",IF(L69<$B$6,"START NOW","ON TRACK")),"no date") -> BEHIND | N69: =IF(ISNUMBER(D69),IF(L69<0,"● LATE",IF(L69<7,"● TIGHT","● OK")),"") -> ● LATE | P69: =IF(ISNUMBER(D69),IF((D69-$B$7)>=7,H69/((D69-$B$7)/7),""),"") | Q69: =IF(ISNUMBER(D69),IF((D69-$B$7)>=7,I69/((D69-$B$7)/7),""),"") | R69: =IF(ISNUMBER(D69),IF((D69-$B$7)>=7,J69/((D69-$B$7)/7),""),"")
A70: =NEW!A1438 -> 1578 | B70: =NEW!C1438 -> DAN AMBROSE | C70: =NEW!G1438 -> 46167 | D70: =IF(ISNUMBER(C70),C70-$B$6,"") -> 46166 | E70: =IF(OR(NEW!M1438="COMPLETED",AND(NEW!N1438="COMPLETED",NEW!O1438="COMPLETED")),0,NEW!V1438*24) -> 0 | F70: =IF(NEW!K1438="COMPLETED",0,NEW!W1438*24) -> 0 | G70: =IF(NEW!L1438="COMPLETED",0,NEW!X1438*24) -> 0 | H70: =SUM(E$39:E70) -> 0 | I70: =SUM(F$39:F70) -> 0 | J70: =SUM(G$39:G70) -> 0 | K70: =$B$7+MAX(H70,I70,J70)/$B$5*7 -> 46255 | L70: =IF(ISNUMBER(D70),D70-K70,"") -> -89 | M70: =IF(ISNUMBER(D70),IF(L70<0,"BEHIND",IF(L70<$B$6,"START NOW","ON TRACK")),"no date") -> BEHIND | N70: =IF(ISNUMBER(D70),IF(L70<0,"● LATE",IF(L70<7,"● TIGHT","● OK")),"") -> ● LATE | P70: =IF(ISNUMBER(D70),IF((D70-$B$7)>=7,H70/((D70-$B$7)/7),""),"") | Q70: =IF(ISNUMBER(D70),IF((D70-$B$7)>=7,I70/((D70-$B$7)/7),""),"") | R70: =IF(ISNUMBER(D70),IF((D70-$B$7)>=7,J70/((D70-$B$7)/7),""),"")
A71: =NEW!A1441 -> 1581 | B71: =NEW!C1441 -> 32 COLOR SAMPLE RINGS | C71: =NEW!G1441 -> 46169 | D71: =IF(ISNUMBER(C71),C71-$B$6,"") -> 46168 | E71: =IF(OR(NEW!M1441="COMPLETED",AND(NEW!N1441="COMPLETED",NEW!O1441="COMPLETED")),0,NEW!V1441*24) -> 0 | F71: =IF(NEW!K1441="COMPLETED",0,NEW!W1441*24) -> 0 | G71: =IF(NEW!L1441="COMPLETED",0,NEW!X1441*24) -> 0 | H71: =SUM(E$39:E71) -> 0 | I71: =SUM(F$39:F71) -> 0 | J71: =SUM(G$39:G71) -> 0 | K71: =$B$7+MAX(H71,I71,J71)/$B$5*7 -> 46255 | L71: =IF(ISNUMBER(D71),D71-K71,"") -> -87 | M71: =IF(ISNUMBER(D71),IF(L71<0,"BEHIND",IF(L71<$B$6,"START NOW","ON TRACK")),"no date") -> BEHIND | N71: =IF(ISNUMBER(D71),IF(L71<0,"● LATE",IF(L71<7,"● TIGHT","● OK")),"") -> ● LATE | P71: =IF(ISNUMBER(D71),IF((D71-$B$7)>=7,H71/((D71-$B$7)/7),""),"") | Q71: =IF(ISNUMBER(D71),IF((D71-$B$7)>=7,I71/((D71-$B$7)/7),""),"") | R71: =IF(ISNUMBER(D71),IF((D71-$B$7)>=7,J71/((D71-$B$7)/7),""),"")
A72: =NEW!A1443 -> 1584 | B72: =NEW!C1443 -> SHARIF MALIHE | C72: =NEW!G1443 -> 46176 | D72: =IF(ISNUMBER(C72),C72-$B$6,"") -> 46175 | E72: =IF(OR(NEW!M1443="COMPLETED",AND(NEW!N1443="COMPLETED",NEW!O1443="COMPLETED")),0,NEW!V1443*24) -> 0 | F72: =IF(NEW!K1443="COMPLETED",0,NEW!W1443*24) -> 0 | G72: =IF(NEW!L1443="COMPLETED",0,NEW!X1443*24) -> 0 | H72: =SUM(E$39:E72) -> 0 | I72: =SUM(F$39:F72) -> 0 | J72: =SUM(G$39:G72) -> 0 | K72: =$B$7+MAX(H72,I72,J72)/$B$5*7 -> 46255 | L72: =IF(ISNUMBER(D72),D72-K72,"") -> -80 | M72: =IF(ISNUMBER(D72),IF(L72<0,"BEHIND",IF(L72<$B$6,"START NOW","ON TRACK")),"no date") -> BEHIND | N72: =IF(ISNUMBER(D72),IF(L72<0,"● LATE",IF(L72<7,"● TIGHT","● OK")),"") -> ● LATE | P72: =IF(ISNUMBER(D72),IF((D72-$B$7)>=7,H72/((D72-$B$7)/7),""),"") | Q72: =IF(ISNUMBER(D72),IF((D72-$B$7)>=7,I72/((D72-$B$7)/7),""),"") | R72: =IF(ISNUMBER(D72),IF((D72-$B$7)>=7,J72/((D72-$B$7)/7),""),"")
A73: =NEW!A1444 -> 1585 | B73: =NEW!C1444 -> JEFF BROWN | C73: =NEW!G1444 -> 46192 | D73: =IF(ISNUMBER(C73),C73-$B$6,"") -> 46191 | E73: =IF(OR(NEW!M1444="COMPLETED",AND(NEW!N1444="COMPLETED",NEW!O1444="COMPLETED")),0,NEW!V1444*24) -> 0 | F73: =IF(NEW!K1444="COMPLETED",0,NEW!W1444*24) -> 0 | G73: =IF(NEW!L1444="COMPLETED",0,NEW!X1444*24) -> 0 | H73: =SUM(E$39:E73) -> 0 | I73: =SUM(F$39:F73) -> 0 | J73: =SUM(G$39:G73) -> 0 | K73: =$B$7+MAX(H73,I73,J73)/$B$5*7 -> 46255 | L73: =IF(ISNUMBER(D73),D73-K73,"") -> -64 | M73: =IF(ISNUMBER(D73),IF(L73<0,"BEHIND",IF(L73<$B$6,"START NOW","ON TRACK")),"no date") -> BEHIND | N73: =IF(ISNUMBER(D73),IF(L73<0,"● LATE",IF(L73<7,"● TIGHT","● OK")),"") -> ● LATE | P73: =IF(ISNUMBER(D73),IF((D73-$B$7)>=7,H73/((D73-$B$7)/7),""),"") | Q73: =IF(ISNUMBER(D73),IF((D73-$B$7)>=7,I73/((D73-$B$7)/7),""),"") | R73: =IF(ISNUMBER(D73),IF((D73-$B$7)>=7,J73/((D73-$B$7)/7),""),"")
A74: =NEW!A1446 -> 1587 | B74: =NEW!C1446 -> WARR-DAN CHINITZ | C74: =NEW!G1446 -> 46170 | D74: =IF(ISNUMBER(C74),C74-$B$6,"") -> 46169 | E74: =IF(OR(NEW!M1446="COMPLETED",AND(NEW!N1446="COMPLETED",NEW!O1446="COMPLETED")),0,NEW!V1446*24) -> 0 | F74: =IF(NEW!K1446="COMPLETED",0,NEW!W1446*24) -> 0 | G74: =IF(NEW!L1446="COMPLETED",0,NEW!X1446*24) -> 0 | H74: =SUM(E$39:E74) -> 0 | I74: =SUM(F$39:F74) -> 0 | J74: =SUM(G$39:G74) -> 0 | K74: =$B$7+MAX(H74,I74,J74)/$B$5*7 -> 46255 | L74: =IF(ISNUMBER(D74),D74-K74,"") -> -86 | M74: =IF(ISNUMBER(D74),IF(L74<0,"BEHIND",IF(L74<$B$6,"START NOW","ON TRACK")),"no date") -> BEHIND | N74: =IF(ISNUMBER(D74),IF(L74<0,"● LATE",IF(L74<7,"● TIGHT","● OK")),"") -> ● LATE | P74: =IF(ISNUMBER(D74),IF((D74-$B$7)>=7,H74/((D74-$B$7)/7),""),"") | Q74: =IF(ISNUMBER(D74),IF((D74-$B$7)>=7,I74/((D74-$B$7)/7),""),"") | R74: =IF(ISNUMBER(D74),IF((D74-$B$7)>=7,J74/((D74-$B$7)/7),""),"")
A75: =NEW!A1447 -> 1588 | B75: =NEW!C1447 -> GREG LYON | C75: =NEW!G1447 -> 46177 | D75: =IF(ISNUMBER(C75),C75-$B$6,"") -> 46176 | E75: =IF(OR(NEW!M1447="COMPLETED",AND(NEW!N1447="COMPLETED",NEW!O1447="COMPLETED")),0,NEW!V1447*24) -> 0 | F75: =IF(NEW!K1447="COMPLETED",0,NEW!W1447*24) -> 0 | G75: =IF(NEW!L1447="COMPLETED",0,NEW!X1447*24) -> 0 | H75: =SUM(E$39:E75) -> 0 | I75: =SUM(F$39:F75) -> 0 | J75: =SUM(G$39:G75) -> 0 | K75: =$B$7+MAX(H75,I75,J75)/$B$5*7 -> 46255 | L75: =IF(ISNUMBER(D75),D75-K75,"") -> -79 | M75: =IF(ISNUMBER(D75),IF(L75<0,"BEHIND",IF(L75<$B$6,"START NOW","ON TRACK")),"no date") -> BEHIND | N75: =IF(ISNUMBER(D75),IF(L75<0,"● LATE",IF(L75<7,"● TIGHT","● OK")),"") -> ● LATE | P75: =IF(ISNUMBER(D75),IF((D75-$B$7)>=7,H75/((D75-$B$7)/7),""),"") | Q75: =IF(ISNUMBER(D75),IF((D75-$B$7)>=7,I75/((D75-$B$7)/7),""),"") | R75: =IF(ISNUMBER(D75),IF((D75-$B$7)>=7,J75/((D75-$B$7)/7),""),"")
A76: =NEW!A1448 -> 1589 | B76: =NEW!C1448 -> RIVER RANCH TIEBACKS | C76: =NEW!G1448 -> 46154 | D76: =IF(ISNUMBER(C76),C76-$B$6,"") -> 46153 | E76: =IF(OR(NEW!M1448="COMPLETED",AND(NEW!N1448="COMPLETED",NEW!O1448="COMPLETED")),0,NEW!V1448*24) -> 0 | F76: =IF(NEW!K1448="COMPLETED",0,NEW!W1448*24) -> 0 | G76: =IF(NEW!L1448="COMPLETED",0,NEW!X1448*24) -> 0 | H76: =SUM(E$39:E76) -> 0 | I76: =SUM(F$39:F76) -> 0 | J76: =SUM(G$39:G76) -> 0 | K76: =$B$7+MAX(H76,I76,J76)/$B$5*7 -> 46255 | L76: =IF(ISNUMBER(D76),D76-K76,"") -> -102 | M76: =IF(ISNUMBER(D76),IF(L76<0,"BEHIND",IF(L76<$B$6,"START NOW","ON TRACK")),"no date") -> BEHIND | N76: =IF(ISNUMBER(D76),IF(L76<0,"● LATE",IF(L76<7,"● TIGHT","● OK")),"") -> ● LATE | P76: =IF(ISNUMBER(D76),IF((D76-$B$7)>=7,H76/((D76-$B$7)/7),""),"") | Q76: =IF(ISNUMBER(D76),IF((D76-$B$7)>=7,I76/((D76-$B$7)/7),""),"") | R76: =IF(ISNUMBER(D76),IF((D76-$B$7)>=7,J76/((D76-$B$7)/7),""),"")
A77: =NEW!A1435 -> 1574 | B77: =NEW!C1435 -> MARTI BERTOLINO | C77: =NEW!G1435 -> 46176 | D77: =IF(ISNUMBER(C77),C77-$B$6,"") -> 46175 | E77: =IF(OR(NEW!M1435="COMPLETED",AND(NEW!N1435="COMPLETED",NEW!O1435="COMPLETED")),0,NEW!V1435*24) -> 0 | F77: =IF(NEW!K1435="COMPLETED",0,NEW!W1435*24) -> 0 | G77: =IF(NEW!L1435="COMPLETED",0,NEW!X1435*24) -> 0 | H77: =SUM(E$39:E77) -> 0 | I77: =SUM(F$39:F77) -> 0 | J77: =SUM(G$39:G77) -> 0 | K77: =$B$7+MAX(H77,I77,J77)/$B$5*7 -> 46255 | L77: =IF(ISNUMBER(D77),D77-K77,"") -> -80 | M77: =IF(ISNUMBER(D77),IF(L77<0,"BEHIND",IF(L77<$B$6,"START NOW","ON TRACK")),"no date") -> BEHIND | N77: =IF(ISNUMBER(D77),IF(L77<0,"● LATE",IF(L77<7,"● TIGHT","● OK")),"") -> ● LATE | P77: =IF(ISNUMBER(D77),IF((D77-$B$7)>=7,H77/((D77-$B$7)/7),""),"") | Q77: =IF(ISNUMBER(D77),IF((D77-$B$7)>=7,I77/((D77-$B$7)/7),""),"") | R77: =IF(ISNUMBER(D77),IF((D77-$B$7)>=7,J77/((D77-$B$7)/7),""),"")
A78: =NEW!A1449 -> 1590 | B78: =NEW!C1449 -> MICHELLE JAO VELASQUEZ | C78: =NEW!G1449 -> 46185 | D78: =IF(ISNUMBER(C78),C78-$B$6,"") -> 46184 | E78: =IF(OR(NEW!M1449="COMPLETED",AND(NEW!N1449="COMPLETED",NEW!O1449="COMPLETED")),0,NEW!V1449*24) -> 0 | F78: =IF(NEW!K1449="COMPLETED",0,NEW!W1449*24) -> 0 | G78: =IF(NEW!L1449="COMPLETED",0,NEW!X1449*24) -> 0 | H78: =SUM(E$39:E78) -> 0 | I78: =SUM(F$39:F78) -> 0 | J78: =SUM(G$39:G78) -> 0 | K78: =$B$7+MAX(H78,I78,J78)/$B$5*7 -> 46255 | L78: =IF(ISNUMBER(D78),D78-K78,"") -> -71 | M78: =IF(ISNUMBER(D78),IF(L78<0,"BEHIND",IF(L78<$B$6,"START NOW","ON TRACK")),"no date") -> BEHIND | N78: =IF(ISNUMBER(D78),IF(L78<0,"● LATE",IF(L78<7,"● TIGHT","● OK")),"") -> ● LATE | P78: =IF(ISNUMBER(D78),IF((D78-$B$7)>=7,H78/((D78-$B$7)/7),""),"") | Q78: =IF(ISNUMBER(D78),IF((D78-$B$7)>=7,I78/((D78-$B$7)/7),""),"") | R78: =IF(ISNUMBER(D78),IF((D78-$B$7)>=7,J78/((D78-$B$7)/7),""),"")
A79: =NEW!A1499 -> 1155-S | B79: =NEW!C1499 -> DIDI SPINA REDOIG SEAT-DEKTON | C79: =NEW!G1499 -> 45841 | D79: =IF(ISNUMBER(C79),C79-$B$6,"") -> 45840 | E79: =IF(OR(NEW!M1499="COMPLETED",AND(NEW!N1499="COMPLETED",NEW!O1499="COMPLETED")),0,NEW!V1499*24) -> 0 | F79: =IF(NEW!K1499="COMPLETED",0,NEW!W1499*24) -> 0 | G79: =IF(NEW!L1499="COMPLETED",0,NEW!X1499*24) -> 0 | H79: =SUM(E$39:E79) -> 0 | I79: =SUM(F$39:F79) -> 0 | J79: =SUM(G$39:G79) -> 0 | K79: =$B$7+MAX(H79,I79,J79)/$B$5*7 -> 46255 | L79: =IF(ISNUMBER(D79),D79-K79,"") -> -415 | M79: =IF(ISNUMBER(D79),IF(L79<0,"BEHIND",IF(L79<$B$6,"START NOW","ON TRACK")),"no date") -> BEHIND | N79: =IF(ISNUMBER(D79),IF(L79<0,"● LATE",IF(L79<7,"● TIGHT","● OK")),"") -> ● LATE | P79: =IF(ISNUMBER(D79),IF((D79-$B$7)>=7,H79/((D79-$B$7)/7),""),"") | Q79: =IF(ISNUMBER(D79),IF((D79-$B$7)>=7,I79/((D79-$B$7)/7),""),"") | R79: =IF(ISNUMBER(D79),IF((D79-$B$7)>=7,J79/((D79-$B$7)/7),""),"")
A80: =NEW!A1500 -> 1156-S | B80: =NEW!C1500 -> HOLDERBY, DREW | C80: =NEW!G1500 -> 45840 | D80: =IF(ISNUMBER(C80),C80-$B$6,"") -> 45839 | E80: =IF(OR(NEW!M1500="COMPLETED",AND(NEW!N1500="COMPLETED",NEW!O1500="COMPLETED")),0,NEW!V1500*24) -> 0 | F80: =IF(NEW!K1500="COMPLETED",0,NEW!W1500*24) -> 0 | G80: =IF(NEW!L1500="COMPLETED",0,NEW!X1500*24) -> 0 | H80: =SUM(E$39:E80) -> 0 | I80: =SUM(F$39:F80) -> 0 | J80: =SUM(G$39:G80) -> 0 | K80: =$B$7+MAX(H80,I80,J80)/$B$5*7 -> 46255 | L80: =IF(ISNUMBER(D80),D80-K80,"") -> -416 | M80: =IF(ISNUMBER(D80),IF(L80<0,"BEHIND",IF(L80<$B$6,"START NOW","ON TRACK")),"no date") -> BEHIND | N80: =IF(ISNUMBER(D80),IF(L80<0,"● LATE",IF(L80<7,"● TIGHT","● OK")),"") -> ● LATE | P80: =IF(ISNUMBER(D80),IF((D80-$B$7)>=7,H80/((D80-$B$7)/7),""),"") | Q80: =IF(ISNUMBER(D80),IF((D80-$B$7)>=7,I80/((D80-$B$7)/7),""),"") | R80: =IF(ISNUMBER(D80),IF((D80-$B$7)>=7,J80/((D80-$B$7)/7),""),"")
A81: =NEW!A1501 -> 1187C70 | B81: =NEW!C1501 -> GENCUSH-AARON HERANG | C81: =NEW!G1501 -> 45798 | D81: =IF(ISNUMBER(C81),C81-$B$6,"") -> 45797 | E81: =IF(OR(NEW!M1501="COMPLETED",AND(NEW!N1501="COMPLETED",NEW!O1501="COMPLETED")),0,NEW!V1501*24) -> 0 | F81: =IF(NEW!K1501="COMPLETED",0,NEW!W1501*24) -> 0 | G81: =IF(NEW!L1501="COMPLETED",0,NEW!X1501*24) -> 0 | H81: =SUM(E$39:E81) -> 0 | I81: =SUM(F$39:F81) -> 0 | J81: =SUM(G$39:G81) -> 0 | K81: =$B$7+MAX(H81,I81,J81)/$B$5*7 -> 46255 | L81: =IF(ISNUMBER(D81),D81-K81,"") -> -458 | M81: =IF(ISNUMBER(D81),IF(L81<0,"BEHIND",IF(L81<$B$6,"START NOW","ON TRACK")),"no date") -> BEHIND | N81: =IF(ISNUMBER(D81),IF(L81<0,"● LATE",IF(L81<7,"● TIGHT","● OK")),"") -> ● LATE | P81: =IF(ISNUMBER(D81),IF((D81-$B$7)>=7,H81/((D81-$B$7)/7),""),"") | Q81: =IF(ISNUMBER(D81),IF((D81-$B$7)>=7,I81/((D81-$B$7)/7),""),"") | R81: =IF(ISNUMBER(D81),IF((D81-$B$7)>=7,J81/((D81-$B$7)/7),""),"")
A82: =NEW!A1502 -> 1223-S | B82: =NEW!C1502 -> LISA POWELL RUSH ORDER | C82: =NEW!G1502 -> 45819 | D82: =IF(ISNUMBER(C82),C82-$B$6,"") -> 45818 | E82: =IF(OR(NEW!M1502="COMPLETED",AND(NEW!N1502="COMPLETED",NEW!O1502="COMPLETED")),0,NEW!V1502*24) -> 0 | F82: =IF(NEW!K1502="COMPLETED",0,NEW!W1502*24) -> 0 | G82: =IF(NEW!L1502="COMPLETED",0,NEW!X1502*24) -> 0 | H82: =SUM(E$39:E82) -> 0 | I82: =SUM(F$39:F82) -> 0 | J82: =SUM(G$39:G82) -> 0 | K82: =$B$7+MAX(H82,I82,J82)/$B$5*7 -> 46255 | L82: =IF(ISNUMBER(D82),D82-K82,"") -> -437 | M82: =IF(ISNUMBER(D82),IF(L82<0,"BEHIND",IF(L82<$B$6,"START NOW","ON TRACK")),"no date") -> BEHIND | N82: =IF(ISNUMBER(D82),IF(L82<0,"● LATE",IF(L82<7,"● TIGHT","● OK")),"") -> ● LATE | P82: =IF(ISNUMBER(D82),IF((D82-$B$7)>=7,H82/((D82-$B$7)/7),""),"") | Q82: =IF(ISNUMBER(D82),IF((D82-$B$7)>=7,I82/((D82-$B$7)/7),""),"") | R82: =IF(ISNUMBER(D82),IF((D82-$B$7)>=7,J82/((D82-$B$7)/7),""),"")
A83: =NEW!A1503 -> 1234A | B83: =NEW!C1503 -> MARK MOSKAL WARRANTY | C83: =NEW!G1503 -> 45904 | D83: =IF(ISNUMBER(C83),C83-$B$6,"") -> 45903 | E83: =IF(OR(NEW!M1503="COMPLETED",AND(NEW!N1503="COMPLETED",NEW!O1503="COMPLETED")),0,NEW!V1503*24) -> 0 | F83: =IF(NEW!K1503="COMPLETED",0,NEW!W1503*24) -> 0 | G83: =IF(NEW!L1503="COMPLETED",0,NEW!X1503*24) -> 0 | H83: =SUM(E$39:E83) -> 0 | I83: =SUM(F$39:F83) -> 0 | J83: =SUM(G$39:G83) -> 0 | K83: =$B$7+MAX(H83,I83,J83)/$B$5*7 -> 46255 | L83: =IF(ISNUMBER(D83),D83-K83,"") -> -352 | M83: =IF(ISNUMBER(D83),IF(L83<0,"BEHIND",IF(L83<$B$6,"START NOW","ON TRACK")),"no date") -> BEHIND | N83: =IF(ISNUMBER(D83),IF(L83<0,"● LATE",IF(L83<7,"● TIGHT","● OK")),"") -> ● LATE | P83: =IF(ISNUMBER(D83),IF((D83-$B$7)>=7,H83/((D83-$B$7)/7),""),"") | Q83: =IF(ISNUMBER(D83),IF((D83-$B$7)>=7,I83/((D83-$B$7)/7),""),"") | R83: =IF(ISNUMBER(D83),IF((D83-$B$7)>=7,J83/((D83-$B$7)/7),""),"")
A84: =NEW!A1504 -> 1244-1 | B84: =NEW!C1504 -> OPTIMA 7220 SEC#1 TO #9 | C84: =NEW!G1504 -> 45887 | D84: =IF(ISNUMBER(C84),C84-$B$6,"") -> 45886 | E84: =IF(OR(NEW!M1504="COMPLETED",AND(NEW!N1504="COMPLETED",NEW!O1504="COMPLETED")),0,NEW!V1504*24) -> 0 | F84: =IF(NEW!K1504="COMPLETED",0,NEW!W1504*24) -> 0 | G84: =IF(NEW!L1504="COMPLETED",0,NEW!X1504*24) -> 0 | H84: =SUM(E$39:E84) -> 0 | I84: =SUM(F$39:F84) -> 0 | J84: =SUM(G$39:G84) -> 0 | K84: =$B$7+MAX(H84,I84,J84)/$B$5*7 -> 46255 | L84: =IF(ISNUMBER(D84),D84-K84,"") -> -369 | M84: =IF(ISNUMBER(D84),IF(L84<0,"BEHIND",IF(L84<$B$6,"START NOW","ON TRACK")),"no date") -> BEHIND | N84: =IF(ISNUMBER(D84),IF(L84<0,"● LATE",IF(L84<7,"● TIGHT","● OK")),"") -> ● LATE | P84: =IF(ISNUMBER(D84),IF((D84-$B$7)>=7,H84/((D84-$B$7)/7),""),"") | Q84: =IF(ISNUMBER(D84),IF((D84-$B$7)>=7,I84/((D84-$B$7)/7),""),"") | R84: =IF(ISNUMBER(D84),IF((D84-$B$7)>=7,J84/((D84-$B$7)/7),""),"")
A85: =NEW!A1505 -> 1244-2 | B85: =NEW!C1505 -> OPTIMA 7220 SEC#10 TO #12 | C85: =NEW!G1505 -> 45888 | D85: =IF(ISNUMBER(C85),C85-$B$6,"") -> 45887 | E85: =IF(OR(NEW!M1505="COMPLETED",AND(NEW!N1505="COMPLETED",NEW!O1505="COMPLETED")),0,NEW!V1505*24) -> 0 | F85: =IF(NEW!K1505="COMPLETED",0,NEW!W1505*24) -> 0 | G85: =IF(NEW!L1505="COMPLETED",0,NEW!X1505*24) -> 0 | H85: =SUM(E$39:E85) -> 0 | I85: =SUM(F$39:F85) -> 0 | J85: =SUM(G$39:G85) -> 0 | K85: =$B$7+MAX(H85,I85,J85)/$B$5*7 -> 46255 | L85: =IF(ISNUMBER(D85),D85-K85,"") -> -368 | M85: =IF(ISNUMBER(D85),IF(L85<0,"BEHIND",IF(L85<$B$6,"START NOW","ON TRACK")),"no date") -> BEHIND | N85: =IF(ISNUMBER(D85),IF(L85<0,"● LATE",IF(L85<7,"● TIGHT","● OK")),"") -> ● LATE | P85: =IF(ISNUMBER(D85),IF((D85-$B$7)>=7,H85/((D85-$B$7)/7),""),"") | Q85: =IF(ISNUMBER(D85),IF((D85-$B$7)>=7,I85/((D85-$B$7)/7),""),"") | R85: =IF(ISNUMBER(D85),IF((D85-$B$7)>=7,J85/((D85-$B$7)/7),""),"")
A86: =NEW!A1506 -> 1244-3 | B86: =NEW!C1506 -> OPTIMA 7220 SEC#13 TO #17 | C86: =NEW!G1506 -> 45888 | D86: =IF(ISNUMBER(C86),C86-$B$6,"") -> 45887 | E86: =IF(OR(NEW!M1506="COMPLETED",AND(NEW!N1506="COMPLETED",NEW!O1506="COMPLETED")),0,NEW!V1506*24) -> 0 | F86: =IF(NEW!K1506="COMPLETED",0,NEW!W1506*24) -> 0 | G86: =IF(NEW!L1506="COMPLETED",0,NEW!X1506*24) -> 0 | H86: =SUM(E$39:E86) -> 0 | I86: =SUM(F$39:F86) -> 0 | J86: =SUM(G$39:G86) -> 0 | K86: =$B$7+MAX(H86,I86,J86)/$B$5*7 -> 46255 | L86: =IF(ISNUMBER(D86),D86-K86,"") -> -368 | M86: =IF(ISNUMBER(D86),IF(L86<0,"BEHIND",IF(L86<$B$6,"START NOW","ON TRACK")),"no date") -> BEHIND | N86: =IF(ISNUMBER(D86),IF(L86<0,"● LATE",IF(L86<7,"● TIGHT","● OK")),"") -> ● LATE | P86: =IF(ISNUMBER(D86),IF((D86-$B$7)>=7,H86/((D86-$B$7)/7),""),"") | Q86: =IF(ISNUMBER(D86),IF((D86-$B$7)>=7,I86/((D86-$B$7)/7),""),"") | R86: =IF(ISNUMBER(D86),IF((D86-$B$7)>=7,J86/((D86-$B$7)/7),""),"")
A87: =NEW!A1507 -> 1244-4 | B87: =NEW!C1507 -> OPTIMA 7220 SEC#18 TO #19 | C87: =NEW!G1507 -> 45888 | D87: =IF(ISNUMBER(C87),C87-$B$6,"") -> 45887 | E87: =IF(OR(NEW!M1507="COMPLETED",AND(NEW!N1507="COMPLETED",NEW!O1507="COMPLETED")),0,NEW!V1507*24) -> 0 | F87: =IF(NEW!K1507="COMPLETED",0,NEW!W1507*24) -> 0 | G87: =IF(NEW!L1507="COMPLETED",0,NEW!X1507*24) -> 0 | H87: =SUM(E$39:E87) -> 0 | I87: =SUM(F$39:F87) -> 0 | J87: =SUM(G$39:G87) -> 0 | K87: =$B$7+MAX(H87,I87,J87)/$B$5*7 -> 46255 | L87: =IF(ISNUMBER(D87),D87-K87,"") -> -368 | M87: =IF(ISNUMBER(D87),IF(L87<0,"BEHIND",IF(L87<$B$6,"START NOW","ON TRACK")),"no date") -> BEHIND | N87: =IF(ISNUMBER(D87),IF(L87<0,"● LATE",IF(L87<7,"● TIGHT","● OK")),"") -> ● LATE | P87: =IF(ISNUMBER(D87),IF((D87-$B$7)>=7,H87/((D87-$B$7)/7),""),"") | Q87: =IF(ISNUMBER(D87),IF((D87-$B$7)>=7,I87/((D87-$B$7)/7),""),"") | R87: =IF(ISNUMBER(D87),IF((D87-$B$7)>=7,J87/((D87-$B$7)/7),""),"")
A88: =NEW!A1508 -> 1244-5 | B88: =NEW!C1508 -> OPTIMA 7220 SEC#20 TO #22 | C88: =NEW!G1508 -> 45888 | D88: =IF(ISNUMBER(C88),C88-$B$6,"") -> 45887 | E88: =IF(OR(NEW!M1508="COMPLETED",AND(NEW!N1508="COMPLETED",NEW!O1508="COMPLETED")),0,NEW!V1508*24) -> 0 | F88: =IF(NEW!K1508="COMPLETED",0,NEW!W1508*24) -> 0 | G88: =IF(NEW!L1508="COMPLETED",0,NEW!X1508*24) -> 0 | H88: =SUM(E$39:E88) -> 0 | I88: =SUM(F$39:F88) -> 0 | J88: =SUM(G$39:G88) -> 0 | K88: =$B$7+MAX(H88,I88,J88)/$B$5*7 -> 46255 | L88: =IF(ISNUMBER(D88),D88-K88,"") -> -368 | M88: =IF(ISNUMBER(D88),IF(L88<0,"BEHIND",IF(L88<$B$6,"START NOW","ON TRACK")),"no date") -> BEHIND | N88: =IF(ISNUMBER(D88),IF(L88<0,"● LATE",IF(L88<7,"● TIGHT","● OK")),"") -> ● LATE | P88: =IF(ISNUMBER(D88),IF((D88-$B$7)>=7,H88/((D88-$B$7)/7),""),"") | Q88: =IF(ISNUMBER(D88),IF((D88-$B$7)>=7,I88/((D88-$B$7)/7),""),"") | R88: =IF(ISNUMBER(D88),IF((D88-$B$7)>=7,J88/((D88-$B$7)/7),""),"")

Sheet CUSHION
A1: {={NEW!A1:A2904, NEW!B1:B2904, NEW!C1:C2904, NEW!F1:F2904, NEW!M1:M2904, NEW!N1:N2904, NEW!O1:O2904, NEW!P1:P2904, NEW!Q1:Q2904, NEW!R1:R2904, NEW!S1:S2904, NEW!V1:V2904}} -> Order Number | B1: Column 2 | C1: Customer Info | D1: Production Deadline | E1: CUSHIONS | F1: CORTE | G1: SEW | H1: FILLING | I1: FABRIC | J1: FOAM | K1: QTY CUSH | L1: Proj. Hrs Cushion
A2: 1572 | B2: ORDER COMPLETED | C2: BETH COHEN | D2: 46203 | E2: COMPLETED | F2: COMPLETED | G2: COMPLETED | H2: COMPLETED | I2: RECEIVED | J2: RECEIVED | K2: 4
A3: 1591 | B3: ORDER COMPLETED | C3: BRIAN BEVERLY BUFFINI | D3: 46203 | E3: COMPLETED | F3: COMPLETED | G3: COMPLETED | H3: COMPLETED | I3: RECEIVED | J3: RECEIVED | K3: 13
A4: 1593 | B4: ORDER COMPLETED | C4: JENNIFER LAABS | D4: 46203 | E4: COMPLETED | F4: COMPLETED | G4: COMPLETED | H4: COMPLETED | I4: RECEIVED | J4: RECEIVED | K4: 16
A5: 1598 | B5: ORDER COMPLETED | C5: WARR-DAN MAYNARD | D5: 46203 | E5: COMPLETED | F5: COMPLETED | G5: COMPLETED | H5: COMPLETED | I5: RECEIVED | J5: SAME-NEED | K5: 25
A6: 1622 | B6: ORDER COMPLETED | C6: MADONA KAKISH | D6: 46203 | E6: COMPLETED | F6: COMPLETED | G6: COMPLETED | H6: COMPLETED | I6: RECEIVED | J6: NOT REQUIRED | K6: 1
A7: 1639 | B7: READY FOR DELIVERY | C7: ROBYN LAUKIE-CHRIS PARK | D7: 46204 | E7: COMPLETED | F7: COMPLETED | G7: COMPLETED | H7: COMPLETED | I7: RECEIVED | J7: RECEIVED | K7: 1
A8: 1677 | B8: READY FOR DELIVERY | C8: TONY KURTH | D8: 46204 | E8: NOT REQUIRED | F8: NOT REQUIRED | G8: NOT REQUIRED | H8: NOT REQUIRED | I8: NOT REQUIRED | J8: NOT REQUIRED | K8: 0 | L8: 0
A9: 1688 | B9: NEW | C9: ERIC WHITTAKER | D9: 46204 | E9: NOT REQUIRED | F9: NOT REQUIRED | G9: NOT REQUIRED | H9: NOT REQUIRED | I9: NOT REQUIRED | J9: NOT REQUIRED | K9: 0 | L9: 0
A10: 1715 | B10: ORDER COMPLETED | C10: JAIME KIM LIMBER | D10: 46204 | E10: NOT REQUIRED | F10: NOT REQUIRED | G10: NOT REQUIRED | H10: NOT REQUIRED | I10: NOT REQUIRED | J10: NOT REQUIRED | K10: 0 | L10: 0
A11: 1627 | B11: ORDER COMPLETED | C11: BRITTANY MCDOWELL | D11: 46204 | E11: NOT REQUIRED | F11: NOT REQUIRED | G11: NOT REQUIRED | H11: NOT REQUIRED | I11: NOT REQUIRED | J11: NOT REQUIRED | K11: 0
A12: 1708 | B12: ORDER COMPLETED | C12: ECHMEYER, KRISTINA & EVAN | D12: 46204 | E12: NOT REQUIRED | F12: NOT REQUIRED | G12: NOT REQUIRED | H12: NOT REQUIRED | I12: NOT REQUIRED | J12: RECEIVED | K12: 0 | L12: 0
A13: 1491 | B13: NEW | C13: KONA RE-DOING-GENCUSH | D13: 46204 | E13: NOT STARTED | F13: NOT STARTED | G13: NOT STARTED | H13: NOT STARTED | I13: NEED | J13: SAME NEED | K13: 20 | L13: 0
A14: 1662 | B14: ORDER COMPLETED | C14: KERYN GERBER | D14: 46253 | E14: NOT REQUIRED | F14: NOT REQUIRED | G14: NOT REQUIRED | H14: NOT REQUIRED | I14: NOT REQUIRED | J14: NOT REQUIRED | K14: 0 | L14: 0
A15: 1663 | B15: ORDER COMPLETED | C15: DAVE MONTZ | D15: 46204 | E15: COMPLETED | F15: COMPLETED | G15: COMPLETED | H15: COMPLETED | I15: RECEIVED | J15: SAME RECEIVED | K15: 1
A16: 1687 | B16: ORDER COMPLETED | C16: JEN BERGMAN | D16: 46204 | E16: COMPLETED | F16: COMPLETED | G16: COMPLETED | H16: COMPLETED | I16: ON STOCK | J16: SAME RECEIVED | K16: 1
A17: 1702 | B17: ORDER COMPLETED | C17: JILL CUTRONE | D17: 46204 | E17: NOT REQUIRED | F17: NOT REQUIRED | G17: NOT REQUIRED | H17: NOT REQUIRED | I17: NOT REQUIRED | J17: NOT REQUIRED
A18: 1703 | B18: ORDER COMPLETED | C18: MIKE CHAFFEUR | D18: 46204 | E18: COMPLETED | F18: COMPLETED | G18: COMPLETED | H18: COMPLETED | I18: NOT REQUIRED | J18: SAME RECEIVED | K18: 2
A19: 1696 | B19: ORDER COMPLETED | C19: LISA FORD | D19: 46205 | E19: COMPLETED | F19: COMPLETED | G19: COMPLETED | H19: COMPLETED | I19: ON STOCK | J19: RECEIVED | K19: 1
A20: 1704 | B20: ORDER COMPLETED | C20: LINDSAY MADERIA WALSH | D20: 46205 | E20: COMPLETED | F20: COMPLETED | G20: COMPLETED | H20: NOT REQUIRED | I20: RECEIVED | J20: NOT REQUIRED | K20: 9
A21: 1638 | B21: ORDER COMPLETED | C21: DIANE GALATI | D21: 46209 | E21: NOT REQUIRED | F21: NOT REQUIRED | G21: NOT REQUIRED | H21: NOT REQUIRED | I21: NOT REQUIRED | J21: NOT REQUIRED | K21: 0
A22: 1605 | B22: ORDER COMPLETED | C22: DEANNE SPRENGER | D22: 46210 | E22: COMPLETED | F22: COMPLETED | G22: COMPLETED | H22: COMPLETED | I22: NOT REQUIRED | J22: RECEIVED | K22: 1
A23: 1643 | B23: ORDER COMPLETED | C23: MEGAN KELLY ADD-ON | D23: 46210 | E23: COMPLETED | F23: COMPLETED | G23: COMPLETED | H23: COMPLETED | I23: IN STOCK | J23: RECEIVED | K23: 5
A24: 1521 | B24: ORDER COMPLETED | C24: RUSH SHOWROOM SWING CUSHION | D24: 46212 | E24: COMPLETED | F24: COMPLETED | G24: COMPLETED | H24: COMPLETED | I24: IN STOCK | J24: RECEIVED | K24: 1
A25: 1502 | B25: ORDER COMPLETED | C25: ROB ROY | D25: 46217 | E25: COMPLETED | F25: COMPLETED | G25: COMPLETED | H25: COMPLETED | I25: RECEIVED | J25: RECEIVED | K25: 18
A26: 1573 | B26: ORDER COMPLETED | C26: SOLANA BEACH SHOWROOM 4-29 | D26: 46217 | E26: COMPLETED | F26: COMPLETED | G26: COMPLETED | H26: COMPLETED | I26: RECEIVED | J26: RECEIVED | K26: 4
A27: 1576 | B27: ORDER COMPLETED | C27: RICHARD AGUILAR | D27: 46217 | E27: COMPLETED | F27: COMPLETED | G27: COMPLETED | H27: COMPLETED | I27: RECEIVED | J27: RECEIVED | K27: 7
A28: 1604 | B28: ORDER COMPLETED | C28: MELANIE SPAHN | D28: 46217 | E28: NOT REQUIRED | F28: NOT REQUIRED | G28: NOT REQUIRED | H28: NOT REQUIRED | I28: NOT REQUIRED | J28: NOT REQUIRED | K28: 0
A29: 1610 | B29: ORDER COMPLETED | C29: PAUL DICOSMO-REDO | D29: 46217 | E29: COMPLETED | F29: COMPLETED | G29: COMPLETED | H29: COMPLETED | I29: RECEIVED | J29: RECEIVED | K29: 2
... A32: 1624 | B32: ORDER COMPLETED | C32: RAQUEL-JASON NORTON | D32: 46217 | E32: NOT REQUIRED | F32: NOT REQUIRED | G32: NOT REQUIRED | H32: NOT REQUIRED | I32: NOT REQUIRED | J32: NOT REQUIRED | K32: 0
A33: 1651 | B33: ORDER COMPLETED | C33: CHAD | D33: 46217 | E33: NOT REQUIRED | F33: NOT REQUIRED | G33: NOT REQUIRED | H33: NOT REQUIRED | I33: NOT REQUIRED | J33: NOT REQUIRED
A34: 1653 | B34: ORDER COMPLETED | C34: CA AMAR TAKHUR | D34: 46217 | E34: NOT REQUIRED | F34: NOT REQUIRED | G34: NOT REQUIRED | H34: NOT REQUIRED | I34: NOT REQUIRED | J34: NOT REQUIRED | K34: 0
A35: 1608 | B35: ORDER COMPLETED | C35: ANDREA SYDENHAM-SERVICE | D35: 46218 | E35: NOT REQUIRED | F35: NOT REQUIRED | G35: NOT REQUIRED | H35: NOT REQUIRED | I35: NOT REQUIRED | J35: NOT REQUIRED | K35: 0
A36: 1617 | B36: ORDER COMPLETED | C36: REDO SHELLY GROTHAUS | D36: 46218 | E36: COMPLETED | F36: COMPLETED | G36: COMPLETED | H36: COMPLETED | I36: IN STOCK | J36: SAME-READY | K36: 2
A37: 1654 | B37: ORDER COMPLETED | C37: CA Edisoon Reynoso | D37: 46218 | E37: NOT REQUIRED | F37: NOT REQUIRED | G37: NOT REQUIRED | H37: NOT REQUIRED | I37: NOT REQUIRED | J37: NOT REQUIRED | K37: 0
A38: 1607 | B38: ORDER COMPLETED | C38: STEPHANIE EVERS-SERVICE | D38: 46219 | E38: NOT REQUIRED | F38: NOT REQUIRED | G38: NOT REQUIRED | H38: NOT REQUIRED | I38: NOT REQUIRED | J38: NOT REQUIRED | K38: 0
A39: 1669 | B39: ORDER COMPLETED | C39: HAMID SHOWROOM 7-17-26 | D39: 46219 | E39: COMPLETED | F39: COMPLETED | G39: COMPLETED | H39: COMPLETED | I39: IN STOCK | J39: RECEIVED | K39: 8
A40: 1546 | B40: ORDER COMPLETED | C40: JIM-CAROL LAUB | D40: 46223 | E40: COMPLETED | F40: COMPLETED | G40: COMPLETED | H40: COMPLETED | I40: RECEIVED | J40: RECEIVED | K40: 19
A41: 1646 | B41: ORDER COMPLETED | C41: JOE REDMOND III | D41: 46225 | E41: COMPLETED | F41: COMPLETED | G41: COMPLETED | H41: COMPLETED | I41: RECEIVED | J41: RECEIVED | K41: 6
A42: 1626 | B42: ORDER COMPLETED | C42: ERIC WHITTAKER | D42: 46226 | E42: COMPLETED | F42: COMPLETED | G42: COMPLETED | H42: COMPLETED | I42: RECEIVED | J42: RECEIVED | K42: 62
A43: 1623 | B43: ORDER COMPLETED | C43: DEBBIE KILIAN | D43: 46227 | E43: COMPLETED | F43: COMPLETED | G43: COMPLETED | H43: COMPLETED | I43: RECEIVED | J43: RECEIVED | K43: 28
A44: 1655 | B44: ORDER COMPLETED | C44: OPTIMA CHICAGO FINAL | D44: 46227 | E44: NOT REQUIRED | F44: NOT REQUIRED | G44: NOT REQUIRED | H44: NOT REQUIRED | I44: NOT REQUIRED | J44: NOT REQUIRED | K44: 0
A45: 1670 | B45: ORDER COMPLETED | C45: STEPHANIE LALLEY | D45: 46227 | E45: NOT REQUIRED | F45: NOT REQUIRED | G45: NOT REQUIRED | H45: NOT REQUIRED | I45: NOT REQUIRED | J45: NOT REQUIRED | K45: 0
A46: 1616 | B46: ORDER COMPLETED | C46: JILL CUTRONE | D46: 46230 | E46: COMPLETED | F46: COMPLETED | G46: COMPLETED | H46: COMPLETED | I46: RECEIVED | J46: RECEIVED | K46: 80 | L46: 3.6076389
A47: 1628 | B47: ORDER COMPLETED | C47: JOHN MARTELL | D47: 46230 | E47: COMPLETED | F47: COMPLETED | G47: COMPLETED | H47: COMPLETED | I47: RECEIVED | J47: RECEIVED | K47: 2
A48: 1615 | B48: ORDER COMPLETED | C48: KORRENA GLEN | D48: 46231 | E48: COMPLETED | F48: COMPLETED | G48: COMPLETED | H48: COMPLETED | I48: RECEIVED | J48: RECEIVED | K48: 11 | L48: 0.625
A49: 1634 | B49: ORDER COMPLETED | C49: NIKKI PERES | D49: 46231 | E49: COMPLETED | F49: COMPLETED | G49: COMPLETED | H49: COMPLETED | I49: RECEIVED | J49: RECEIVED | K49: 4 | L49: 0.20833333
A50: 1656 | B50: ORDER COMPLETED | C50: LINDA SALKOW | D50: 46231 | E50: COMPLETED | F50: COMPLETED | G50: COMPLETED | H50: COMPLETED | I50: RECEIVED | J50: RECEIVED | K50: 4 | L50: 0.041666667
A51: 1660 | B51: ORDER COMPLETED | C51: NIKKI PERES - HUNTER T TABLES | D51: 46231 | E51: NOT REQUIRED | F51: NOT REQUIRED | G51: NOT REQUIRED | H51: NOT REQUIRED | I51: NOT REQUIRED | J51: NOT REQUIRED | K51: 0
A52: 1620 | B52: ORDER COMPLETED | C52: JENNIFER JOHNSON | D52: 46232 | E52: COMPLETED | F52: COMPLETED | G52: COMPLETED | H52: COMPLETED | I52: RECEIVED | J52: SAME RECEIVED | K52: 2
A53: 1631 | B53: ORDER COMPLETED | C53: JEN BERGMAN | D53: 46232 | E53: COMPLETED | F53: COMPLETED | G53: COMPLETED | H53: COMPLETED | I53: RECEIVED | J53: SAME RECEIVED | K53: 39 | L53: 1.3958333
A54: 1618 | B54: ORDER COMPLETED | C54: MIKE CHAFFEUR | D54: 46233 | E54: COMPLETED | F54: COMPLETED | G54: COMPLETED | H54: COMPLETED | I54: RECEIVED | J54: RECEIVED | K54: 37 | L54: 1.21875
A55: 1606 | B55: ORDER COMPLETED | C55: CORINA COVACIU-SERVICE | D55: 46234 | E55: NOT REQUIRED | F55: NOT REQUIRED | G55: NOT REQUIRED | H55: NOT REQUIRED | I55: NOT REQUIRED | J55: NOT REQUIRED | K55: 0
A56: 1619 | B56: ORDER COMPLETED | C56: LISA FORD | D56: 46234 | E56: COMPLETED | F56: COMPLETED | G56: COMPLETED | H56: COMPLETED | I56: RECEIVED | J56: RECEIVED | K56: 13
A57: 1633 | B57: ORDER COMPLETED | C57: KIRK JOHNS | D57: 46234 | E57: COMPLETED | F57: COMPLETED | G57: COMPLETED | H57: COMPLETED | I57: RECEIVED | J57: RECEIVED | K57: 2 | L57: 0.60416667
A58: 1647 | B58: ORDER COMPLETED | C58: LINDSAY MADERIA WALSH | D58: 46234 | E58: COMPLETED | F58: COMPLETED | G58: COMPLETED | H58: COMPLETED | I58: RECEIVED | J58: RECEIVED | K58: 9
A59: 1648 | B59: ORDER COMPLETED | C59: MELISSA FISCHER | D59: 46234 | E59: COMPLETED | F59: COMPLETED | G59: COMPLETED | H59: COMPLETED | I59: RECEIVED | J59: RECEIVED | K59: 5
A60: 1671 | B60: ORDER COMPLETED | C60: CAROL LAUB RUSH | D60: 46234 | E60: COMPLETED | F60: COMPLETED | G60: COMPLETED | H60: COMPLETED | I60: RECEIVED | J60: RECEIVED | K60: 12 | L60: 0.27777778
A61: 1683 | B61: ORDER COMPLETED | C61: CAROL LAUB RUSH | D61: 46234 | E61: NOT REQUIRED | F61: NOT REQUIRED | G61: NOT REQUIRED | H61: NOT REQUIRED | I61: NOT REQUIRED | J61: NOT REQUIRED | K61: 0
A62: 1637 | B62: ORDER COMPLETED | C62: DENISE STEINKIRCHNER | D62: 46237 | E62: COMPLETED | F62: COMPLETED | G62: COMPLETED | H62: COMPLETED | I62: RECEIVED | J62: RECEIVED | K62: 1 | L62: 0.375
A63: 1664 | B63: ORDER COMPLETED | C63: TONY SCHINDLER | D63: 46237 | E63: NOT REQUIRED | F63: NOT REQUIRED | G63: NOT REQUIRED | H63: NOT REQUIRED | I63: NOT REQUIRED | J63: NOT REQUIRED | K63: 0
A64: 1689 | B64: ORDER COMPLETED | C64: KIRK JOHNS | D64: 46237 | E64: NOT REQUIRED | F64: NOT REQUIRED | G64: NOT REQUIRED | H64: NOT REQUIRED | I64: NOT REQUIRED | J64: NOT REQUIRED | K64: 0
A65: 1583 | B65: ORDER COMPLETED | C65: MELANIE DEPATIE WARRANTY | D65: 46238 | E65: COMPLETED | F65: COMPLETED | G65: COMPLETED | H65: COMPLETED | I65: RECEIVED | J65: SAME RECEIVED | K65: 13
A66: 1583 | B66: ORDER COMPLETED | C66: MELANIE DEPATIE NEW SECTION | D66: 46238 | E66: COMPLETED | F66: COMPLETED | G66: COMPLETED | H66: COMPLETED | I66: RECEIVED | J66: RECEIVED | K66: 14 | L66: 0.49652778
A67: 1642 | B67: ORDER COMPLETED | C67: CATHY-JIM SURRAT | D67: 46239 | E67: COMPLETED | F67: COMPLETED | G67: COMPLETED | H67: COMPLETED | I67: RECEIVED | J67: RECEIVED | K67: 5
A68: 1661 | B68: ORDER COMPLETED | C68: PERKINS COIE LLP-WARRANTY | D68: 46239 | E68: COMPLETED | F68: COMPLETED | G68: COMPLETED | H68: COMPLETED | I68: ON STOCK | J68: SAME RECEIVED | K68: 4
A69: 1705 | B69: ORDER COMPLETED | C69: JOHN MARTELL REDO | D69: 46239 | E69: NOT REQUIRED | F69: NOT REQUIRED | G69: NOT REQUIRED | H69: NOT REQUIRED | I69: NOT REQUIRED | J69: NOT REQUIRED
A70: 1698 | B70: ORDER COMPLETED | C70: OPTIMA 7220 BARSTOOL REUPHOLSTERY | D70: 46244 | E70: COMPLETED | F70: COMPLETED | G70: COMPLETED | H70: COMPLETED | I70: RECEIVED | J70: SAME RECEIVED | K70: 12
A71: 1713 | B71: ORDER COMPLETED | C71: OPTIMA 7220 RUSH DOWNSTAIRS | D71: 46244 | E71: COMPLETED | F71: COMPLETED | G71: COMPLETED | H71: IN PROGRESS | I71: ON STOCK | J71: SAME RECEIVED | K71: 49 | L71: 2.2958333
A72: 1657 | B72: ORDER COMPLETED | C72: TIFFANY HERTER | D72: 46245 | E72: COMPLETED | F72: COMPLETED | G72: COMPLETED | H72: COMPLETED | I72: RECEIVED | J72: RECEIVED | K72: 34
A73: 1684 | B73: ORDER COMPLETED | C73: OPTIMA 7140 FRAMES PHASE I | D73: 46245 | E73: NOT REQUIRED | F73: NOT REQUIRED | G73: NOT REQUIRED | H73: NOT REQUIRED | I73: NOT REQUIRED | J73: NOT REQUIRED | K73: 0
A74: 1641 | B74: ORDER COMPLETED | C74: DEBBIE BATTISTA | D74: 46246 | E74: COMPLETED | F74: COMPLETED | G74: COMPLETED | H74: COMPLETED | I74: RECEIVED | J74: RECEIVED | K74: 1
A75: 1650 | B75: ORDER COMPLETED | C75: CAROL COLOMBO | D75: 46246 | E75: COMPLETED | F75: COMPLETED | G75: COMPLETED | H75: COMPLETED | I75: RECEIVED | J75: RECEIVED | K75: 12
A76: 1684 | B76: ORDER COMPLETED | C76: OPTIMA 7140 FRAMES PHASE II | D76: 46248 | E76: NOT REQUIRED | F76: NOT REQUIRED | G76: NOT REQUIRED | H76: NOT REQUIRED | I76: NOT REQUIRED | J76: NOT REQUIRED | K76: 0 | L76: 0
A77: 1714 | B77: ORDER COMPLETED | C77: CHERYL BURK | D77: 46253 | E77: NOT REQUIRED | F77: NOT REQUIRED | G77: NOT REQUIRED | H77: NOT REQUIRED | I77: NOT REQUIRED | J77: NOT REQUIRED | K77: 0 | L77: 0
A78: 1684 | B78: NEW | C78: OPTIMA 7140 PHASE III | D78: 46254 | E78: IN PROGRESS | F78: IN PROGRESS | G78: IN PROGRESS | H78: IN PROGRESS | I78: RECEIVED | J78: RECEIVED | K78: 0 | L78: 0.70833333
A79: 1635 | B79: ORDER COMPLETED | C79: KATHLEEN WIT | D79: 46254 | E79: COMPLETED | F79: COMPLETED | G79: COMPLETED | H79: COMPLETED | I79: RECEIVED | J79: RECEIVED | L79: 0.125
A80: 1668 | B80: ORDER COMPLETED | C80: SHARIF & MALIHE | D80: 46254 | E80: COMPLETED | F80: COMPLETED | G80: COMPLETED | H80: COMPLETED | I80: ON STOCK | J80: RECEIVED | L80: 0.083333333
A81: 1679 | B81: READY FOR DELIVERY | C81: BETH HOFFMAN | D81: 46254 | E81: NOT REQUIRED | F81: NOT REQUIRED | G81: NOT REQUIRED | H81: NOT REQUIRED | I81: NOT REQUIRED | J81: NOT REQUIRED | K81: 0 | L81: 0
A82: 1690 | B82: ORDER COMPLETED | C82: SOLONA BEACH SHOWROOM | D82: 46254 | E82: COMPLETED | F82: COMPLETED | G82: COMPLETED | H82: COMPLETED | I82: RECEIVED | J82: RECEIVED | L82: 0.25
A83: 1693 | B83: READY FOR DELIVERY | C83: DAN AMBROSE | D83: 46254 | E83: COMPLETED | F83: COMPLETED | G83: COMPLETED | H83: COMPLETED | I83: RECEIVED | J83: RECEIVED | K83: 2 | L83: 1
A84: 1578-S | B84: READY FOR DELIVERY | C84: DAN AMBROSE | D84: 46254 | E84: NOT REQUIRED | F84: NOT REQUIRED | G84: NOT REQUIRED | H84: NOT REQUIRED | I84: NOT REQUIRED | J84: NOT REQUIRED | K84: 0 | L84: 0
A85: 1726 | B85: ORDER COMPLETED | C85: CAROL COLOMBO | D85: 46254 | E85: NOT REQUIRED | F85: NOT REQUIRED | G85: NOT REQUIRED | H85: NOT REQUIRED | I85: NOT REQUIRED | J85: NOT REQUIRED
A86: 1707 | B86: NEW | C86: SCOTTSDALE SHOWROOM | D86: 46258 | E86: IN PROGRESS | F86: IN PROGRESS | G86: IN PROGRESS | H86: IN PROGRESS | I86: RECEIVED | J86: RECEIVED | K86: 30 | L86: 0.375
A87: 1673 | B87: NEW | C87: CYNTHIA MANN | D87: 46258 | E87: IN PROGRESS | F87: COMPLETED | G87: COMPLETED | H87: IN PROGRESS | I87: RECEIVED | J87: RECEIVED | K87: 8 | L87: 0.25
A88: 1682 | B88: READY FOR DELIVERY | C88: JOHN BUTZ | D88: 46259 | E88: NOT REQUIRED | F88: NOT REQUIRED | G88: NOT REQUIRED | H88: NOT REQUIRED | I88: NOT REQUIRED | J88: NOT REQUIRED | K88: 0 | L88: 0
A89: 1685 | B89: NEW | C89: OPTIMA 7190 FRAMES PHASE I | D89: 46259 | E89: NOT REQUIRED | F89: NOT REQUIRED | G89: NOT REQUIRED | H89: NOT REQUIRED | I89: NOT REQUIRED | J89: NOT REQUIRED | L89: 0
A90: 1680 | B90: READY FOR DELIVERY | C90: SHERI RODGERS | D90: 46261 | E90: NOT REQUIRED | F90: NOT REQUIRED | G90: NOT REQUIRED | H90: NOT REQUIRED | I90: NOT REQUIRED | J90: NOT REQUIRED | K90: 0 | L90: 0
A91: 1694 | B91: NEW | C91: MIKE GANTZEL | D91: 46261 | E91: COMPLETED | F91: COMPLETED | G91: COMPLETED | H91: COMPLETED | I91: RECEIVED | J91: RECEIVED | K91: 10 | L91: 0.375
A92: 1644 | B92: READY FOR DELIVERY | C92: CHRISTINE WILSON | D92: 46265 | E92: COMPLETED | F92: COMPLETED | G92: COMPLETED | H92: COMPLETED | I92: RECEIVED | J92: RECEIVED | L92: 0.25
A93: 1681 | B93: NEW | C93: DAVE KRISTEN ANDERSON | D93: 46265 | E93: IN PROGRESS | F93: IN PROGRESS | G93: IN PROGRESS | H93: NOT STARTED | I93: RECEIVED | J93: PARTIAL ORDERED | K93: 86 | L93: 0.83333333
A94: 1701 | B94: READY FOR DELIVERY | C94: MADONNA KAKISH | D94: 46265 | E94: NOT REQUIRED | F94: NOT REQUIRED | G94: NOT REQUIRED | H94: NOT REQUIRED | I94: NOT REQUIRED | J94: NOT REQUIRED | K94: 0 | L94: 0
A95: 1548 | B95: READY FOR DELIVERY | C95: STEVE-MARGUERITE MORRELL | D95: 46266 | E95: COMPLETED | F95: COMPLETED | G95: COMPLETED | H95: COMPLETED | I95: RECEIVED | J95: RECEIVED | K95: 8
A96: 1685 | B96: NEW | C96: OPTIMA 7190 FRAMES PHASE II | D96: 46266 | E96: NOT REQUIRED | F96: NOT REQUIRED | G96: NOT REQUIRED | H96: NOT REQUIRED | I96: NOT REQUIRED | J96: NOT REQUIRED | L96: 0
A97: 1667 | B97: READY FOR DELIVERY | C97: STEPHEN HAKAMI | D97: 46267 | E97: COMPLETED | F97: COMPLETED | G97: COMPLETED | H97: COMPLETED | I97: ON STOCK | J97: RECEIVED | K97: 6 | L97: 0.59027778
A98: 1723 | B98: NEW | C98: GIL KONFINO | D98: 46268 | E98: NOT STARTED | F98: NOT STARTED | G98: NOT STARTED | H98: NOT STARTED | I98: ORDERED | J98: NEED | K98: 6 | L98: 0.41666667
A99: 1716 | B99: NEW | C99: JENNIFER JOHNSON | D99: 46269 | E99: NOT STARTED | F99: NOT STARTED | G99: NOT STARTED | H99: NOT STARTED | I99: RECEIVED | J99: SAME NEED | L99: 0.041666667
A100: 1645 | B100: NEW | C100: ERIN CRAVENS | D100: 46269 | E100: NOT STARTED | F100: NOT STARTED | G100: NOT STARTED | H100: NOT STARTED | I100: RECEIVED | J100: NEED
A101: 1695 | B101: NEW | C101: JOSH DORKIN | D101: 46272 | E101: NOT STARTED | F101: NOT STARTED | G101: NOT STARTED | H101: NOT STARTED | I101: RECEIVED | J101: NEED | L101: 0.41666667
A102: 1700 | B102: NEW | C102: TINA FRANTZ | D102: 46272 | E102: NOT STARTED | F102: NOT STARTED | G102: NOT STARTED | H102: NOT STARTED | I102: RECEIVED | J102: NEED | L102: 0.125
...

Sheet ACCESORIOS
A1: {={NEW!A1:A1982, NEW!B1:B1982, NEW!C1:C1982, NEW!F1:F1982, NEW!Y1:Y1982, NEW!Z1:Z1982, NEW!AA1:AA1982, NEW!AB1:AB1982, NEW!AC1:AC1982}} -> Order Number | B1: Column 2 | C1: Customer Info | D1: Production Deadline | E1: Covers | F1: Umbrella | G1: Tenjam/Others | H1: Firepit System | I1: Delivery Address
A2: 1572 | B2: ORDER COMPLETED | C2: BETH COHEN | D2: 46203 | E2: NOT REQUIRED | F2: NOT REQUIRED | G2: NOT REQUIRED | H2: NOT REQUIRED | I2: 10604 Arista Ln, Fountain Hills, AZ 85268, USA
A3: 1591 | B3: ORDER COMPLETED | C3: BRIAN BEVERLY BUFFINI | D3: 46203 | E3: NOT REQUIRED | F3: RECEIVED | G3: NOT REQUIRED | H3: NOT REQUIRED | I3: CALIFORNIA
A4: 1593 | B4: ORDER COMPLETED | C4: JENNIFER LAABS | D4: 46203 | E4: NOT REQUIRED | F4: RECEIVED | G4: NOT REQUIRED | H4: RECEIVED | I4: 484 Halcyon Pl, Bethel Island, CA 94511
A5: 1598 | B5: ORDER COMPLETED | C5: WARR-DAN MAYNARD | D5: 46203 | E5: NOT REQUIRED | F5: NOT REQUIRED | G5: NOT REQUIRED | H5: NOT REQUIRED | I5: 20408 E Cloud Rd, Queen Creek, AZ 85142, USA
A6: 1622 | B6: ORDER COMPLETED | C6: MADONA KAKISH | D6: 46203 | E6: NOT REQUIRED | F6: NOT REQUIRED | G6: NOT REQUIRED | H6: NOT REQUIRED | I6: CALIFORNIA
A7: 1639 | B7: READY FOR DELIVERY | C7: ROBYN LAUKIE-CHRIS PARK | D7: 46204 | E7: NOT REQUIRED | F7: NOT REQUIRED | G7: NOT REQUIRED | H7: NOT REQUIRED | I7: 6352 Arroyo Rd, Cave Creek, AZ 85331, USA
A8: 1677 | B8: READY FOR DELIVERY | C8: TONY KURTH | D8: 46204 | E8: NOT REQUIRED | F8: NOT REQUIRED | G8: NOT REQUIRED | H8: NOT REQUIRED | I8: PICKUP
A9: 1688 | B9: NEW | C9: ERIC WHITTAKER | D9: 46204 | E9: ORDERED | F9: NOT REQUIRED | G9: NOT REQUIRED | H9: NOT REQUIRED | I9: 5400 E Valle Vista Rd #6, Phoenix, AZ 85018
A10: 1715 | B10: ORDER COMPLETED | C10: JAIME KIM LIMBER | D10: 46204 | E10: NOT REQUIRED | F10: NOT REQUIRED | G10: NOT REQUIRED | H10: NOT REQUIRED | I10: 4202 N 58th St PHOENIX AZ 85018
A11: 1627 | B11: ORDER COMPLETED | C11: BRITTANY MCDOWELL | D11: 46204 | E11: RECEIVED | F11: NOT REQUIRED | G11: NOT REQUIRED | H11: NOT REQUIRED | I11: 8404 N 75th St, Scottsdale, AZ 85258, USA
A12: 1708 | B12: ORDER COMPLETED | C12: ECHMEYER, KRISTINA & EVAN | D12: 46204 | E12: NOT REQUIRED | F12: NOT REQUIRED | G12: NOT REQUIRED | H12: NOT REQUIRED | I12: 8321 Baseline Rd, Boulder, CO 80303, USA
A13: 1491 | B13: NEW | C13: KONA RE-DOING-GENCUSH | D13: 46204 | E13: NOT REQUIRED | F13: NOT REQUIRED | G13: NOT REQUIRED | H13: NOT REQUIRED | I13: 72-300 Maheawalu Drive, Kailua-Kona HI 96740
... A70: 1698 | B70: ORDER COMPLETED | C70: OPTIMA 7220 BARSTOOL REUPHOLSTERY | D70: 46244 | E70: NOT REQUIRED | F70: NOT REQUIRED | G70: NOT REQUIRED | H70: NOT REQUIRED | I70: OPTIMA 7220
A71: 1713 | B71: ORDER COMPLETED | C71: OPTIMA 7220 RUSH DOWNSTAIRS | D71: 46244 | E71: NOT REQUIRED | F71: NOT REQUIRED | G71: NOT REQUIRED | H71: NOT REQUIRED
A72: 1657 | B72: ORDER COMPLETED | C72: TIFFANY HERTER | D72: 46245 | E72: NOT REQUIRED | F72: NOT REQUIRED | G72: NOT REQUIRED | H72: NOT REQUIRED | I72: 28119 N. 109th Way
A73: 1684 | B73: ORDER COMPLETED | C73: OPTIMA 7140 FRAMES PHASE I | D73: 46245 | E73: NOT REQUIRED | F73: NOT REQUIRED | G73: NOT REQUIRED | H73: NOT REQUIRED | I73: OPTIMA 7140
A74: 1641 | B74: ORDER COMPLETED | C74: DEBBIE BATTISTA | D74: 46246 | E74: RECEIVED | F74: NOT REQUIRED | G74: NOT REQUIRED | H74: NOT REQUIRED | I74: 1175 E. Copper Hollow Way, Queen Creek, AZ 85740
A75: 1650 | B75: ORDER COMPLETED | C75: CAROL COLOMBO | D75: 46246 | E75: NOT REQUIRED | F75: NOT REQUIRED | G75: NOT REQUIRED | H75: NOT REQUIRED | I75: 5633 N. Royal Circle, Paradise Valley, AZ
A76: 1684 | B76: ORDER COMPLETED | C76: OPTIMA 7140 FRAMES PHASE II | D76: 46248 | E76: NOT REQUIRED | F76: NOT REQUIRED | G76: NOT REQUIRED | H76: NOT REQUIRED | I76: OPTIMA 7140
A77: 1714 | B77: ORDER COMPLETED | C77: CHERYL BURK | D77: 46253 | E77: NOT REQUIRED | F77: NOT REQUIRED | G77: NOT REQUIRED | H77: NOT REQUIRED | I77: SCOTTSDALE SHOWROOM
A78: 1684 | B78: NEW | C78: OPTIMA 7140 PHASE III | D78: 46254 | E78: NOT REQUIRED | F78: NOT REQUIRED | G78: NOT REQUIRED | H78: NOT REQUIRED | I78: OPTIMA 7140
A79: 1635 | B79: ORDER COMPLETED | C79: KATHLEEN WIT | D79: 46254 | E79: NOT REQUIRED | F79: NEED | G79: NOT REQUIRED | H79: NOT REQUIRED | I79: 157 Mozart Ave , CA 92007
A80: 1668 | B80: ORDER COMPLETED | C80: SHARIF & MALIHE | D80: 46254 | E80: NOT REQUIRED | F80: NOT REQUIRED | G80: NOT REQUIRED | H80: NOT REQUIRED | I80: 4832 Fairport Way, San Diego, CA 92130, USA
A81: 1679 | B81: READY FOR DELIVERY | C81: BETH HOFFMAN | D81: 46254 | E81: NOT REQUIRED | F81: NOT REQUIRED | G81: NOT REQUIRED | H81: NOT REQUIRED | I81: 5895 Blazing Star Ln, San Diego, CA 92130, USA
A82: 1690 | B82: ORDER COMPLETED | C82: SOLONA BEACH SHOWROOM | D82: 46254 | E82: NOT REQUIRED | F82: NOT REQUIRED | G82: NOT REQUIRED | H82: NOT REQUIRED | I82: SOLONA BEACH SHOWROOM
A83: 1693 | B83: READY FOR DELIVERY | C83: DAN AMBROSE | D83: 46254 | E83: NOT REQUIRED | F83: NOT REQUIRED | G83: NOT REQUIRED | H83: NOT REQUIRED | I83: 26 9th St HER,OSA BEACH CA
A84: 1578-S | B84: READY FOR DELIVERY | C84: DAN AMBROSE | D84: 46254 | E84: NOT REQUIRED | F84: NOT REQUIRED | G84: NOT REQUIRED | H84: NOT REQUIRED | I84: 26 9th St HER,OSA BEACH CA
A85: 1726 | B85: ORDER COMPLETED | C85: CAROL COLOMBO | D85: 46254 | E85: NOT REQUIRED | F85: NOT REQUIRED | G85: NOT REQUIRED | H85: NOT REQUIRED
A86: 1707 | B86: NEW | C86: SCOTTSDALE SHOWROOM | D86: 46258 | E86: NOT REQUIRED | F86: NOT REQUIRED | G86: NOT REQUIRED | H86: NOT REQUIRED | I86: SCOTTSDALE SHOWROOM
A87: 1673 | B87: NEW | C87: CYNTHIA MANN | D87: 46258 | E87: NOT REQUIRED | F87: NOT REQUIRED | G87: NOT REQUIRED | H87: NOT REQUIRED | I87: 556 W. Moon Valley Drive, Phoenix, AZ
A88: 1682 | B88: READY FOR DELIVERY | C88: JOHN BUTZ | D88: 46259 | E88: NOT REQUIRED | F88: NOT REQUIRED | G88: NOT REQUIRED | H88: NOT REQUIRED | I88: 2926 North Valencia Lane
A89: 1685 | B89: NEW | C89: OPTIMA 7190 FRAMES PHASE I | D89: 46259 | E89: NOT REQUIRED | F89: NOT REQUIRED | G89: NOT REQUIRED | H89: NOT REQUIRED | I89: OPTIMA 7190
A90: 1680 | B90: READY FOR DELIVERY | C90: SHERI RODGERS | D90: 46261 | E90: NOT REQUIRED | F90: NOT REQUIRED | G90: NOT REQUIRED | H90: NOT REQUIRED | I90: 1802 E Phoenix St Payson AZ 85541 / PICK UP FROM SCOTTSDALE SHOWROOM
A91: 1694 | B91: NEW | C91: MIKE GANTZEL | D91: 46261 | E91: NOT REQUIRED | F91: NOT REQUIRED | G91: NOT REQUIRED | H91: NOT REQUIRED | I91: 4099 East Meadowview Dr Gilbert Az 85298
A92: 1644 | B92: READY FOR DELIVERY | C92: CHRISTINE WILSON | D92: 46265 | E92: NOT REQUIRED | F92: NOT REQUIRED | G92: NOT REQUIRED | H92: NOT REQUIRED | I92: 1854 DOWNS ST OCEAN SIDE CA 92054
A93: 1681 | B93: NEW | C93: DAVE KRISTEN ANDERSON | D93: 46265 | E93: NOT REQUIRED | F93: NEED | G93: NOT REQUIRED | H93: NOT REQUIRED | I93: 6343 Clubhouse Dr, Rancho Santa Fe, CA 92091, USA
A94: 1701 | B94: READY FOR DELIVERY | C94: MADONNA KAKISH | D94: 46265 | E94: NOT REQUIRED | F94: NOT REQUIRED | G94: NOT REQUIRED | H94: NOT REQUIRED | I94: 32090 Via Bella Vita TEMECULA CA
A95: 1548 | B95: READY FOR DELIVERY | C95: STEVE-MARGUERITE MORRELL | D95: 46266 | E95: NOT REQUIRED | F95: NOT REQUIRED | G95: NOT REQUIRED | H95: NOT REQUIRED | I95: 16734 N Mountain Parkway, FOUNTAIN HILLS
A96: 1685 | B96: NEW | C96: OPTIMA 7190 FRAMES PHASE II | D96: 46266 | E96: NOT REQUIRED | F96: NOT REQUIRED | G96: NOT REQUIRED | H96: NOT REQUIRED | I96: OPTIMA 7190
A97: 1667 | B97: READY FOR DELIVERY | C97: STEPHEN HAKAMI | D97: 46267 | E97: NOT REQUIRED | F97: NOT REQUIRED | G97: NOT REQUIRED | H97: NOT REQUIRED | I97: 6026 North 77th Place SCOTTSDALE AZ 85250
... A129: 1675 | B129: NEW | C129: MAI YAHN | D129: 46309 | E129: NOT REQUIRED | F129: NEED | G129: NOT REQUIRED | H129: RECEIVED | I129: 1688 E. DESERT GARDEN DRIVE TUCSON, AZ 85743
A130: 1712 | B130: READY FOR DELIVERY | C130: SUZANNE HIPPEL | D130: HOLD | E130: NOT REQUIRED | F130: NOT REQUIRED | G130: NOT REQUIRED | H130: NOT REQUIRED | I130: 4323 E. Upper Ridge Way, Paradise Valley, Az
A131: 1629 | B131: NEW | C131: FRED HERMANN | D131: HOLD | E131: NOT REQUIRED | F131: NOT REQUIRED | G131: NOT REQUIRED | H131: NOT REQUIRED | I131: 11204 E Moonlight Canyon, Scottsdale, AZ 85255
A132: 1632 | B132: NEW | C132: LINDA FRIESER | D132: HOLD | E132: NOT REQUIRED | F132: NOT REQUIRED | G132: NOT REQUIRED | H132: NOT REQUIRED | I132: FACTORY DROP OFF / PICK UP
A133: 1658 | B133: NEW | C133: ABIGAIL GAGE | D133: HOLD | E133: NEED | F133: NOT REQUIRED | G133: NOT REQUIRED | H133: NOT REQUIRED | I133: 18121 East Juniper Oaks Drive Rio Verde AZ
A134: 1676 | B134: NEW | C134: TAMMY BONE | D134: HOLD | E134: NOT REQUIRED | F134: NOT REQUIRED | G134: NOT REQUIRED | H134: RECEIVED | I134: 7167 E Rancho Vista Driuve #1012
A135: 1728 | B135: NEW | C135: KEN & WHITNEY FINKELSTEIN | D135: 46279 | E135: NOT REQUIRED | F135: NOT REQUIRED | G135: NOT REQUIRED | H135: NOT REQUIRED | I135: 10801 E. Happy Valley Road #64
A136: 1678 | B136: ORDER COMPLETED | C136: LAURA ROBINSON | D136: TBD | E136: NEED | F136: NOT REQUIRED | G136: NOT REQUIRED | H136: NOT REQUIRED | I136: 6043 N Camino Preciado, Tucson, AZ 85718, USA
A137: 184 | B137: ORDER COMPLETED | C137: LAMB, CINDY & JOHN | E137: NOT REQUIRED | F137: NOT REQUIRED | G137: NOT REQUIRED | H137: NOT REQUIRED | I137: 7702 N Moonlight Ln, , PARADISE VALLEY, 85253, Arizona
A138: 186 | B138: ORDER COMPLETED | C138: CAROLL, DAVID | E138: NOT REQUIRED | F138: NOT REQUIRED | G138: NOT REQUIRED | H138: NOT REQUIRED | I138: 19702 W. MULBERRY DR, , BUCKEYE, 85396, Arizona
A139: 199 | B139: ORDER COMPLETED | C139: PALMER, TERESA | E139: NOT REQUIRED | F139: NOT REQUIRED | G139: NOT REQUIRED | H139: NOT REQUIRED | I139: 8532 E WHISPER ROCK, , SCOTTSDALE, 85266, Arizona
A140: 248 | B140: ORDER COMPLETED | C140: TRADER, PAULA & BOB | E140: NOT REQUIRED | F140: NOT REQUIRED | G140: NOT REQUIRED | H140: NOT REQUIRED | I140: 17370 W Montpelier, , Surprise, 85388, Arizona
A141: 259 | B141: ORDER COMPLETED | C141: BLOEBAUM, AMY | E141: NOT REQUIRED | F141: NOT REQUIRED | G141: NOT REQUIRED | H141: NOT REQUIRED | I141: , , , , Arizona
A142: 262 | B142: ORDER COMPLETED | C142: SALZMAN, JENNIFER | E142: NOT REQUIRED | F142: NOT REQUIRED | G142: NOT REQUIRED | H142: NOT REQUIRED | I142: , , , ,
A143: 263 | B143: ORDER COMPLETED | C143: BARAVADA, ATLAS | E143: NOT REQUIRED | F143: NOT REQUIRED | G143: NOT REQUIRED | H143: NOT REQUIRED | I143: , , , ,
A144: 267 | B144: ORDER COMPLETED | C144: JONES, MARY LU | E144: NOT REQUIRED | F144: NOT REQUIRED | G144: NOT REQUIRED | H144: NOT REQUIRED | I144: 10902 E MICHIGAN AVE, , SUN LAKES, 85248, Arizona
A145: 269 | B145: ORDER COMPLETED | C145: BICKELHAUPT, REESE | E145: NOT REQUIRED | F145: NOT REQUIRED | G145: NOT REQUIRED | H145: NOT REQUIRED | I145: 12043 E CAVEDALE DR, , SCOTTSDALE, 85262, Arizona
A146: 273 | B146: ORDER COMPLETED | C146: DOCHTERMAN, KENDRA | E146: NOT REQUIRED | F146: NOT REQUIRED | G146: NOT REQUIRED | H146: NOT REQUIRED | I146: …........
A147: 274 | B147: ORDER COMPLETED | C147: GUELI, SUSAN | E147: NOT REQUIRED | F147: NOT REQUIRED | G147: NOT REQUIRED | H147: NOT REQUIRED | I147: 24099 N 123RD WAY, , SCOTTSDALE, 85255, Arizona
A148: 276 | B148: ORDER COMPLETED | C148: BELL, SUSAN | E148: NOT REQUIRED | F148: NOT REQUIRED | G148: NOT REQUIRED | H148: NOT REQUIRED | I148: 26475 N 107th Way. Scottsdale. 85255, , SCOTTSDALE, 85255, Arizona
... A212: 344 | B212: ORDER COMPLETED | C212: KC, AOUFE | E212: NOT REQUIRED | F212: NOT REQUIRED | G212: NOT REQUIRED | H212: NOT REQUIRED | I212: 2788 E HUMMINGBIRD WAY, , GILBERT, 85297, Arizona
A213: 346 | B213: ORDER COMPLETED | C213: LYNN, CC PATIO | E213: NOT REQUIRED | F213: NOT REQUIRED | G213: NOT REQUIRED | H213: NOT REQUIRED
A214: 347 | B214: ORDER COMPLETED | C214: HEMSTREET, GREG | E214: NOT REQUIRED | F214: NOT REQUIRED | G214: NOT REQUIRED | H214: NOT REQUIRED
A215: 348 | B215: ORDER COMPLETED | C215: AZIZ, BILL | E215: NOT REQUIRED | F215: NOT REQUIRED | G215: NOT REQUIRED | H215: NOT REQUIRED | I215: , , , ,
A216: 349 | B216: ORDER COMPLETED | C216: BASCHE, ADAM | E216: NOT REQUIRED | F216: NOT REQUIRED | G216: NOT REQUIRED | H216: NOT REQUIRED | I216: 4235 N 18th St, , Phoenix, 85014, Arizona
A217: 350 | B217: ORDER COMPLETED | C217: REITER, COLLEEN & STEVE | E217: NOT REQUIRED | F217: NOT REQUIRED | G217: NOT REQUIRED | H217: NOT REQUIRED | I217: 7929 E Santa Catalina Dr, , SCOTTSDALE, 85255, Arizona
A218: 351 | B218: ORDER COMPLETED | C218: MARINO, JOEY & BECKY | E218: NOT REQUIRED | F218: NOT REQUIRED | G218: NOT REQUIRED | H218: NOT REQUIRED | I218: 14855 E VALLEY VISTA DR, , FOUNTAIN HILLS, , Arizona
A219: 352 | B219: ORDER COMPLETED | C219: CLAUSEN, KEITH | E219: NOT REQUIRED | F219: NOT REQUIRED | G219: NOT REQUIRED | H219: NOT REQUIRED | I219: 29648 N PUEBLO BLVD, , RIO VERDE, 85263, Arizona
A220: 353 | B220: ORDER COMPLETED | C220: Petznick, Olen | E220: NOT REQUIRED | F220: NOT REQUIRED | G220: NOT REQUIRED | H220: NOT REQUIRED
A221: 354 | B221: ORDER COMPLETED | C221: Gerber, Kyrin | E221: NOT REQUIRED | F221: NOT REQUIRED | G221: NOT REQUIRED | H221: NOT REQUIRED | I221: 4103 n 64th pl, , Scottsdale, 85251, Arizona
A222: 355 | B222: ORDER COMPLETED | C222: UNIAT, LOIS | E222: NOT REQUIRED | F222: NOT REQUIRED | G222: NOT REQUIRED | H222: NOT REQUIRED | I222: 14324 E. HARMONY LANE, , FOUNTAIN HILLS, , Arizona
A223: 356 | B223: ORDER COMPLETED | C223: LOVE, SUSAN & CRAWFORD | E223: NOT REQUIRED | F223: NOT REQUIRED | G223: NOT REQUIRED | H223: NOT REQUIRED | I223: 24660 N 109th St, , SCOTTSDALE, 85255, Arizona
A224: 357 | B224: ORDER COMPLETED | C224: BALDWIN, ANNIE | E224: NOT REQUIRED | F224: NOT REQUIRED | G224: NOT REQUIRED | H224: NOT REQUIRED | I224: 5503 Beechwood Terrace, , West Des Moines, 50266, Iowa
A225: 358 | B225: ORDER COMPLETED | C225: SCHNEIDER, STACY | E225: NOT REQUIRED | F225: NOT REQUIRED | G225: NOT REQUIRED | H225: NOT REQUIRED | I225: 8920 S Hardy Dr, , TEMPE, , Arizona
A226: 359 | B226: ORDER COMPLETED | C226: DeSouza, FRANCIS | E226: NOT REQUIRED | F226: NOT REQUIRED | G226: NOT REQUIRED | H226: NOT REQUIRED | I226: 13487 Stone View Trail, , FOUNTAIN HILLS, , Arizona
A227: 360 | B227: ORDER COMPLETED | C227: Bertenshaw, Kathi | E227: NOT REQUIRED | F227: NOT REQUIRED | G227: NOT REQUIRED | H227: NOT REQUIRED | I227: 8029 N 74th Pl, , Scottsdale, 85258, Arizona
A228: 361 | B228: ORDER COMPLETED | C228: CICIORA, SUSAN | E228: NOT REQUIRED | F228: NOT REQUIRED | G228: NOT REQUIRED | H228: NOT REQUIRED | I228: 5452 E MORRISON LN, , PARADISE VALLEY, , Arizona
A229: 362 | B229: ORDER COMPLETED | C229: KITTLESON, KELSEY | E229: NOT REQUIRED | F229: NOT REQUIRED | G229: NOT REQUIRED | H229: NOT REQUIRED | I229: 7418 E CHOLLA LN, , SCOTTSDALE, 85250, Arizona
A230: 363 | B230: ORDER COMPLETED | C230: CHAPMAN, MATTHEW | E230: NOT REQUIRED | F230: NOT REQUIRED | G230: NOT REQUIRED | H230: NOT REQUIRED | I230: 3616 N 48TH PL, , PJOENIX, , Arizona
A231: 364 | B231: ORDER COMPLETED | C231: SALTI, AMEENA | E231: NOT REQUIRED | F231: NOT REQUIRED | G231: NOT REQUIRED | H231: NOT REQUIRED | I231: 3959 East Navigator Lane, , PHOENIX, , Arizona
A232: 366 | B232: ORDER COMPLETED | C232: LEWIS, JUNE & LES | E232: NOT REQUIRED | F232: NOT REQUIRED | G232: NOT REQUIRED | H232: NOT REQUIRED | I232: 37200 N Cave Creek Rd, Unit 1054, Scottsdale, AZ, 85262, Arizona
... A234: 368 | B234: ORDER COMPLETED | C234: UZCATEGUI, NICOLAS | E234: NOT REQUIRED | F234: NOT REQUIRED | G234: NOT REQUIRED | H234: NOT REQUIRED | I234: 10801 E Happy Valley Rd, #4, SCOTTSDALE, , Arizona
A235: 369 | B235: ORDER COMPLETED | C235: KILLIAN, STEVE & DEBBIE | E235: NOT REQUIRED | F235: NOT REQUIRED | G235: NOT REQUIRED | H235: NOT REQUIRED
A236: 370 | B236: ORDER COMPLETED | C236: KILIAN, STEVE & DEBBIE | E236: NOT REQUIRED | F236: NOT REQUIRED | G236: NOT REQUIRED | H236: NOT REQUIRED
A237: 371 | B237: ORDER COMPLETED | C237: SMITH, KEELY (DAISY TOBIAS) | E237: NOT REQUIRED | F237: NOT REQUIRED | G237: NOT REQUIRED | H237: NOT REQUIRED | I237: 6483 E El Maro Cir,, , PARADISE VALLEY, , Arizona
A238: 372 | B238: ORDER COMPLETED | C238: Ableson, Annallee | E238: NOT REQUIRED | F238: NOT REQUIRED | G238: NOT REQUIRED | H238: NOT REQUIRED | I238: 165 N Ski Court, , Gilbert, 85233, Arizona
A239: 373 | B239: ORDER COMPLETED | C239: RUDNITZKI, SUZANNE | E239: NOT REQUIRED | F239: NOT REQUIRED | G239: NOT REQUIRED | H239: NOT REQUIRED | I239: 420 S Pinto Pl, , Tucson, 85748, Arizona
A240: 374 | B240: ORDER COMPLETED | C240: Jakobsen, Bryan | E240: NOT REQUIRED | F240: NOT REQUIRED | G240: NOT REQUIRED | H240: NOT REQUIRED
A241: 375 | B241: ORDER COMPLETED | C241: LANDRO, JENNIFER | E241: NOT REQUIRED | F241: NOT REQUIRED | G241: NOT REQUIRED | H241: NOT REQUIRED | I241: 7430 E MONTRO WAY, , SCOTTSDALE, , Arizona
A242: 376 | B242: ORDER COMPLETED | C242: HAGHI, ALI & KERRI | E242: NOT REQUIRED | F242: NOT REQUIRED | G242: NOT REQUIRED | H242: NOT REQUIRED | I242: , , , , Nevada
A243: 377 | B243: ORDER COMPLETED | C243: COVACIE, MAGGIE | E243: NOT REQUIRED | F243: NOT REQUIRED | G243: NOT REQUIRED | H243: NOT REQUIRED | I243: 4939 E Mockingbird Ln, , PARADISE VALLEY, , Arizona
A244: 378 | B244: ORDER COMPLETED | C244: DeSouza, FRANCIS | E244: NOT REQUIRED | F244: NOT REQUIRED | G244: NOT REQUIRED | H244: NOT REQUIRED | I244: 13487 Stone View Trail, , FOUNTAIN HILLS, , Arizona
A245: 379 | B245: ORDER COMPLETED | C245: MCGELLA, SUSAN | E245: NOT REQUIRED | F245: NOT REQUIRED | G245: NOT REQUIRED | H245: NOT REQUIRED | I245: , , SCOTTSDALE, , Arizona
A246: 380 | B246: ORDER COMPLETED | C246: PRICHARD, PEGGY & JOEL | E246: NOT REQUIRED | F246: NOT REQUIRED | G246: NOT REQUIRED | H246: NOT REQUIRED | I246: 20432 N 94th Way, , Scottsdale, AZ, 85255, Arizona
A247: 381 | B247: ORDER COMPLETED | C247: Berliner, Cynthia | E247: NOT REQUIRED | F247: NOT REQUIRED | G247: NOT REQUIRED | H247: NOT REQUIRED | I247: 11735 E. Buckskin Trail, , Scottsdale, 85255, Arkansas
A248: 383 | B248: ORDER COMPLETED | C248: HEIST, KATHY & JEFF | E248: NOT REQUIRED | F248: NOT REQUIRED | G248: NOT REQUIRED | H248: NOT REQUIRED | I248: 25150 N WINOY WALK DR # 22, , SCOTTSDALE, 85255, Arizona
A249: 384 | B249: ORDER COMPLETED | C249: MT, SHADOWA | E249: NOT REQUIRED | F249: NOT REQUIRED | G249: NOT REQUIRED | H249: NOT REQUIRED
A250: 385 | B250: ORDER COMPLETED | C250: BELL, SUSAN & GORDON | E250: NOT REQUIRED | F250: NOT REQUIRED | G250: NOT REQUIRED | H250: NOT REQUIRED | I250: 26475 N 107th Way, , SCOTTSDALE, 85255, Arizona
A251: 386 | B251: ORDER COMPLETED | C251: BERTON, JACK & JOANNE | E251: NOT REQUIRED | F251: NOT REQUIRED | G251: NOT REQUIRED | H251: NOT REQUIRED | I251: 18805 E BLUE SKY DR, , Rio Verde, , Arizona
...

Sheet CONFIRMACIONES
A1: {={NEW!A1:A1982, NEW!C1:C1982, NEW!B1:B1982, NEW!F1:F1982, NEW!G1:G1982, NEW!H1:H1982, NEW!E1:E1982, NEW!I1:I1982, NEW!AC1:AC1982}} -> Order Number | B1: Customer Info | C1: Column 2 | D1: Production Deadline | E1: Delivery Date | F1: Delivery Conf. | G1: PU / DROP | H1: PU / DROP Confirmed | I1: Delivery Address
A2: 1572 | B2: BETH COHEN | C2: ORDER COMPLETED | D2: 46203 | E2: 46204 | F2: YES | I2: 10604 Arista Ln, Fountain Hills, AZ 85268, USA
A3: 1591 | B3: BRIAN BEVERLY BUFFINI | C3: ORDER COMPLETED | D3: 46203 | E3: 46204 | F3: YES | I3: CALIFORNIA
A4: 1593 | B4: JENNIFER LAABS | C4: ORDER COMPLETED | D4: 46203 | E4: 46205 | F4: YES | I4: 484 Halcyon Pl, Bethel Island, CA 94511
A5: 1598 | B5: WARR-DAN MAYNARD | C5: ORDER COMPLETED | D5: 46203 | E5: 46203 | G5: 46203 | I5: 20408 E Cloud Rd, Queen Creek, AZ 85142, USA
A6: 1622 | B6: MADONA KAKISH | C6: ORDER COMPLETED | D6: 46203 | E6: 46205 | F6: YES | I6: CALIFORNIA
A7: 1639 | B7: ROBYN LAUKIE-CHRIS PARK | C7: READY FOR DELIVERY | D7: 46204 | E7: 46204 | F7: NO | H7: NA | I7: 6352 Arroyo Rd, Cave Creek, AZ 85331, USA
A8: 1677 | B8: TONY KURTH | C8: READY FOR DELIVERY | D8: 46204 | E8: 46204 | F8: NO | H8: NA | I8: PICKUP
A9: 1688 | B9: ERIC WHITTAKER | C9: NEW | D9: 46204 | E9: 46204 | F9: NO | H9: NA | I9: 5400 E Valle Vista Rd #6, Phoenix, AZ 85018
A10: 1715 | B10: JAIME KIM LIMBER | C10: ORDER COMPLETED | D10: 46204 | E10: 46246 | F10: YES | G10: 46246 | H10: YES | I10: 4202 N 58th St PHOENIX AZ 85018
A11: 1627 | B11: BRITTANY MCDOWELL | C11: ORDER COMPLETED | D11: 46204 | E11: 46204 | F11: YES | G11: 46233 | H11: YES | I11: 8404 N 75th St, Scottsdale, AZ 85258, USA
A12: 1708 | B12: ECHMEYER, KRISTINA & EVAN | C12: ORDER COMPLETED | D12: 46204 | E12: 46204 | F12: NO | H12: NA | I12: 8321 Baseline Rd, Boulder, CO 80303, USA
A13: 1491 | B13: KONA RE-DOING-GENCUSH | C13: NEW | D13: 46204 | E13: 46204 | F13: NO | H13: NA | I13: 72-300 Maheawalu Drive, Kailua-Kona HI 96740
A14: 1662 | B14: KERYN GERBER | C14: ORDER COMPLETED | D14: 46253 | E14: 46253 | F14: YES | G14: 46233 | H14: YES | I14: 4103 n 64th pl, Scottsdale, Arizona 85251
A15: 1663 | B15: DAVE MONTZ | C15: ORDER COMPLETED | D15: 46204 | E15: 46204 | F15: NO | G15: 46212 | H15: YES | I15: DROP & PICK AT FACTORY
A16: 1687 | B16: JEN BERGMAN | C16: ORDER COMPLETED | D16: 46204 | E16: 46204 | F16: NO | H16: NA | I16: 3386 S Stuart Ave, Gilbert, AZ 85297, USA
A17: 1702 | B17: JILL CUTRONE | C17: ORDER COMPLETED | D17: 46204 | E17: 46204 | F17: NO | H17: NA | I17: 14762 N Strong Stone Dr, Oro Valley, AZ 85755, USA
A18: 1703 | B18: MIKE CHAFFEUR | C18: ORDER COMPLETED | D18: 46204 | E18: 46204 | F18: NO | H18: NA | I18: 9431 N Solitude Canyon Fountain Hills AZ 85268
A19: 1696 | B19: LISA FORD | C19: ORDER COMPLETED | D19: 46205 | E19: 46205 | F19: YES | H19: NA | I19: COLORADO
A20: 1704 | B20: LINDSAY MADERIA WALSH | C20: ORDER COMPLETED | D20: 46205 | E20: 46205 | F20: YES | H20: NA | I20: 2055 Bear Hollow Dr, Park City, UT 84098, USA
A21: 1638 | B21: DIANE GALATI | C21: ORDER COMPLETED | D21: 46209 | E21: 46210 | F21: YES | I21: 4939 E Horseshoe Rd, Paradise Valley, AZ 85253, USA
A22: 1605 | B22: DEANNE SPRENGER | C22: ORDER COMPLETED | D22: 46210 | E22: 46210 | F22: YES | G22: 46212 | H22: YES | I22: 13452 E Desert Trail Scottsdale, AZ 85259
A23: 1643 | B23: MEGAN KELLY ADD-ON | C23: ORDER COMPLETED | D23: 46210 | E23: 46211 | F23: YES | H23: NA | I23: 10276 White Birch St, Presque Isle, MI 49777, USA
A24: 1521 | B24: RUSH SHOWROOM SWING CUSHION | C24: ORDER COMPLETED | D24: 46212 | E24: 46212 | F24: YES | H24: NA | I24: 15037 N Scottsdale Rd Ste 120, Scottsdale, AZ 85254
A25: 1502 | B25: ROB ROY | C25: ORDER COMPLETED | D25: 46217 | E25: 46218 | F25: YES | H25: NA | I25: CALIFORNIA
A26: 1573 | B26: SOLANA BEACH SHOWROOM 4-29 | C26: ORDER COMPLETED | D26: 46217 | E26: 46218 | F26: YES | H26: NA | I26: CALIFORNIA
A27: 1576 | B27: RICHARD AGUILAR | C27: ORDER COMPLETED | D27: 46217 | E27: 46218 | F27: YES | H27: NA | I27: 5435 Calumet Ave, LA JOLLA, CA
A28: 1604 | B28: MELANIE SPAHN | C28: ORDER COMPLETED | D28: 46217 | E28: 46218 | F28: YES | G28: 46218 | H28: YES | I28: 8621 E Clarendon Ave, Scottsdale, AZ 85251, USA
A29: 1610 | B29: PAUL DICOSMO-REDO | C29: ORDER COMPLETED | D29: 46217 | E29: 46217 | F29: YES | G29: 46211 | H29: YES | I29: 18724 E Chandler Heights Rd, Queen Creek, AZ 85142, USA
A30: 1613 | B30: RAQUEL-JASON NORTON | C30: ORDER COMPLETED | D30: 46217 | E30: 46218 | F30: YES | H30: NA | I30: CALIFORNIA
A31: 1614 | B31: BETH HOFFMAN | C31: ORDER COMPLETED | D31: 46217 | E31: 46218 | F31: YES | H31: NA | I31: CALIFORNIA
A32: 1624 | B32: RAQUEL-JASON NORTON | C32: ORDER COMPLETED | D32: 46217 | E32: 46218 | F32: YES | H32: NA | I32: 1468 Rimcrest Ct, BONITA CA 91902
A33: 1651 | B33: CHAD | C33: ORDER COMPLETED | D33: 46217 | E33: 46218 | F33: YES | G33: 46212 | H33: YES | I33: 13260 N 83rd Pl SCOTTSDALE AZ 85260
A34: 1653 | B34: CA AMAR TAKHUR | C34: ORDER COMPLETED | D34: 46217 | E34: 46219 | F34: YES | H34: NA | I34: 304 N Sierra Ave, Solana Beach, CA 92075
A35: 1608 | B35: ANDREA SYDENHAM-SERVICE | C35: ORDER COMPLETED | D35: 46218 | E35: 46219 | F35: YES | G35: 46202 | H35: YES | I35: 26814 Boulder Ln, Scottsdale, AZ 85255, USA
A36: 1617 | B36: REDO SHELLY GROTHAUS | C36: ORDER COMPLETED | D36: 46218 | E36: 46219 | F36: YES | G36: 46202 | H36: YES | I36: 10801 E Happy Valley Rd, Scottsdale, AZ 85255, USA
A37: 1654 | B37: CA Edisoon Reynoso | C37: ORDER COMPLETED | D37: 46218 | E37: 46219 | F37: YES | H37: NA | I37: 5986 Greensview Ct, RANCHO SANTA FE, CA 92067
A38: 1607 | B38: STEPHANIE EVERS-SERVICE | C38: ORDER COMPLETED | D38: 46219 | E38: 46219 | F38: YES | G38: 46204 | H38: YES | I38: 5736 E Lowden Rd, Cave Creek, AZ 85331, USA
A39: 1669 | B39: HAMID SHOWROOM 7-17-26 | C39: ORDER COMPLETED | D39: 46219 | E39: 46219 | F39: YES | H39: NA | I39: SCOTTSDALE SHOWROOM
A40: 1546 | B40: JIM-CAROL LAUB | C40: ORDER COMPLETED | D40: 46223 | E40: 46225 | F40: YES | H40: NA | I40: 8745 North Lookout Lane, Park City, UT
A41: 1646 | B41: JOE REDMOND III | C41: ORDER COMPLETED | D41: 46225 | E41: 46226 | F41: YES | H41: NA | I41: 5824 E SABDFORD ST MESA 85215
A42: 1626 | B42: ERIC WHITTAKER | C42: ORDER COMPLETED | D42: 46226 | E42: 46227 | F42: YES | H42: NA | I42: 5400 E Valle Vista rd 85018
A43: 1623 | B43: DEBBIE KILIAN | C43: ORDER COMPLETED | D43: 46227 | E43: 46230 | F43: YES | H43: NA | I43: 4208 Kettle Ridge Trail, SLINGER, WISCONSIN
A44: 1655 | B44: OPTIMA CHICAGO FINAL | C44: ORDER COMPLETED | D44: 46227 | E44: 46227 | F44: YES | H44: NA | I44: CHICAGO
A45: 1670 | B45: STEPHANIE LALLEY | C45: ORDER COMPLETED | D45: 46227 | E45: 46226 | F45: YES | H45: NA | I45: 1000 Berkshire Ln N #11 Plymouth, MN 55441
A46: 1616 | B46: JILL CUTRONE | C46: ORDER COMPLETED | D46: 46230 | E46: 46231 | F46: YES | H46: NA | I46: 14762 N Strong Stone Dr Oro Valley, AZ 85755
A47: 1628 | B47: JOHN MARTELL | C47: ORDER COMPLETED | D47: 46230 | E47: 46230 | F47: YES | H47: NA | I47: 7120 E kierland, Scottsdale AZ 85254 APT #705
A48: 1615 | B48: KORRENA GLEN | C48: ORDER COMPLETED | D48: 46231 | E48: 46232 | F48: YES | H48: YES | I48: 8230 N. Mockinbird Ln Paradise valley AZ 85253
A49: 1634 | B49: NIKKI PERES | C49: ORDER COMPLETED | D49: 46231 | E49: 46232 | F49: YES | G49: 46212 | H49: YES | I49: DROP & PICK FROM FACTORY
A50: 1656 | B50: LINDA SALKOW | C50: ORDER COMPLETED | D50: 46231 | E50: 46232 | F50: YES | H50: YES | I50: 10330 E Nolina Trail, Scottsdale, AZ
A51: 1660 | B51: NIKKI PERES - HUNTER T TABLES | C51: ORDER COMPLETED | D51: 46231 | E51: 46232 | F51: YES | H51: YES | I51: 8980 East Raintree Drive, Suite 100 Scottsdale, Az 85260
A52: 1620 | B52: JENNIFER JOHNSON | C52: ORDER COMPLETED | D52: 46232 | E52: 46233 | F52: YES | G52: 46233 | H52: YES | I52: 2666 E Raven Way, Gilbert, AZ 85297, USA
A53: 1631 | B53: JEN BERGMAN | C53: ORDER COMPLETED | D53: 46232 | E53: 46233 | F53: YES | G53: 46217 | H53: YES | I53: 3386 S Stuart Ave, Gilbert, AZ 85297, USA
A54: 1618 | B54: MIKE CHAFFEUR | C54: ORDER COMPLETED | D54: 46233 | E54: 46237 | F54: YES | H54: NA | I54: 9431 N Solitude Canyon, Fountain Hills AZ 85268
A55: 1606 | B55: CORINA COVACIU-SERVICE | C55: ORDER COMPLETED | D55: 46234 | E55: 46224 | F55: NO | G55: 46209 | H55: YES | I55: 7936 W Villa Chula, Peoria, AZ 85383, USA
A56: 1619 | B56: LISA FORD | C56: ORDER COMPLETED | D56: 46234 | E56: 46235 | F56: YES | H56: NA | I56: 2260 Bear Hollow Dr. PARK CITY, UTAH
A57: 1633 | B57: KIRK JOHNS | C57: ORDER COMPLETED | D57: 46234 | E57: 46235 | F57: YES | H57: NA | I57: 3418 Seneca Dr. Las Vegas, NV 89169
A58: 1647 | B58: LINDSAY MADERIA WALSH | C58: ORDER COMPLETED | D58: 46234 | E58: 46235 | F58: YES | H58: NA | I58: 2055 Bear Hollow Drive, PC 84098 PARK CITY UTAH
A59: 1648 | B59: MELISSA FISCHER | C59: ORDER COMPLETED | D59: 46234 | E59: 46235 | F59: YES | H59: NA | I59: 201 White Pine Canyon Road, Park City UT 84060
A60: 1671 | B60: CAROL LAUB RUSH | C60: ORDER COMPLETED | D60: 46234 | E60: 46235 | F60: YES | H60: NA | I60: 8745 North Lookout Lane, Park City, UT
A61: 1683 | B61: CAROL LAUB RUSH | C61: ORDER COMPLETED | D61: 46234 | E61: 46234 | F61: YES | H61: NA | I61: 8745 North Lookout Lane, Park City, UT
A62: 1637 | B62: DENISE STEINKIRCHNER | C62: ORDER COMPLETED | D62: 46237 | E62: 46237 | F62: YES | H62: NA | I62: 293 Canterwood Lane Wexford, PA 15090
A63: 1664 | B63: TONY SCHINDLER | C63: ORDER COMPLETED | D63: 46237 | E63: 46238 | F63: YES | H63: NA | I63: 37702 N. Schoolhouse Rd CAVE CREEK AZ
A64: 1689 | B64: KIRK JOHNS | C64: ORDER COMPLETED | D64: 46237 | E64: 46237 | F64: YES | H64: NA | I64: 3418 Seneca Dr. Las Vegas, NV 89169
A65: 1583 | B65: MELANIE DEPATIE WARRANTY | C65: ORDER COMPLETED | D65: 46238 | E65: 46239 | F65: YES | G65: 46195 | H65: YES | I65: 5879 E Onyx Ave, SCOTTSDALE, AZ
A66: 1583 | B66: MELANIE DEPATIE NEW SECTION | C66: ORDER COMPLETED | D66: 46238 | E66: 46239 | F66: YES | H66: NA | I66: 5879 E Onyx Ave, SCOTTSDALE, AZ
A67: 1642 | B67: CATHY-JIM SURRAT | C67: ORDER COMPLETED | D67: 46239 | E67: 46240 | F67: YES | H67: NA | I67: 14347 E THOROUGHBRED TRAIL, SCOTTSDALE AZ 85259
A68: 1661 | B68: PERKINS COIE LLP-WARRANTY | C68: ORDER COMPLETED | D68: 46239 | E68: 46240 | F68: YES | G68: 46231 | H68: YES | I68: 2525 E Camelback Rd suite 500, Phoenix, AZ 85016, USA
A69: 1705 | B69: JOHN MARTELL REDO | C69: ORDER COMPLETED | D69: 46239 | E69: 46239 | F69: YES | H69: NA | I69: DROP OFF AT SCOTTSDALE SHOWROOM
A70: 1698 | B70: OPTIMA 7220 BARSTOOL REUPHOLSTERY | C70: ORDER COMPLETED | D70: 46244 | E70: 46244 | F70: YES | G70: 46244 | H70: YES | I70: OPTIMA 7220
A71: 1713 | B71: OPTIMA 7220 RUSH DOWNSTAIRS | C71: ORDER COMPLETED | D71: 46244 | E71: 46244 | F71: YES | G71: 46244 | H71: YES
A72: 1657 | B72: TIFFANY HERTER | C72: ORDER COMPLETED | D72: 46245 | E72: 46246 | F72: YES | G72: 46246 | H72: YES | I72: 28119 N. 109th Way
A73: 1684 | B73: OPTIMA 7140 FRAMES PHASE I | C73: ORDER COMPLETED | D73: 46245 | E73: 46245 | F73: YES | G73: 46240 | H73: YES | I73: OPTIMA 7140
A74: 1641 | B74: DEBBIE BATTISTA | C74: ORDER COMPLETED | D74: 46246 | E74: 46247 | F74: YES | H74: NA | I74: 1175 E. Copper Hollow Way, Queen Creek, AZ 85740
A75: 1650 | B75: CAROL COLOMBO | C75: ORDER COMPLETED | D75: 46246 | E75: 46247 | F75: YES | H75: NA | I75: 5633 N. Royal Circle, Paradise Valley, AZ
A76: 1684 | B76: OPTIMA 7140 FRAMES PHASE II | C76: ORDER COMPLETED | D76: 46248 | E76: 46248 | F76: YES | G76: 46245 | H76: YES | I76: OPTIMA 7140
A77: 1714 | B77: CHERYL BURK | C77: ORDER COMPLETED | D77: 46253 | E77: 46253 | F77: YES | H77: NA | I77: SCOTTSDALE SHOWROOM
A78: 1684 | B78: OPTIMA 7140 PHASE III | C78: NEW | D78: 46254 | E78: 46253 | F78: YES | G78: 46254 | H78: YES | I78: OPTIMA 7140
A79: 1635 | B79: KATHLEEN WIT | C79: ORDER COMPLETED | D79: 46254 | E79: 46254 | F79: YES | H79: NA | I79: 157 Mozart Ave , CA 92007
A80: 1668 | B80: SHARIF & MALIHE | C80: ORDER COMPLETED | D80: 46254 | E80: 46254 | F80: YES | H80: NA | I80: 4832 Fairport Way, San Diego, CA 92130, USA
A81: 1679 | B81: BETH HOFFMAN | C81: READY FOR DELIVERY | D81: 46254 | E81: 46255 | F81: YES | H81: NA | I81: 5895 Blazing Star Ln, San Diego, CA 92130, USA
A82: 1690 | B82: SOLONA BEACH SHOWROOM | C82: ORDER COMPLETED | D82: 46254 | E82: 46254 | F82: YES | H82: NA | I82: SOLONA BEACH SHOWROOM
A83: 1693 | B83: DAN AMBROSE | C83: READY FOR DELIVERY | D83: 46254 | E83: 46255 | F83: YES | H83: NA | I83: 26 9th St HER,OSA BEACH CA
A84: 1578-S | B84: DAN AMBROSE | C84: READY FOR DELIVERY | D84: 46254 | E84: 46255 | F84: YES | H84: NA | I84: 26 9th St HER,OSA BEACH CA
A85: 1726 | B85: CAROL COLOMBO | C85: ORDER COMPLETED | D85: 46254 | E85: 46254 | F85: YES | H85: NA
A86: 1707 | B86: SCOTTSDALE SHOWROOM | C86: NEW | D86: 46258 | E86: 46258 | F86: YES | H86: NA | I86: SCOTTSDALE SHOWROOM
A87: 1673 | B87: CYNTHIA MANN | C87: NEW | D87: 46258 | E87: 46259 | F87: YES | G87: NEED TEMPLATE | H87: YES | I87: 556 W. Moon Valley Drive, Phoenix, AZ
A88: 1682 | B88: JOHN BUTZ | C88: READY FOR DELIVERY | D88: 46259 | E88: 46260 | F88: YES | H88: NA | I88: 2926 North Valencia Lane
A89: 1685 | B89: OPTIMA 7190 FRAMES PHASE I | C89: NEW | D89: 46259 | E89: 46259 | F89: YES | G89: 46252 | H89: YES | I89: OPTIMA 7190
A90: 1680 | B90: SHERI RODGERS | C90: READY FOR DELIVERY | D90: 46261 | E90: 46261 | F90: YES | G90: 46261 | H90: YES | I90: 1802 E Phoenix St Payson AZ 85541 / PICK UP FROM SCOTTSDALE SHOWROOM
A91: 1694 | B91: MIKE GANTZEL | C91: NEW | D91: 46261 | E91: 46261 | F91: YES | G91: 46238 | H91: YES | I91: 4099 East Meadowview Dr Gilbert Az 85298
A92: 1644 | B92: CHRISTINE WILSON | C92: READY FOR DELIVERY | D92: 46265 | E92: 46265 | F92: YES | H92: NA | I92: 1854 DOWNS ST OCEAN SIDE CA 92054
A93: 1681 | B93: DAVE KRISTEN ANDERSON | C93: NEW | D93: 46265 | E93: 46265 | F93: YES | G93: KIAN DROP | H93: YES | I93: 6343 Clubhouse Dr, Rancho Santa Fe, CA 92091, USA
A94: 1701 | B94: MADONNA KAKISH | C94: READY FOR DELIVERY | D94: 46265 | E94: 46265 | F94: YES | H94: NA | I94: 32090 Via Bella Vita TEMECULA CA
A95: 1548 | B95: STEVE-MARGUERITE MORRELL | C95: READY FOR DELIVERY | D95: 46266 | E95: 46266 | F95: YES | H95: NA | I95: 16734 N Mountain Parkway, FOUNTAIN HILLS
A96: 1685 | B96: OPTIMA 7190 FRAMES PHASE II | C96: NEW | D96: 46266 | E96: 46266 | F96: YES | G96: 46259 | H96: YES | I96: OPTIMA 7190
A97: 1667 | B97: STEPHEN HAKAMI | C97: READY FOR DELIVERY | D97: 46267 | E97: 46267 | F97: YES | H97: NA | I97: 6026 North 77th Place SCOTTSDALE AZ 85250
A98: 1723 | B98: GIL KONFINO | C98: NEW | D98: 46268 | E98: 46268 | F98: YES | H98: NA | I98: 33962 N Cole Ranch Rd QUEEN CREEK AZ
A99: 1716 | B99: JENNIFER JOHNSON | C99: NEW | D99: 46269 | E99: 46269 | F99: NO | H99: NO | I99: 2666 E Raven Way GILBERT AZ 85297
A100: 1645 | B100: ERIN CRAVENS | C100: NEW | D100: 46269 | E100: 46269 | F100: NO | H100: NA | I100: 8650 E SAN LORENZO DR SCOTTSDALE AZ 85258
...

Sheet Lookup
A1: ORDER QUICK LOOKUP
A3: Look up Order #: | B3: 1563
A5: Customer | B5: {=IF($B$3="","",IFNA(_xlfn.XLOOKUP($B$3,NEW!$A:$A,NEW!$C:$C),"Not found"))} -> JIM BUTLER
A6: Order Status | B6: {=IF($B$3="","",IFNA(_xlfn.XLOOKUP($B$3,NEW!$A:$A,NEW!$B:$B),"Not found"))} -> ORDER COMPLETED
A7: PDF / Type | B7: {=IF($B$3="","",IFNA(_xlfn.XLOOKUP($B$3,NEW!$A:$A,NEW!$D:$D),"Not found"))} -> RESIDENTIAL
A8: Prod. Deadline | B8: {=IF($B$3="","",IFNA(_xlfn.XLOOKUP($B$3,NEW!$A:$A,NEW!$F:$F),"Not found"))}
A9: Delivery Date | B9: {=IF($B$3="","",IFNA(_xlfn.XLOOKUP($B$3,NEW!$A:$A,NEW!$G:$G),"Not found"))} -> 46169
A10: Delivery Conf. | B10: {=IF($B$3="","",IFNA(_xlfn.XLOOKUP($B$3,NEW!$A:$A,NEW!$H:$H),"Not found"))}
A11: PU/Drop Confirmed | B11: {=IF($B$3="","",IFNA(_xlfn.XLOOKUP($B$3,NEW!$A:$A,NEW!$I:$I),"Not found"))}
A12: COMPONENTS
A13: Metal | B13: {=IF($B$3="","",IFNA(_xlfn.XLOOKUP($B$3,NEW!$A:$A,NEW!$J:$J),"Not found"))} -> NOT STARTED
A14: Powder Coat | B14: {=IF($B$3="","",IFNA(_xlfn.XLOOKUP($B$3,NEW!$A:$A,NEW!$K:$K),"Not found"))} -> NOT STARTED
A15: Dekton | B15: {=IF($B$3="","",IFNA(_xlfn.XLOOKUP($B$3,NEW!$A:$A,NEW!$L:$L),"Not found"))} -> NOT STARTED
A16: Cushions | B16: {=IF($B$3="","",IFNA(_xlfn.XLOOKUP($B$3,NEW!$A:$A,NEW!$M:$M),"Not found"))} -> NOT REQUIRED
A17: Corte | B17: {=IF($B$3="","",IFNA(_xlfn.XLOOKUP($B$3,NEW!$A:$A,NEW!$N:$N),"Not found"))} -> NOT REQUIRED
A18: Sew | B18: {=IF($B$3="","",IFNA(_xlfn.XLOOKUP($B$3,NEW!$A:$A,NEW!$O:$O),"Not found"))} -> NOT REQUIRED
A19: Filling | B19: {=IF($B$3="","",IFNA(_xlfn.XLOOKUP($B$3,NEW!$A:$A,NEW!$P:$P),"Not found"))} -> NOT REQUIRED
A20: Fabric | B20: {=IF($B$3="","",IFNA(_xlfn.XLOOKUP($B$3,NEW!$A:$A,NEW!$Q:$Q),"Not found"))} -> NOT REQUIRED
A21: Foam | B21: {=IF($B$3="","",IFNA(_xlfn.XLOOKUP($B$3,NEW!$A:$A,NEW!$R:$R),"Not found"))} -> NOT REQUIRED
A22: QTY & ADD-ONS
A23: Qty Cushions | B23: {=IF($B$3="","",IFNA(_xlfn.XLOOKUP($B$3,NEW!$A:$A,NEW!$S:$S),"Not found"))} -> 0
A24: Qty Metal | B24: {=IF($B$3="","",IFNA(_xlfn.XLOOKUP($B$3,NEW!$A:$A,NEW!$T:$T),"Not found"))}
A25: Qty Dekton | B25: {=IF($B$3="","",IFNA(_xlfn.XLOOKUP($B$3,NEW!$A:$A,NEW!$U:$U),"Not found"))}
A26: Covers | B26: {=IF($B$3="","",IFNA(_xlfn.XLOOKUP($B$3,NEW!$A:$A,NEW!$Y:$Y),"Not found"))} -> NOT REQUIRED
A27: Umbrella | B27: {=IF($B$3="","",IFNA(_xlfn.XLOOKUP($B$3,NEW!$A:$A,NEW!$Z:$Z),"Not found"))} -> NOT REQUIRED
A28: Tenjam/Others | B28: {=IF($B$3="","",IFNA(_xlfn.XLOOKUP($B$3,NEW!$A:$A,NEW!$AA:$AA),"Not found"))} -> NOT REQUIRED
A29: Firepit System | B29: {=IF($B$3="","",IFNA(_xlfn.XLOOKUP($B$3,NEW!$A:$A,NEW!$AB:$AB),"Not found"))} -> NOT REQUIRED
A30: Delivery Address | B30: {=IF($B$3="","",IFNA(_xlfn.XLOOKUP($B$3,NEW!$A:$A,NEW!$AC:$AC),"Not found"))} -> 6720 N Whispering Hills Rd, Paradise Valley, AZ 85253

Sheet Hoja1
A1: Order # | B1: Customer info | C1: Start Date | D1: End Date | E1: Weeks Prog | F1: Delivery Date | G1: Weeks Real | H1: Order status | I1: Urgency Level | J1: Metal | K1: Powder Coat | L1: Dekton | M1: Wood | N1: Cushions | O1: Delivery Time | P1: Delivery Address
A2: 1 | B2: Jenson, Monika | C2: 44257 | D2: 44311 | E2: =(D2-C2)/7 -> 7.7142857 | F2: 44524 | G2: =IF(F2>0,((F2-C2)/7),0) -> 38.142857 | H2: Order Completed | I2: Urgent | J2: Completed | K2: Completed | L2: Completed | M2: Completed | N2: Completed | P2: 2 Makena Ln Rancho Mirage, , , 92270, California
A3: 2 | B3: Sonora Village, Optima | C3: 43884 | D3: 43926 | E3: =(D3-C3)/7 -> 6 | G3: =IF(F3>0,((F3-C3)/7),0) -> 0 | H3: Order Completed | J3: Not required | K3: Not required | L3: Completed | M3: Not required | N3: Not started | P3: , , , ,
A4: 4 | B4: Mike, & Carlie | C4: 44276 | D4: 44333 | E4: =(D4-C4)/7 -> 8.1428571 | F4: 44341 | G4: =IF(F4>0,((F4-C4)/7),0) -> 9.2857143 | H4: Order Completed | J4: Completed | K4: Completed | L4: Completed | M4: Completed | N4: Completed | O4: 8AM-12PM | P4: 3466 E SAGEBRUSH ST, , Gilbert, 85296, Arizona
A5: 5 | B5: Mancino, James | C5: 44277 | D5: 44333 | E5: =(D5-C5)/7 -> 8 | F5: 44341 | G5: =IF(F5>0,((F5-C5)/7),0) -> 9.1428571 | H5: Order Completed | J5: Completed | K5: Completed | L5: Completed | M5: Completed | N5: Completed | O5: 12PM-4PM | P5: 3106 E Boot Track Trail, , Gilbert, 85296, Arizona
A6: 6 | B6: Pederson, Erin | C6: 44279 | D6: 44335 | E6: =(D6-C6)/7 -> 8 | F6: 44343 | G6: =IF(F6>0,((F6-C6)/7),0) -> 9.1428571 | H6: Order Completed | J6: Completed | K6: Completed | L6: Completed | M6: Completed | N6: Completed | O6: 8AM-12PM | P6: 7542 East Sundown Court, , Scottsdale, 85250, Arizona
A7: 7 | B7: Larsen, Mike & Leasha | C7: 44284 | D7: 44340 | E7: =(D7-C7)/7 -> 8 | F7: 44361 | G7: =IF(F7>0,((F7-C7)/7),0) -> 11 | H7: Order Completed | J7: Completed | K7: Completed | L7: Completed | M7: Completed | N7: Completed | O7: 8AM-12PM | P7: 8954 E ROSEDALE CIR, , Mesa, , Arizona
A8: 9 | B8: Gusmano, Grayce | C8: 44284 | D8: 44340 | E8: =(D8-C8)/7 -> 8 | F8: 44352 | G8: =IF(F8>0,((F8-C8)/7),0) -> 9.7142857 | H8: Order Completed | J8: Completed | K8: Completed | L8: Completed | M8: Completed | N8: Completed | O8: 8AM-12PM | P8: 16406 E BRADFORD DR, , Fountain Hills, 85268, Arizona
A9: 10 | B9: Berlin, Tony | C9: 44266 | D9: 44322 | E9: =(D9-C9)/7 -> 8 | F9: 44357 | G9: =IF(F9>0,((F9-C9)/7),0) -> 13 | H9: Order Completed | J9: Completed | K9: Completed | L9: Completed | M9: Completed | N9: Completed | O9: 8AM-12PM | P9: 7510 N AJO RD, , Scottsdale, 85258, Arizona
A10: 11 | B10: Herb, & Pattie | C10: 44289 | D10: 44345 | E10: =(D10-C10)/7 -> 8 | G10: =IF(F10>0,((F10-C10)/7),0) -> 0 | H10: Order Completed | J10: Completed | K10: Completed | L10: Completed | M10: Completed | N10: Completed | P10: 10801 E Happy Valley Rd, , Scottsdale, 85255, Arizona
A11: 13 | B11: n/a, Sheila | C11: 44291 | D11: 44347 | E11: =(D11-C11)/7 -> 8 | G11: =IF(F11>0,((F11-C11)/7),0) -> 0 | H11: Order Completed | J11: Completed | K11: Completed | L11: Completed | M11: Completed | N11: Completed | P11: , , , ,
A12: 14 | B12: Sacia, Lisa | C12: 44336 | D12: 44478 | E12: =(D12-C12)/7 -> 20.285714 | F12: 44499 | G12: =IF(F12>0,((F12-C12)/7),0) -> 23.285714 | H12: Order Completed | I12: Notice | J12: Completed | K12: Completed | L12: Completed | M12: Not required | N12: Completed | P12: 10801 E HAPPY VALLEY RD, , Scottsdale, 85255, Arizona
A13: 15 | B13: Maccurly, Bill | C13: 44336 | D13: 44511 | E13: =(D13-C13)/7 -> 25 | G13: =IF(F13>0,((F13-C13)/7),0) -> 0 | H13: Order Completed | J13: Completed | K13: Completed | L13: Not started | M13: Not started | N13: Issue | P13: 41550 N 111TH PL, , Scottsdale, 85262, Arizona
A14: 16 | B14: Steinberg, Riva | C14: 44336 | D14: 44365 | E14: =(D14-C14)/7 -> 4.1428571 | G14: =IF(F14>0,((F14-C14)/7),0) -> 0 | H14: Order Completed | J14: Completed | K14: Completed | L14: Completed | M14: Not started | N14: Completed | P14: 7238 E MONTEBELLO AVE, , Scottsdale, , Arizona
A15: 17 | B15: Gerber, Kyrin | C15: 44336 | D15: 44351 | E15: =(D15-C15)/7 -> 2.1428571 | F15: 44358 | G15: =IF(F15>0,((F15-C15)/7),0) -> 3.1428571 | H15: Order Completed | J15: Completed | K15: Completed | L15: Completed | M15: Completed | N15: Completed | O15: 44785 | P15: 4103 n 64th pl, , Scottsdale, 85251, Arizona
A16: 18 | B16: Dolins, Marcy | C16: 44336 | D16: 44439 | E16: =(D16-C16)/7 -> 14.714286 | G16: =IF(F16>0,((F16-C16)/7),0) -> 0 | H16: Order Completed | J16: Completed | K16: Completed | L16: Completed | M16: Not required | N16: Completed | P16: 5717 E ARROYO RD, , Paradise Valley, , Arizona
A17: 19 | B17: Gralen, MJ | C17: 44336 | D17: 44383 | E17: =(D17-C17)/7 -> 6.7142857 | G17: =IF(F17>0,((F17-C17)/7),0) -> 0 | H17: Order Completed | J17: Completed | K17: Completed | L17: Completed | M17: Not started | N17: Completed | P17: 9112 E MOUNTAIN SPRINGS RD, , Scottsdale, 85255, Arizona
A18: 20 | B18: Gabbay, Nisan | C18: 44295 | D18: 44351 | E18: =(D18-C18)/7 -> 8 | F18: 44365 | G18: =IF(F18>0,((F18-C18)/7),0) -> 10 | H18: Order Completed | J18: Completed | K18: Completed | L18: Completed | M18: Completed | N18: Completed | O18: 44785 | P18: 321 HIDDEN PINES RD, , Del Mar, 92014, California
A19: 21 | B19: Wear, Linda | C19: 44315 | D19: 44371 | E19: =(D19-C19)/7 -> 8 | F19: 44365 | G19: =IF(F19>0,((F19-C19)/7),0) -> 7.1428571 | H19: Order Completed | J19: Completed | K19: Completed | L19: Completed | M19: Not required | N19: Completed | O19: 44785 | P19: 702 JERSEY COURT, , San Diego, 92109, California
A20: 23 | B20: Snader, Michael | C20: 44315 | D20: 44350 | E20: =(D20-C20)/7 -> 5 | F20: 44350 | G20: =IF(F20>0,((F20-C20)/7),0) -> 5 | H20: Order Completed | J20: Completed | K20: Completed | L20: Completed | M20: Completed | N20: Completed | O20: Showroom Pick-up | P20: Showroom, , Scottsdale, , Arizona
A21: 24 | B21: Meyers, Doug | C21: 44333 | D21: 44340 | E21: =(D21-C21)/7 -> 1 | F21: 44342 | G21: =IF(F21>0,((F21-C21)/7),0) -> 1.2857143 | H21: Order Completed | J21: Completed | K21: Completed | L21: Completed | M21: Completed | N21: Completed | O21: 8AM-12PM | P21: 4625 N Launfal Ave, , Phoenix, 85018, Arizona
A22: 26 | B22: Hemstreet, Greg | C22: 44336 | D22: 44414 | E22: =(D22-C22)/7 -> 11.142857 | G22: =IF(F22>0,((F22-C22)/7),0) -> 0 | H22: Order Completed | J22: Completed | K22: Completed | L22: Completed | M22: Completed | N22: Completed | P22: , , , ,
A23: 27 | B23: & Shari, Alan | C23: 44317 | D23: 44373 | E23: =(D23-C23)/7 -> 8 | G23: =IF(F23>0,((F23-C23)/7),0) -> 0 | H23: Order Completed | J23: Completed | K23: Completed | L23: Completed | M23: Not required | N23: Completed | P23: 22100 N 97th, , , 85256, Arizona
A24: 29 | B24: Jarrell, Steven | C24: 44329 | D24: 44384 | E24: =(D24-C24)/7 -> 7.8571429 | G24: =IF(F24>0,((F24-C24)/7),0) -> 0 | H24: Order Completed | J24: Completed | K24: Completed | L24: Completed | M24: Not started | N24: Completed | P24: 18611 W. Marshall Ave., , Litchfield Park,, 85340, Arizona
A25: 30 | B25: Collect, Buffalo | C25: 44340 | D25: 44344 | E25: =(D25-C25)/7 -> 0.57142857 | F25: 44347 | G25: =IF(F25>0,((F25-C25)/7),0) -> 1 | H25: Order Completed | J25: Completed | K25: Completed | L25: Completed | M25: Completed | N25: Completed | O25: 8AM-12PM | P25: 3338 N 62nd Pl, , Scottsdale, 85251, Arizona
A26: 31 | B26: Weintraub, Jeff | C26: 44328 | D26: 44351 | E26: =(D26-C26)/7 -> 3.2857143 | G26: =IF(F26>0,((F26-C26)/7),0) -> 0 | H26: Order Completed | J26: Completed | K26: Completed | L26: Completed | M26: Completed | N26: Completed | P26: 6587 E Running Deer Trail, gate code #1216, Scottsdale, 85266, Arizona
A27: 32 | B27: Shadows, Mountain | C27: 44328 | D27: 44351 | E27: =(D27-C27)/7 -> 3.2857143 | G27: =IF(F27>0,((F27-C27)/7),0) -> 0 | H27: Order Completed | J27: Completed | K27: Completed | L27: Completed | M27: Completed | N27: Completed | P27: , , , ,
A28: 33 | B28: Smith, Jeani | C28: 44328 | D28: 44351 | E28: =(D28-C28)/7 -> 3.2857143 | F28: 44360 | G28: =IF(F28>0,((F28-C28)/7),0) -> 4.5714286 | H28: Order Completed | J28: Completed | K28: Completed | L28: Completed | M28: Not started | N28: Not started | O28: 8AM-12PM | P28: 6950 e cactus wren rd#42, , Scottsdale, 85250, Arizona
A29: 34 | B29: & Chantel, Grady | C29: 44321 | D29: 44377 | E29: =(D29-C29)/7 -> 8 | F29: 44490 | G29: =IF(F29>0,((F29-C29)/7),0) -> 24.142857 | H29: Order Completed | J29: Completed | K29: Completed | L29: Completed | M29: Completed | N29: Completed | P29: 15037 N Scottsdale Rd, unit 120, Scottsdale, 85254, Arizona
A30: 35 | B30: Stone, Lisa | C30: 44330 | D30: 44386 | E30: =(D30-C30)/7 -> 8 | G30: =IF(F30>0,((F30-C30)/7),0) -> 0 | H30: Order Completed | J30: Completed | K30: Completed | L30: Completed | M30: Not started | N30: Not required | P30: 19225 N 98TH, , Scottsdale, 85255, Arizona
A31: 36 | B31: n/a, Florence | C31: 44319 | D31: 44375 | E31: =(D31-C31)/7 -> 8 | G31: =IF(F31>0,((F31-C31)/7),0) -> 0 | H31: Order Completed | I31: Notice | J31: Completed | K31: Completed | L31: Completed | M31: Not required | N31: Completed | P31: 4700 S FULTON BLVD, unit 28, Chandler, 85248, Arizona
A32: 37 | B32: Apache, Rise on | C32: 44340 | D32: 44396 | E32: =(D32-C32)/7 -> 8 | G32: =IF(F32>0,((F32-C32)/7),0) -> 0 | H32: Order Completed | J32: Completed | K32: Completed | L32: Completed | M32: Not started | N32: Completed | P32: 1000 E Apache Blvd, , Tempe, 85281, Arizona
A33: 38 | B33: Foringer, Rebecca | C33: 44317 | D33: 44366 | E33: =(D33-C33)/7 -> 7 | G33: =IF(F33>0,((F33-C33)/7),0) -> 0 | H33: Order Completed | J33: Completed | K33: Completed | L33: Completed | M33: Not started | N33: Completed | P33: 11623 E BLOOMFIELD DR, , Scottsdale, 85259, Arizona
A34: 39 | B34: Grigg, Scott | C34: 44345 | D34: 44378 | E34: =(D34-C34)/7 -> 4.7142857 | G34: =IF(F34>0,((F34-C34)/7),0) -> 0 | H34: Order Completed | J34: Completed | K34: Completed | L34: Completed | M34: Completed | N34: Completed | P34: 3101 E PLEASANT VALLEY, , , , Arizona
A35: 40 | B35: & Nancy, Ken | C35: 44326 | D35: 44382 | E35: =(D35-C35)/7 -> 8 | G35: =IF(F35>0,((F35-C35)/7),0) -> 0 | H35: Order Completed | J35: Completed | K35: Completed | L35: Completed | M35: Not started | N35: Completed | P35: 7755 E San Fernando Dr, Gate Code: #2350, Scottsdale, 85255, Arizona
A36: 41 | B36: Group, BKV | C36: 44335 | D36: 44386 | E36: =(D36-C36)/7 -> 7.2857143 | F36: 44476 | G36: =IF(F36>0,((F36-C36)/7),0) -> 20.142857 | H36: Order Completed | J36: Completed | K36: Completed | L36: Not required | M36: Not required | N36: Completed | P36: 6158 E Horseshoe Road, , Paradise Valley, 85253, Arizona
A37: 44 | B37: Mansueto, Lisa (Nancy) | C37: 44342 | D37: 44398 | E37: =(D37-C37)/7 -> 8 | G37: =IF(F37>0,((F37-C37)/7),0) -> 0 | H37: Order Completed | J37: Completed | K37: Completed | L37: Completed | M37: Not started | N37: Not required | P37: 1709 W Glacier Way,, gate code #0615, Chandler, 85248, Arizona
A38: 45 | B38: & Chris, Tim | C38: 44353 | D38: 44408 | E38: =(D38-C38)/7 -> 7.8571429 | G38: =IF(F38>0,((F38-C38)/7),0) -> 0 | H38: Order Completed | J38: Completed | K38: Completed | L38: Completed | M38: Not started | N38: Completed | P38: 5508 S 106TH PLACE, , Mesa, 85212, Arizona
A39: 46 | B39: Gusmano, Grayce | C39: 44353 | D39: 44365 | E39: =(D39-C39)/7 -> 1.7142857 | G39: =IF(F39>0,((F39-C39)/7),0) -> 0 | H39: Order Completed | J39: Not required | K39: Not required | L39: Completed | M39: Not required | N39: Not required | P39: 16406 E BRADFORD DR, , Fountain Hills, 85268, Arizona
A40: 47 | B40: Evans, John & Susan | C40: 44355 | D40: 44417 | E40: =(D40-C40)/7 -> 8.8571429 | G40: =IF(F40>0,((F40-C40)/7),0) -> 0 | H40: Order Completed | J40: Completed | K40: Completed | L40: Completed | M40: Not started | N40: Completed | P40: 10666 E Yearling Dr, , Scottsdale, , Arizona
A41: 48 | B41: Foxman, Ted | C41: 44355 | D41: 44364 | E41: =(D41-C41)/7 -> 1.2857143 | G41: =IF(F41>0,((F41-C41)/7),0) -> 0 | H41: Order Completed | J41: Completed | K41: Completed | L41: Completed | M41: Not required | N41: Completed | P41: 3950 Royal Oak Pl, , Encino, 91436, California
A42: 49 | B42: SIMMONS, JEFFERSON | C42: 44357 | D42: 44386 | E42: =(D42-C42)/7 -> 4.1428571 | G42: =IF(F42>0,((F42-C42)/7),0) -> 0 | H42: Order Completed | J42: Completed | K42: Completed | L42: Completed | M42: Not started | N42: Completed | P42: 4432 E MONTECITO AVE, , Phoenix, 85018, Arizona
A43: 50 | B43: MEYER, ERIC | C43: 44357 | D43: 44386 | E43: =(D43-C43)/7 -> 4.1428571 | G43: =IF(F43>0,((F43-C43)/7),0) -> 0 | H43: Order Completed | J43: Completed | K43: Completed | L43: Completed | M43: Not required | N43: Completed | P43: 3732 E ROBIN LN, , Phoenix, , Arizona
A44: 51 | B44: BOSWORTH, DAVID | C44: 44360 | D44: 44409 | E44: =(D44-C44)/7 -> 7 | G44: =IF(F44>0,((F44-C44)/7),0) -> 0 | H44: Order Completed | J44: Completed | K44: Completed | L44: Completed | M44: Not started | N44: Completed | P44: 4209 N 18TH PLACE, , Phoenix, 85016, Arizona
A45: 52 | B45: VOS, NAIDU | C45: 44362 | D45: 44396 | E45: =(D45-C45)/7 -> 4.8571429 | G45: =IF(F45>0,((F45-C45)/7),0) -> 0 | H45: Order Completed | J45: Completed | K45: Completed | L45: Completed | M45: Not required | N45: Completed | P45: 10604 N 60th Pl, , SCOTTSDALE, 85254, Arizona
A46: 53 | B46: KOUROUGLOS, JENNIFER | C46: 44363 | D46: 44417 | E46: =(D46-C46)/7 -> 7.7142857 | G46: =IF(F46>0,((F46-C46)/7),0) -> 0 | H46: Order Completed | J46: Completed | K46: Completed | L46: Completed | M46: Not required | N46: Completed | P46: 8600 N CABALLO CIR, , PARADISE VALLEY, , Arizona
A47: 54 | B47: ROMO, ROBERTO & GEORGETTE | C47: 44363 | D47: 44399 | E47: =(D47-C47)/7 -> 5.1428571 | G47: =IF(F47>0,((F47-C47)/7),0) -> 0 | H47: Order Completed | J47: Completed | K47: Completed | L47: Completed | M47: Not started | N47: Completed | P47: 39935 N 98TH WAY, , SCOTTSDALE, 85262, Arizona
A48: 55 | B48: MARSH, BETH | C48: 44368 | D48: 44402 | E48: =(D48-C48)/7 -> 4.8571429 | G48: =IF(F48>0,((F48-C48)/7),0) -> 0 | H48: Order Completed | J48: Completed | K48: Completed | L48: Completed | M48: Not started | N48: Completed | P48: 4714 E VIA LOS CABALLOS, , PHOENIX, 85028, Arizona
A49: 56 | B49: Satz, Marsha | C49: 44375 | D49: 44926 | E49: =(D49-C49)/7 -> 78.714286 | F49: 44747 | G49: =IF(F49>0,((F49-C49)/7),0) -> 53.142857 | H49: Order Completed | I49: Notice | J49: Completed | K49: Completed | L49: Cut End | M49: Not Required | N49: Completed | P49: 12374 E LA JUNTA RD, , Scottsdale, , Arizona
A50: 57 | B50: DUNN, ANDREW & GINA | C50: 44378 | D50: 44444 | E50: =(D50-C50)/7 -> 9.4285714 | G50: =IF(F50>0,((F50-C50)/7),0) -> 0 | H50: Order Completed | J50: Completed | K50: Completed | L50: Completed | M50: Not required | N50: Completed | P50: 10202 N 58th St, , PARADISE VALLEY, 85253, Arizona
A51: 58 | B51: POTHIER, SHAWNI | C51: 44378 | D51: 44437 | E51: =(D51-C51)/7 -> 8.4285714 | G51: =IF(F51>0,((F51-C51)/7),0) -> 0 | H51: Order Completed | J51: Completed | K51: Completed | L51: Completed | M51: Not started | N51: Completed | P51: 4811 E CAMEL HEAD DR, , PHOENIX, 85018, Arizona
A52: 59 | B52: PHAM, THUY | C52: 44378 | D52: 44438 | E52: =(D52-C52)/7 -> 8.5714286 | G52: =IF(F52>0,((F52-C52)/7),0) -> 0 | H52: Order Completed | J52: Completed | K52: Completed | L52: Completed | M52: Not required | N52: Completed | P52: 9332 N 71ST ST, , PARADISE VALLEY, 85253, Arizona
A53: 60 | B53: SLACK, KATIE | C53: 44378 | D53: 44454 | E53: =(D53-C53)/7 -> 10.857143 | F53: 44533 | G53: =IF(F53>0,((F53-C53)/7),0) -> 22.142857 | H53: Order Completed | I53: Urgent | J53: Not required | K53: Not required | L53: Not required | M53: Not required | N53: Completed | P53: 3732 E Dunlap Ave, , Phoenix, 85028, Arizona
A54: 61 | B54: JAIME ROSE INTERIOR, ( SUSAN BENTZ ) | C54: 44383 | D54: 44428 | E54: =(D54-C54)/7 -> 6.4285714 | G54: =IF(F54>0,((F54-C54)/7),0) -> 0 | H54: Order Completed | J54: Completed | K54: Completed | L54: Completed | M54: Not required | N54: Completed | P54: 6866 E CACTUS WREN RD, , PARADISE VALLEY, 85253, Arizona
A55: 62 | B55: TULI, PRITPAL | C55: 44383 | D55: 44489 | E55: =(D55-C55)/7 -> 15.142857 | F55: 44488 | G55: =IF(F55>0,((F55-C55)/7),0) -> 15 | H55: Order Completed | I55: Urgent | J55: Completed | K55: Completed | L55: Completed | M55: Not required | N55: Completed | P55: 6501 N 40TH PL, , PARADISE VALLEY, 85253, Arizona
A56: 63 | B56: BELL, BRITTANY | C56: 44389 | D56: 44436 | E56: =(D56-C56)/7 -> 6.7142857 | G56: =IF(F56>0,((F56-C56)/7),0) -> 0 | H56: Order Completed | J56: Completed | K56: Completed | L56: Completed | M56: Not required | N56: Completed | P56: 8108 E Desert Cove Ave, , SCOTTSDALE, 85260, Arizona
A57: 64 | B57: DECARLO, KACIE & CARLO | C57: 44390 | D57: 44437 | E57: =(D57-C57)/7 -> 6.7142857 | G57: =IF(F57>0,((F57-C57)/7),0) -> 0 | H57: Order Completed | J57: Completed | K57: Completed | L57: Completed | M57: Not required | N57: Completed | P57: 7043 N LONGLOOK RD, , PARADISE VALLEY, 85253, Arizona
A58: 65 | B58: MURPHY, DENICE | C58: 44392 | D58: 44459 | E58: =(D58-C58)/7 -> 9.5714286 | G58: =IF(F58>0,((F58-C58)/7),0) -> 0 | H58: Order Completed | I58: Urgent | J58: Completed | K58: Completed | L58: Completed | M58: Not required | N58: Completed | P58: 2796 W CARAVEO PL, , PEORIA, , Arizona
A59: 66 | B59: ROSS, PAUL | C59: 44394 | D59: 44450 | E59: =(D59-C59)/7 -> 8 | G59: =IF(F59>0,((F59-C59)/7),0) -> 0 | H59: Order Completed | J59: Completed | K59: Completed | L59: Completed | M59: Not required | N59: Completed | P59: 15417 E PALATIAL CIR, , FOUNTAIN HILLS, , Arizona
A60: 67 | B60: GROTHAUS, SHELLEY | C60: 44396 | D60: 44464 | E60: =(D60-C60)/7 -> 9.7142857 | F60: 44474 | G60: =IF(F60>0,((F60-C60)/7),0) -> 11.142857 | H60: Order Completed | J60: Completed | K60: Completed | L60: Completed | M60: Not required | N60: Completed | P60: 10801 E Happy Valley Rd, lot #66, SCOTTSDALE, 85255, Arizona
A61: 68 | B61: LEWIS, JUNE | C61: 44399 | D61: 44422 | E61: =(D61-C61)/7 -> 3.2857143 | G61: =IF(F61>0,((F61-C61)/7),0) -> 0 | H61: Order Completed | J61: Completed | K61: Completed | L61: Not required | M61: Not required | N61: Not started | P61: 7215 E SILVERSTONE DR, , SCOTTSDALE, 85255, Arizona
A62: 69 | B62: GRANITE, TOM & ROSANNE | C62: 44399 | D62: 44449 | E62: =(D62-C62)/7 -> 7.1428571 | F62: 44558 | G62: =IF(F62>0,((F62-C62)/7),0) -> 22.714286 | H62: Order Completed | I62: Urgent | J62: Completed | K62: Completed | L62: Completed | M62: Not required | N62: Completed | P62: 17934 N 100TH ST, , scottsdale, 85255, Arizona
A63: 70 | B63: MK, DESIGN ONE | C63: 44399 | D63: 44422 | E63: =(D63-C63)/7 -> 3.2857143 | G63: =IF(F63>0,((F63-C63)/7),0) -> 0 | H63: Order Completed | J63: Not required | K63: Not required | L63: Not required | M63: Not required | N63: Completed | P63: , , , ,
A64: 72 | B64: PETERS, HEIDI | C64: 44401 | D64: 44614 | E64: =(D64-C64)/7 -> 30.428571 | F64: 44628 | G64: =IF(F64>0,((F64-C64)/7),0) -> 32.428571 | H64: Order Completed | I64: Notice | J64: Completed | K64: Completed | L64: Completed | M64: Not required | N64: Completed | P64: 4280 RIDGE RD, , STEVENSVILLE, 49127, Michigan
A65: 73 | B65: Mcquarie, Brandon | C65: 44404 | D65: 44410 | E65: =(D65-C65)/7 -> 0.85714286 | G65: =IF(F65>0,((F65-C65)/7),0) -> 0 | H65: Order Completed | J65: Not started | K65: Not started | L65: Completed | M65: Not required | N65: Not required | P65: Showroom, , , , Arizona
A66: 74 | B66: WARZYNSKI, KEN | C66: 44404 | D66: 44440 | E66: =(D66-C66)/7 -> 5.1428571 | G66: =IF(F66>0,((F66-C66)/7),0) -> 0 | H66: Order Completed | J66: Completed | K66: Completed | L66: Completed | M66: Not required | N66: Completed | P66: 6640 E JOSHUA TREE LN, , PARADISE VALLEY, , Arizona
A67: 75 | B67: MUELLER, JUDY | C67: 44404 | D67: 44418 | E67: =(D67-C67)/7 -> 2 | G67: =IF(F67>0,((F67-C67)/7),0) -> 0 | H67: Order Completed | J67: Completed | K67: Completed | L67: Completed | M67: Not required | N67: Not started | P67: 679 ROLLING HILLS RD, , VISTA, 92081, California
A68: 76 | B68: MARSH, BETH | C68: 44417 | D68: 44421 | E68: =(D68-C68)/7 -> 0.57142857 | G68: =IF(F68>0,((F68-C68)/7),0) -> 0 | H68: Order Completed | I68: Notice | J68: Not required | K68: Completed | L68: Not started | M68: Not required | N68: Not required | P68: 4714 E VIA LOS CABALLOS, , PHOENIX, 85028, Arizona
A69: 77 | B69: Evans, John & Susan | C69: 44417 | D69: 44421 | E69: =(D69-C69)/7 -> 0.57142857 | G69: =IF(F69>0,((F69-C69)/7),0) -> 0 | H69: Order Completed | J69: Not required | K69: Not required | L69: Not required | M69: Not required | N69: Completed | P69: 10666 E Yearling Dr, , Scottsdale, , Arizona
A70: 78 | B70: PRUETT, HEATHER | C70: 44417 | D70: 44464 | E70: =(D70-C70)/7 -> 6.7142857 | F70: 44485 | G70: =IF(F70>0,((F70-C70)/7),0) -> 9.7142857 | H70: Order Completed | I70: Urgent | J70: Completed | K70: Completed | L70: Completed | M70: Not required | N70: Completed | P70: 10619 Lakeside Mill Ct, , Missouri City, 77459, Texas
A71: 79 | B71: PALEJWALA, NEAL | C71: 44418 | D71: 44478 | E71: =(D71-C71)/7 -> 8.5714286 | F71: 44478 | G71: =IF(F71>0,((F71-C71)/7),0) -> 8.5714286 | H71: Order Completed | I71: Urgent | J71: Completed | K71: Completed | L71: Completed | M71: Not required | N71: Completed | P71: 10569 N 106TH PL, , SCOTTSDALE, 85258, Arizona
A72: 80 | B72: VALLA, KEN | C72: 44418 | D72: 44440 | E72: =(D72-C72)/7 -> 3.1428571 | G72: =IF(F72>0,((F72-C72)/7),0) -> 0 | H72: Order Completed | I72: Urgent | J72: Completed | K72: Completed | L72: Completed | M72: Not required | N72: Completed | P72: 7755 E San Fernando Dr, , Scottsdale, 85255, Arizona
A73: 81 | B73: HAMEL, DONNA | C73: 44418 | D73: 44477 | E73: =(D73-C73)/7 -> 8.4285714 | F73: 44477 | G73: =IF(F73>0,((F73-C73)/7),0) -> 8.4285714 | H73: Order Completed | J73: Completed | K73: Completed | L73: Completed | M73: Not required | N73: Completed | P73: , , , ,
A74: 82 | B74: BEAIRSTO, LINDSEY | C74: 44419 | D74: 44449 | E74: =(D74-C74)/7 -> 4.2857143 | G74: =IF(F74>0,((F74-C74)/7),0) -> 0 | H74: Order Completed | J74: Completed | K74: Completed | L74: Not required | M74: Not required | N74: Completed | P74: lovelinz2@yahoo.com, , PHOENIX, 85018, Arizona
A75: 83 | B75: LONGO, JASON | C75: 44419 | D75: 44475 | E75: =(D75-C75)/7 -> 8 | F75: 44502 | G75: =IF(F75>0,((F75-C75)/7),0) -> 11.857143 | H75: Order Completed | I75: Notice | J75: Completed | K75: Completed | L75: Completed | M75: Completed | N75: Completed | P75: , , , ,
A76: 84 | B76: KIRK, MELISSA | C76: 44420 | D76: 44483 | E76: =(D76-C76)/7 -> 9 | F76: 44491 | G76: =IF(F76>0,((F76-C76)/7),0) -> 10.142857 | H76: Order Completed | I76: Notice | J76: Completed | K76: Completed | L76: Completed | M76: Not required | N76: Completed | P76: 16235 N 62ND PL SCOTTSDALE, , SCOTTSDALE, 85254, Arizona
A77: 85 | B77: WISSAM, TANIA | C77: 44426 | D77: 44469 | E77: =(D77-C77)/7 -> 6.1428571 | F77: 44482 | G77: =IF(F77>0,((F77-C77)/7),0) -> 8 | H77: Order Completed | J77: Completed | K77: Completed | L77: Completed | M77: Not required | N77: Completed | P77: 1330 E HORSESHOE DR, GATE CODE #2000, CHANDLER, 85249, Arizona
A78: 86 | B78: FOXMAN, TED | C78: 44428 | D78: 44439 | E78: =(D78-C78)/7 -> 1.5714286 | F78: 44517 | G78: =IF(F78>0,((F78-C78)/7),0) -> 12.714286 | H78: Order Completed | J78: Not required | K78: Not required | L78: Completed | M78: Not required | N78: Not required | P78: 3950 Royal Oak Pl, , Encino, , California
A79: 87 | B79: 3rd Avenue Lofts, FRANK NARDI | C79: 44432 | D79: 44474 | E79: =(D79-C79)/7 -> 6 | F79: 44483 | G79: =IF(F79>0,((F79-C79)/7),0) -> 7.2857143 | H79: Order Completed | I79: Urgent | J79: Completed | K79: Completed | L79: Completed | M79: Not required | N79: Completed | P79: 7301 E 3rd Ave, , scottsdale, 85251, Arizona
A80: 88 | B80: KEITH, GINA | C80: 44438 | D80: 44502 | E80: =(D80-C80)/7 -> 9.1428571 | F80: 44503 | G80: =IF(F80>0,((F80-C80)/7),0) -> 9.2857143 | H80: Order Completed | I80: Urgent | J80: Completed | K80: Completed | L80: Completed | M80: Not required | N80: Completed | P80: 9000 E BRAHMA RD, , SCOTTSDALE, , Arizona
A81: 89 | B81: CLEMENTS, KATHERINE | C81: 44440 | D81: 44510 | E81: =(D81-C81)/7 -> 10 | F81: 44529 | G81: =IF(F81>0,((F81-C81)/7),0) -> 12.714286 | H81: Order Completed | I81: Notice | J81: Completed | K81: Completed | L81: Completed | M81: Completed | N81: Completed | P81: 12121 E ALTADENA DR, , SCOTTSDALE, 85259, Arizona
A82: 90 | B82: QORRI, TONY | C82: 44441 | D82: 44499 | E82: =(D82-C82)/7 -> 8.2857143 | F82: 44496 | G82: =IF(F82>0,((F82-C82)/7),0) -> 7.8571429 | H82: Order Completed | I82: Notice | J82: Completed | K82: Completed | L82: Completed | M82: Not required | N82: Completed | P82: 8741 E HAZELWOOD ST, , SCOTTSDALE, , Arizona
A83: 91 | B83: BRICK, HOPE | C83: 44441 | D83: 44499 | E83: =(D83-C83)/7 -> 8.2857143 | F83: 44498 | G83: =IF(F83>0,((F83-C83)/7),0) -> 8.1428571 | H83: Order Completed | I83: Urgent | J83: Completed | K83: Completed | L83: Completed | M83: Not required | N83: Completed | P83: 11064 E BENT TREE DR, , SCOTTSDALE, ,
A84: 92 | B84: GREGG, SUZI | C84: 44441 | D84: 44449 | E84: =(D84-C84)/7 -> 1.1428571 | G84: =IF(F84>0,((F84-C84)/7),0) -> 0 | H84: Order Completed | I84: Urgent | J84: Completed | K84: Completed | L84: Completed | M84: Not required | N84: Not required | P84: , , , ,
A85: 93 | B85: KURTH & MICHELLE, MOULTON | C85: 44445 | D85: 44513 | E85: =(D85-C85)/7 -> 9.7142857 | F85: 44511 | G85: =IF(F85>0,((F85-C85)/7),0) -> 9.4285714 | H85: Order Completed | J85: Completed | K85: Completed | L85: Completed | M85: Completed | N85: Completed | O85: 44625 | P85: 30600 N PIMA RD # 82, , SCOTTSDALE, 85266, Arizona
A86: 94 | B86: GROSVENOR, DAVID | C86: 44446 | D86: 44499 | E86: =(D86-C86)/7 -> 7.5714286 | F86: 44505 | G86: =IF(F86>0,((F86-C86)/7),0) -> 8.4285714 | H86: Order Completed | J86: Completed | K86: Completed | L86: Not required | M86: Not required | N86: Completed | P86: 4715 W Horizon Ridge Drive, , Marana, 85658, Arizona
A87: 95 | B87: STOPPS, CHRIS | C87: 44448 | D87: 44506 | E87: =(D87-C87)/7 -> 8.2857143 | F87: 44510 | G87: =IF(F87>0,((F87-C87)/7),0) -> 8.8571429 | H87: Order Completed | J87: Completed | K87: Completed | L87: Completed | M87: Not required | N87: Completed | P87: 10040 E HAPPY VALLEY, UNIT # 478, SCOTTSDALE, 85255, Arizona
A88: 96 | B88: RAMSEY, KATIE | C88: 44448 | D88: 44513 | E88: =(D88-C88)/7 -> 9.2857143 | F88: 44534 | G88: =IF(F88>0,((F88-C88)/7),0) -> 12.285714 | H88: Order Completed | J88: Completed | K88: Completed | L88: Completed | M88: Not required | N88: Completed | P88: 27214 N 71ST PL, , scottsdale, 85266, Arizona
A89: 97 | B89: TEHRANCHI, MANI | C89: 44452 | D89: 44457 | E89: =(D89-C89)/7 -> 0.71428571 | F89: 44457 | G89: =IF(F89>0,((F89-C89)/7),0) -> 0.71428571 | H89: Order Completed | I89: Urgent | J89: Completed | K89: Completed | L89: Completed | M89: Not required | N89: Not started | P89: 39029 n alister mckenzie dr, , SCOTTSDALE, 85262, Arizona
A90: 98 | B90: WILLIAMS, BRENT | C90: 44452 | D90: 44510 | E90: =(D90-C90)/7 -> 8.2857143 | F90: 44530 | G90: =IF(F90>0,((F90-C90)/7),0) -> 11.142857 | H90: Order Completed | J90: Completed | K90: Completed | L90: Completed | M90: Not required | N90: Completed | P90: 39622 C.B. MacDonald, , SCOTTSDALE, 85262, Arizona
A91: 99 | B91: STOWERS, BELINDA | C91: 44455 | D91: 44511 | E91: =(D91-C91)/7 -> 8 | F91: 44504 | G91: =IF(F91>0,((F91-C91)/7),0) -> 7 | H91: Order Completed | I91: Urgent | J91: Completed | K91: Completed | L91: Completed | M91: Not required | N91: Completed | P91: 6999 E BLUE SKY DR, , SCOTTSDALE, 85266, Arizona
A92: 100 | B92: STOWERS, BELINDA | C92: 44455 | D92: 44511 | E92: =(D92-C92)/7 -> 8 | F92: 44518 | G92: =IF(F92>0,((F92-C92)/7),0) -> 9 | H92: Order Completed | J92: Completed | K92: Completed | L92: Completed | M92: Not required | N92: Completed | P92: 7186 TEM PL, , CARLSBAD, , California
A93: 101 | B93: MOUNTAIN SHADOWS, MOUNTAIN SHADOWS | C93: 44456 | D93: 44520 | E93: =(D93-C93)/7 -> 9.1428571 | F93: 44494 | G93: =IF(F93>0,((F93-C93)/7),0) -> 5.4285714 | H93: Order Completed | I93: Notice | J93: Completed | K93: Completed | L93: Completed | M93: Not required | N93: Completed | P93: 5445 E LINCOLN DR, , PARADISE VALLEY, , Arizona
A94: 102 | B94: EVANS, JOHN& SUSAN | C94: 44456 | D94: 44511 | E94: =(D94-C94)/7 -> 7.8571429 | F94: 44501 | G94: =IF(F94>0,((F94-C94)/7),0) -> 6.4285714 | H94: Order Completed | J94: Completed | K94: Completed | L94: Not required | M94: Not required | N94: Completed | P94: 10666 E YEARLING DR, , SCOTTSDALE, , Arizona
A95: 103 | B95: LANDRO, JENNIFER | C95: 44459 | D95: 44489 | E95: =(D95-C95)/7 -> 4.2857143 | F95: 44489 | G95: =IF(F95>0,((F95-C95)/7),0) -> 4.2857143 | H95: Order Completed | J95: Completed | K95: Completed | L95: Completed | M95: Not required | N95: Completed | P95: 7430 E MONTRO WAY, , SCOTTSDALE, , Arizona
A96: 104 | B96: SHAW, RYAN & JODI | C96: 44459 | D96: 44499 | E96: =(D96-C96)/7 -> 5.7142857 | F96: 44492 | G96: =IF(F96>0,((F96-C96)/7),0) -> 4.7142857 | H96: Order Completed | J96: Completed | K96: Completed | L96: Completed | M96: Not required | N96: Completed | P96: 7415 S RITA LN, , TEMPE, , Arizona
